Workbook

Sheet Web_of_Science_20251015 
A1: title | B1: DOI | C1: display_names | D1: OA_URLs | E1: Number of Funders Indicated by Paper | F1: Number of Correct Matches | G1: Number of Wrong Matches | H1: Coder | I1: Avg. Recall | J1: Avg error rate | K1: Hit rate | L1: Avg. Precision | M1: Paper level recall | N1: Paper level error rate | O1: Paper level hit rate | P1: Paper level precision | Q1: Paper is complete hit
A2: Integral-Type Fractional Equations with a Proportional Riemann-Liouville Derivative | B2: https://doi.org/10.1155/2021/9990439 | C2: Prince Sultan University; PSU | D2: https://openalex.org/funders/f4320327702 | E2: =sample_20250925!E2 -> 1 | F2: =IF(sample_20250925!$C2=C2,sample_20250925!F2, NA()) -> 1 | G2: =IF(sample_20250925!$C2=$C2,sample_20250925!G2, NA()) -> 0 | H2: Jacob | I2: =IFERROR(__xludf.DUMMYFUNCTION("AVERAGE(FILTER(M2:M250,ISNUMBER(M2:M250)))"),0.7796877568754548) -> 0.77968776 | J2: =IFERROR(__xludf.DUMMYFUNCTION("AVERAGE(FILTER(N2:N250,ISNUMBER(N2:N250)))"),0.03572485430443579) -> 0.035724854 | K2: =IFERROR(__xludf.DUMMYFUNCTION("AVERAGE(FILTER(O2:O250,ISNUMBER(O2:O250)))"),0.9799196787148594) -> 0.97991968 | L2: =IFERROR(__xludf.DUMMYFUNCTION("AVERAGE(FILTER(P2:P250,ISNUMBER(P2:P250)))"),0.9626349527665317) -> 0.96263495 | M2: =F2/E2 -> 1 | N2: =G2/E2 -> 0 | O2: =IFERROR(__xludf.DUMMYFUNCTION("INT(FILTER(GT(F2,0),ISNUMBER(F2)))"),1.0) -> 1 | P2: =F2/(F2+G2) -> 1 | Q2: =IFERROR(__xludf.DUMMYFUNCTION("INT(FILTER(EQ(E2,F2),ISNUMBER(E2),ISNUMBER(F2)))"),1.0) -> 1
A3: Meta-analysis of day treatment and contingency-management dismantling research: Birmingham homeless cocaine studies (1990-2006) | B3: https://doi.org/10.1037/0022-006X.75.5.823 | C3: National Institute on Alcohol Abuse and Alcoholism; NIH National Institute on Alcohol Abuse and Alcoholism; The National Institute on Alcohol Abuse and Alcoholism; NIAAA; National Institute on Alcohol Abuse & Alcoholism || National Institute on Drug Abuse; NIDA; The National Institute on Drug Abuse; Instituto Nacional sobre el Abuso de Drogas; Instituto Nacional sobre el Abuso de Drogas de Estados Unidos || National Institute on Alcohol Abuse and Alcoholism; NIH National Institute on Alcohol Abuse and Alcoholism; The National Institute on Alcohol Abuse and Alcoholism; NIAAA; National Institute on Alcohol Abuse & Alcoholism || National Institute on Drug Abuse; NIDA; The National Institute on Drug Abuse; Instituto Nacional sobre el Abuso de Drogas; Instituto Nacional sobre el Abuso de Drogas de Estados Unidos | D3: https://openalex.org/funders/f4320337347 || https://openalex.org/funders/f4320337330 | E3: =sample_20250925!E3 -> 1 | F3: =IF(sample_20250925!$C3=C3,sample_20250925!F3, NA()) -> 1 | G3: =IF(sample_20250925!$C3=$C3,sample_20250925!G3, NA()) -> 0 | H3: Jacob | I3: Recall | J3: Error rate | K3: Complete hits | L3: Precision | M3: =F3/E3 -> 1 | N3: =G3/E3 -> 0 | O3: =IFERROR(__xludf.DUMMYFUNCTION("INT(FILTER(GT(F3,0),ISNUMBER(F3)))"),1.0) -> 1 | P3: =F3/(F3+G3) -> 1 | Q3: =IFERROR(__xludf.DUMMYFUNCTION("INT(FILTER(EQ(E3,F3),ISNUMBER(E3),ISNUMBER(F3)))"),1.0) -> 1
A4: MR Imaging-guided Percutaneous Cryoablation of the Prostate in an Animal Model: In Vivo Imaging of Cryoablation-induced Tissue Necrosis with Immediate Histopathologic Correlation | B4: https://doi.org/10.1016/j.jvir.2008.10.030 | C4: National Center for Research Resources; NCRR || National Cancer Institute; NCI; Instituto Nacional del Cáncer || National Center for Research Resources; NCRR | D4: https://openalex.org/funders/f4320337351 || https://openalex.org/funders/f4320337375 | E4: =sample_20250925!E4 -> 2 | F4: =IF(sample_20250925!$C4=C4,sample_20250925!F4, NA()) -> 2 | G4: =IF(sample_20250925!$C4=$C4,sample_20250925!G4, NA()) -> 0 | H4: Jacob | I4: =IFERROR(__xludf.DUMMYFUNCTION("SUM(FILTER(F2:F250,ISNUMBER(F2:F250)))/SUM(FILTER(E2:E250,ISNUMBER(F2:F250)))"),0.7300613496932515) -> 0.73006135 | J4: =IFERROR(__xludf.DUMMYFUNCTION("SUM(FILTER(G2:G250,ISNUMBER(G2:G250)))/SUM(FILTER(E2:E250,ISNUMBER(G2:G250)))"),0.029141104294478526) -> 0.029141104 | K4: =IFERROR(__xludf.DUMMYFUNCTION("AVERAGE(FILTER(Q2:Q250,ISNUMBER(Q2:Q250)))"),0.5418502202643172) -> 0.54185022 | L4: =IFERROR(__xludf.DUMMYFUNCTION("SUM(FILTER(F2:F250,ISNUMBER(F2:F250)))/(SUM(FILTER(F2:F250,ISNUMBER(F2:F250)))+SUM(FILTER(G2:G250,ISNUMBER(F2:F250))))"),0.9616161616161616) -> 0.96161616 | M4: =F4/E4 -> 1 | N4: =G4/E4 -> 0 | O4: =IFERROR(__xludf.DUMMYFUNCTION("INT(FILTER(GT(F4,0),ISNUMBER(F4)))"),1.0) -> 1 | P4: =F4/(F4+G4) -> 1 | Q4: =IFERROR(__xludf.DUMMYFUNCTION("INT(FILTER(EQ(E4,F4),ISNUMBER(E4),ISNUMBER(F4)))"),1.0) -> 1
A5: Enzymatic Hydrolysis of Softwood Derived Paper Sludge by an In Vitro Recombinant Cellulase Cocktail for the Production of Fermentable Sugars | B5: https://doi.org/10.3390/catal10070775 | C5: Department of Science and Technology, Republic of South Africa; DST || National Research Foundation; NRF || Rhodes University; RU; ru.ac.za; Rhodes University College || Universiteit Stellenbosch; Stellenbosch University; US | D5: https://openalex.org/funders/f4320320671 || https://openalex.org/funders/f4320322663 || https://openalex.org/funders/f4320320691 || https://openalex.org/funders/f4320320683 | E5: =sample_20250925!E5 -> 4 | F5: 4 | G5: 0 | H5: Jacob | M5: =F5/E5 -> 1 | N5: =G5/E5 -> 0 | O5: =IFERROR(__xludf.DUMMYFUNCTION("INT(FILTER(GT(F5,0),ISNUMBER(F5)))"),1.0) -> 1 | P5: =F5/(F5+G5) -> 1 | Q5: =IFERROR(__xludf.DUMMYFUNCTION("INT(FILTER(EQ(E5,F5),ISNUMBER(E5),ISNUMBER(F5)))"),1.0) -> 1
A6: Metal nanoparticle-doped epoxy resin to suppress surface charge accumulation on insulators under DC voltage | B6: https://doi.org/10.1088/1361-6528/ab8b91 | C6: National Key Research and Development Program of China; NKRDPC; Special Fund for the National Key Research and Development Plan; 973 Program; National Basic Research Program of China; NKPs; National Plan on Key Basic Research and Development; National Program on Key Basic Research Project (973 Program); National Key Research and Development of China; 重点基础研究发展计划; National Key R&D Program of China; National Key R&D Programmes of China; China's National Key R&D Programmes; National Basic Research Program; National Basic Research Program of China (973 Program); China National Key Research and Development Plan Project; National Key Research and Development Program | D6: https://openalex.org/funders/f4320335777 | E6: =sample_20250925!E6 -> 1 | F6: =IF(sample_20250925!$C6=C6,sample_20250925!F6, NA()) -> 1 | G6: =IF(sample_20250925!$C6=$C6,sample_20250925!G6, NA()) -> 0 | H6: Jacob | M6: =F6/E6 -> 1 | N6: =G6/E6 -> 0 | O6: =IFERROR(__xludf.DUMMYFUNCTION("INT(FILTER(GT(F6,0),ISNUMBER(F6)))"),1.0) -> 1 | P6: =F6/(F6+G6) -> 1 | Q6: =IFERROR(__xludf.DUMMYFUNCTION("INT(FILTER(EQ(E6,F6),ISNUMBER(E6),ISNUMBER(F6)))"),1.0) -> 1
A7: IJCARS-IPCAI 2021 Special Issue: Information Processing for Computer-Assisted Interventions, 12th International Conference 2021-Part 1 | B7: https://doi.org/10.1007/s11548-021-02401-5 | C7: German Rectors' Conference; HRK; Westdeutsche Rektorenkonferenz; Hochschulrektorenkonferenz | D7: https://openalex.org/institutions/i4210095069 | E7: =sample_20250925!E7 -> 1 | F7: =IF(sample_20250925!$C7=C7,sample_20250925!F7, NA()) -> 1 | G7: =IF(sample_20250925!$C7=$C7,sample_20250925!G7, NA()) -> 0 | H7: Jacob | M7: =F7/E7 -> 1 | N7: =G7/E7 -> 0 | O7: =IFERROR(__xludf.DUMMYFUNCTION("INT(FILTER(GT(F7,0),ISNUMBER(F7)))"),1.0) -> 1 | P7: =F7/(F7+G7) -> 1 | Q7: =IFERROR(__xludf.DUMMYFUNCTION("INT(FILTER(EQ(E7,F7),ISNUMBER(E7),ISNUMBER(F7)))"),1.0) -> 1
A8: Identification and partial characterization of a Salp15 homolog from Ixodes ricinus | B8: https://doi.org/10.1016/j.ttbdis.2013.12.004 | C8: European Commission; Europeiska kommissionen; Ευρωπαϊκής Επιτροπής; Comisia Europeană; Europese Commissie; Euroopa Komisjoni; Eiropas Komisiju; Euroopan komission; Europskoj komisiji; EU; Choimisiúin Eorpaigh; EU-Kommissionen; Evropski komisiji; EC; Comisión Europea; Europos Komisijos; Europäische Kommission; La Commissione europea; Evropské komise; Comissão Europeia; Európskej komisii; Европейската комисия; Európai Bizottságról; Komisja Europejska; Commissione europea; European Union; Commission européenne | D8: https://openalex.org/funders/f4320320300 | E8: =sample_20250925!E8 -> 1 | F8: 1 | G8: 0 | H8: Jacob | M8: =F8/E8 -> 1 | N8: =G8/E8 -> 0 | O8: =IFERROR(__xludf.DUMMYFUNCTION("INT(FILTER(GT(F8,0),ISNUMBER(F8)))"),1.0) -> 1 | P8: =F8/(F8+G8) -> 1 | Q8: =IFERROR(__xludf.DUMMYFUNCTION("INT(FILTER(EQ(E8,F8),ISNUMBER(E8),ISNUMBER(F8)))"),1.0) -> 1
A9: Discovery of platelet-type 12-human lipoxygenase selective inhibitors by high-throughput screening of structurally diverse libraries | B9: https://doi.org/10.1016/j.bmc.2007.08.015 | C9: National Cancer Institute; NCI; Instituto Nacional del Cáncer || National Institute of General Medical Sciences; NIGMS; U.S. National Institute of General Medical Sciences || National Cancer Institute; NCI; Instituto Nacional del Cáncer || National Institute of General Medical Sciences; NIGMS; U.S. National Institute of General Medical Sciences | D9: https://openalex.org/funders/f4320337351 || https://openalex.org/funders/f4320337354 | E9: =sample_20250925!E9 -> 3 | F9: =IF(sample_20250925!$C9=C9,sample_20250925!F9, NA()) -> 2 | G9: =IF(sample_20250925!$C9=$C9,sample_20250925!G9, NA()) -> 0 | H9: Jacob | M9: =F9/E9 -> 0.66666667 | N9: =G9/E9 -> 0 | O9: =IFERROR(__xludf.DUMMYFUNCTION("INT(FILTER(GT(F9,0),ISNUMBER(F9)))"),1.0) -> 1 | P9: =F9/(F9+G9) -> 1 | Q9: =IFERROR(__xludf.DUMMYFUNCTION("INT(FILTER(EQ(E9,F9),ISNUMBER(E9),ISNUMBER(F9)))"),0.0) -> 0
A10: Constructing mentally ill inmates: nurses' discursive practices in corrections | B10: https://doi.org/10.1111/j.1440-1800.2011.00526.x | C10: Canadian Institutes of Health Research; CIHR; IRSC; Instituts de Recherche en Santé du Canada | D10: https://openalex.org/funders/f4320334506 | E10: =sample_20250925!E10 -> 1 | F10: =IF(sample_20250925!$C10=C10,sample_20250925!F10, NA()) -> 1 | G10: =IF(sample_20250925!$C10=$C10,sample_20250925!G10, NA()) -> 0 | H10: Jacob | M10: =F10/E10 -> 1 | N10: =G10/E10 -> 0 | O10: =IFERROR(__xludf.DUMMYFUNCTION("INT(FILTER(GT(F10,0),ISNUMBER(F10)))"),1.0) -> 1 | P10: =F10/(F10+G10) -> 1 | Q10: =IFERROR(__xludf.DUMMYFUNCTION("INT(FILTER(EQ(E10,F10),ISNUMBER(E10),ISNUMBER(F10)))"),1.0) -> 1
A11: An in vivo study on bone formation behavior of microporous granular calcium phosphate | B11: https://doi.org/10.1039/c7bm00162b | C11: Coordenação de Aperfeiçoamento de Pessoal de Nível Superior; Coordination for the Improvement of Higher Education Personnel; CAPES; Brazilian Federal Agency for the Support and Evaluation of Graduate Education || Ministerio de Economía y Competitividad; MINECO; MEC; Ministry of Economy and Competitiveness | D11: https://openalex.org/funders/f4320321091 || https://openalex.org/funders/f4320321837 | E11: =sample_20250925!E11 -> 2 | F11: =IF(sample_20250925!$C11=C11,sample_20250925!F11, NA()) -> 2 | G11: =IF(sample_20250925!$C11=$C11,sample_20250925!G11, NA()) -> 0 | H11: Jacob | M11: =F11/E11 -> 1 | N11: =G11/E11 -> 0 | O11: =IFERROR(__xludf.DUMMYFUNCTION("INT(FILTER(GT(F11,0),ISNUMBER(F11)))"),1.0) -> 1 | P11: =F11/(F11+G11) -> 1
A12: Self-directedly assembled porphyrin thin films with high photoactivity | B12: https://doi.org/10.1039/c5ra17015j | C12: National Natural Science Foundation of China; NNSF of China; Guójiā Zìrán Kēxué Jījīn Wěiyuánhuì; NSF of China; The National Natural Science Foundation of China; 国家自然科学基金委员会; National Nature Science Foundation of China; NSFC; National Science Foundation of China; Natural Science Foundation of China; NNSFC; Chinese National Science Foundation; NNSF || Shanghai Municipal Education Commission; Education Commission of Shanghai Municipality; 上海市教育委员会 | D12: https://openalex.org/funders/f4320321881 || https://openalex.org/funders/f4320321001 | E12: =sample_20250925!E12 -> 2 | F12: =IF(sample_20250925!$C12=C12,sample_20250925!F12, NA()) -> 2 | G12: =IF(sample_20250925!$C12=$C12,sample_20250925!G12, NA()) -> 0 | H12: Jacob | M12: =F12/E12 -> 1 | N12: =G12/E12 -> 0 | O12: =IFERROR(__xludf.DUMMYFUNCTION("INT(FILTER(GT(F12,0),ISNUMBER(F12)))"),1.0) -> 1 | P12: =F12/(F12+G12) -> 1 | Q12: =IFERROR(__xludf.DUMMYFUNCTION("INT(FILTER(EQ(E12,F12),ISNUMBER(E12),ISNUMBER(F12)))"),1.0) -> 1
A13: Human Schlafen 5 (SLFN5) Is a Regulator of Motility and Invasiveness of Renal Cell Carcinoma Cells | B13: https://doi.org/10.1128/MCB.00019-15 | C13: National Institutes of Health; US National Institutes of Health; Institutos Nacionales de la Salud; NIH || U.S. Department of Veterans Affairs; United States Department of Veterans Affairs; Veterans Affairs; Veterans Affairs Department; Department of Veterans Affairs; US Department of Veterans Affairs; VA; U.S. Dept. of Veterans Affairs; USDVA || National Cancer Institute; NCI; Instituto Nacional del Cáncer || National Center for Advancing Translational Sciences; NCATS; NIH-NCATS; NIH's National Center for Advancing Translational; NCATS NIH || U.S. Department of Veterans Affairs; United States Department of Veterans Affairs; Veterans Affairs; Veterans Affairs Department; Department of Veterans Affairs; US Department of Veterans Affairs; VA; U.S. Dept. of Veterans Affairs; USDVA | D13: https://openalex.org/funders/f4320332161 || https://openalex.org/funders/f4320337351 || https://openalex.org/funders/f4320306127 || https://openalex.org/funders/f4320337472 | E13: 3 | F13: 3 | G13: 0 | H13: Jacob | M13: =F13/E13 -> 1 | N13: =G13/E13 -> 0 | O13: =IFERROR(__xludf.DUMMYFUNCTION("INT(FILTER(GT(F13,0),ISNUMBER(F13)))"),1.0) -> 1 | P13: =F13/(F13+G13) -> 1 | Q13: =IFERROR(__xludf.DUMMYFUNCTION("INT(FILTER(EQ(E13,F13),ISNUMBER(E13),ISNUMBER(F13)))"),1.0) -> 1
A14: STRUCTURAL ELUCIDATION OF A NEUTRAL WATER-SOLUBLE a-D-GLUCAN FROM THE FUNGUS OF HERICIUM ERINACEUS | B14: https://doi.org/10.1111/j.1745-4514.2010.00492.x | C14: NOT MATCHED || Natural Science Foundation of Zhejiang Province; Zhejiang Natural Science Foundation; ZJNSF; 浙江省自然科学基金根据国; Zhejiang Provincial Natural Science Foundation | D14: https://openalex.org/funders/f4320338464 | E14: =sample_20250925!E14 -> 2 | F14: 1 | G14: 0 | H14: Jacob | M14: =F14/E14 -> 0.5 | N14: =G14/E14 -> 0 | O14: =IFERROR(__xludf.DUMMYFUNCTION("INT(FILTER(GT(F14,0),ISNUMBER(F14)))"),1.0) -> 1 | P14: =F14/(F14+G14) -> 1 | Q14: =IFERROR(__xludf.DUMMYFUNCTION("INT(FILTER(EQ(E14,F14),ISNUMBER(E14),ISNUMBER(F14)))"),0.0) -> 0
A15: Localization of Free and Bound Metal Species through X-Ray Synchrotron Fluorescence Microscopy in the Rodent Brain and Their Relation to Behavior | B15: https://doi.org/10.3390/brainsci9040074 | C15: U.S. Department of Energy; US Department of Energy; DOE; United States Department of Energy; Department of Energy; USDOE; Energy Department; ENERGY.GOV; USADOE; US DOE || U.S. Department of Energy; US Department of Energy; DOE; United States Department of Energy; Department of Energy; USDOE; Energy Department; ENERGY.GOV; USADOE; US DOE | D15: https://openalex.org/funders/f4320306084 | E15: =sample_20250925!E15 -> 1 | F15: =IF(sample_20250925!$C15=C15,sample_20250925!F15, NA()) -> 1 | G15: =IF(sample_20250925!$C15=$C15,sample_20250925!G15, NA()) -> 0 | H15: Jacob | M15: =F15/E15 -> 1 | N15: =G15/E15 -> 0 | O15: =IFERROR(__xludf.DUMMYFUNCTION("INT(FILTER(GT(F15,0),ISNUMBER(F15)))"),1.0) -> 1 | P15: =F15/(F15+G15) -> 1 | Q15: =IFERROR(__xludf.DUMMYFUNCTION("INT(FILTER(EQ(E15,F15),ISNUMBER(E15),ISNUMBER(F15)))"),1.0) -> 1
A16: Establishment, Persistence, and Reactivation of Latent HIV-1 Infection in Renal Epithelial Cells | B16: https://doi.org/10.1128/jvi.00624-22 | C16: National Institute of Diabetes and Digestive and Kidney Diseases; NIH\/National Institute of Diabetes, Digestive & Kidney Diseases; NIH National Institute of Diabetes and Digestive and Kidney Diseases; NIDDK; National Institute of Diabetes & Digestive & Kidney Diseases | D16: https://openalex.org/funders/f4320337357 | E16: =sample_20250925!E16 -> 1 | F16: =IF(sample_20250925!$C16=C16,sample_20250925!F16, NA()) -> 1 | G16: =IF(sample_20250925!$C16=$C16,sample_20250925!G16, NA()) -> 0 | H16: Jacob | M16: =F16/E16 -> 1 | N16: =G16/E16 -> 0 | O16: =IFERROR(__xludf.DUMMYFUNCTION("INT(FILTER(GT(F16,0),ISNUMBER(F16)))"),1.0) -> 1 | P16: =F16/(F16+G16) -> 1 | Q16: =IFERROR(__xludf.DUMMYFUNCTION("INT(FILTER(EQ(E16,F16),ISNUMBER(E16),ISNUMBER(F16)))"),1.0) -> 1
A17: Parallel ddRAD and Genome Skimming Analyses Reveal a Radiative and Reticulate Evolutionary History of the Temperate Bamboos | B17: https://doi.org/10.1093/sysbio/syaa076 | C17: Chinese Academy of Sciences; CAS; 中国科学院 || National Natural Science Foundation of China; NNSF of China; Guójiā Zìrán Kēxué Jījīn Wěiyuánhuì; NSF of China; The National Natural Science Foundation of China; 国家自然科学基金委员会; National Nature Science Foundation of China; NSFC; National Science Foundation of China; Natural Science Foundation of China; NNSFC; Chinese National Science Foundation; NNSF || NOT MATCHED || University of Chinese Academy of Sciences; 中国科学院大学; University of the Chinese Academy of Sciences; UCAS; Graduate University of Chinese Academy of Sciences | D17: https://openalex.org/funders/f4320321133 || https://openalex.org/funders/f4320326972 || https://openalex.org/funders/f4320321001 | E17: =sample_20250925!E17 -> 4 | F17: 3 | G17: 0 | H17: Jacob | M17: =F17/E17 -> 0.75 | N17: =G17/E17 -> 0 | O17: =IFERROR(__xludf.DUMMYFUNCTION("INT(FILTER(GT(F17,0),ISNUMBER(F17)))"),1.0) -> 1 | P17: =F17/(F17+G17) -> 1 | Q17: =IFERROR(__xludf.DUMMYFUNCTION("INT(FILTER(EQ(E17,F17),ISNUMBER(E17),ISNUMBER(F17)))"),0.0) -> 0
A18: Casting a Black Gandhi: Martin Luther King Jr., American Pacifists and the Global Dynamics of Race | B18: https://doi.org/10.1017/S0021875819000033 | C18: Arts and Humanities Research Council; AHRC || Economic and Social Research Council; ESRC || Arts and Humanities Research Council; AHRC | D18: https://openalex.org/funders/f4320334609 || https://openalex.org/funders/f4320334630 | E18: =sample_20250925!E18 -> 2 | F18: =IF(sample_20250925!$C18=C18,sample_20250925!F18, NA()) -> 2 | G18: =IF(sample_20250925!$C18=$C18,sample_20250925!G18, NA()) -> 0 | H18: Jacob | M18: =F18/E18 -> 1 | N18: =G18/E18 -> 0 | O18: =IFERROR(__xludf.DUMMYFUNCTION("INT(FILTER(GT(F18,0),ISNUMBER(F18)))"),1.0) -> 1 | P18: =F18/(F18+G18) -> 1 | Q18: =IFERROR(__xludf.DUMMYFUNCTION("INT(FILTER(EQ(E18,F18),ISNUMBER(E18),ISNUMBER(F18)))"),1.0) -> 1
A19: Synthesis of 2-Vinylbenzofurans via the Copper-Catalyzed Multicomponent Reactions Involving an Oxa-Michael/Arylation/Vinylation Cascade | B19: https://doi.org/10.1021/ol502506g | C19: National Natural Science Foundation of China; NNSF of China; Guójiā Zìrán Kēxué Jījīn Wěiyuánhuì; NSF of China; The National Natural Science Foundation of China; 国家自然科学基金委员会; National Nature Science Foundation of China; NSFC; National Science Foundation of China; Natural Science Foundation of China; NNSFC; Chinese National Science Foundation; NNSF || Education Department of Jiangxi Province; Department of Education, Jiangxi Province; Jiangxi Provincial Education Department; 江西省教育厅; Department of Education of Jiangxi Province; Jiangxi Provincial Department of Education | D19: https://openalex.org/funders/f4320325626 || https://openalex.org/funders/f4320321001 | E19: =sample_20250925!E19 -> 2 | F19: =IF(sample_20250925!$C19=C19,sample_20250925!F19, NA()) -> 2 | G19: =IF(sample_20250925!$C19=$C19,sample_20250925!G19, NA()) -> 0 | H19: Jacob | M19: =F19/E19 -> 1 | N19: =G19/E19 -> 0 | O19: =IFERROR(__xludf.DUMMYFUNCTION("INT(FILTER(GT(F19,0),ISNUMBER(F19)))"),1.0) -> 1 | P19: =F19/(F19+G19) -> 1 | Q19: =IFERROR(__xludf.DUMMYFUNCTION("INT(FILTER(EQ(E19,F19),ISNUMBER(E19),ISNUMBER(F19)))"),1.0) -> 1
A20: A thermosensitive molecularly imprinted poly-NIPAM coated MWCNTs/TiO2 photocatalyst for the preferential removal of pendimethalin pesticide from wastewater | B20: https://doi.org/10.1016/j.jphotochem.2020.112802 | C20: Shahid Beheshti University; دانشگاه شهید بهشتی; SBU | D20: https://openalex.org/funders/f4320319808 | E20: =sample_20250925!E20 -> 1 | F20: =IF(sample_20250925!$C20=C20,sample_20250925!F20, NA()) -> 1 | G20: =IF(sample_20250925!$C20=$C20,sample_20250925!G20, NA()) -> 0 | H20: Jacob | M20: =F20/E20 -> 1 | N20: =G20/E20 -> 0 | O20: =IFERROR(__xludf.DUMMYFUNCTION("INT(FILTER(GT(F20,0),ISNUMBER(F20)))"),1.0) -> 1 | P20: =F20/(F20+G20) -> 1 | Q20: =IFERROR(__xludf.DUMMYFUNCTION("INT(FILTER(EQ(E20,F20),ISNUMBER(E20),ISNUMBER(F20)))"),1.0) -> 1
A21: Renal Cell Carcinoma in the Era of Precision Medicine: From Molecular Pathology to Tissue-Based Biomarkers | B21: https://doi.org/10.1200/JCO.2018.79.2259 | C21: National Institutes of Health; US National Institutes of Health; Institutos Nacionales de la Salud; NIH || Memorial Sloan-Kettering Cancer Center; MSK Cancer Center; Memorial Sloan Kettering Cancer Center; MSKCC; MSK; Memorial Sloan Kettering || Society of Memorial Sloan Kettering; Society of MSK || National Cancer Institute; NCI; Instituto Nacional del Cáncer | D21: https://openalex.org/funders/f4320332161 || https://openalex.org/funders/f4320309468 || https://openalex.org/funders/f4320313397 || https://openalex.org/funders/f4320337351 | E21: =sample_20250925!E21 -> 5 | F21: =IF(sample_20250925!$C21=C21,sample_20250925!F21, NA()) -> 4 | G21: =IF(sample_20250925!$C21=$C21,sample_20250925!G21, NA()) -> 0 | H21: Jacob | M21: =F21/E21 -> 0.8 | N21: =G21/E21 -> 0 | O21: =IFERROR(__xludf.DUMMYFUNCTION("INT(FILTER(GT(F21,0),ISNUMBER(F21)))"),1.0) -> 1 | P21: =F21/(F21+G21) -> 1 | Q21: =IFERROR(__xludf.DUMMYFUNCTION("INT(FILTER(EQ(E21,F21),ISNUMBER(E21),ISNUMBER(F21)))"),0.0) -> 0
A22: CAIR-1/BAG-3 modulates cell adhesion and migration by downregulating activity of focal adhesion proteins | B22: https://doi.org/10.1016/j.yexcr.2006.05.023 | C22: National Cancer Institute; NCI; Instituto Nacional del Cáncer || National Institutes of Health; US National Institutes of Health; Institutos Nacionales de la Salud; NIH | D22: https://openalex.org/funders/f4320332161 || https://openalex.org/funders/f4320337351 | E22: =sample_20250925!E22 -> 2 | F22: =IF(sample_20250925!$C22=C22,sample_20250925!F22, NA()) -> 2 | G22: =IF(sample_20250925!$C22=$C22,sample_20250925!G22, NA()) -> 0 | H22: Jacob | M22: =F22/E22 -> 1 | N22: =G22/E22 -> 0 | O22: =IFERROR(__xludf.DUMMYFUNCTION("INT(FILTER(GT(F22,0),ISNUMBER(F22)))"),1.0) -> 1 | P22: =F22/(F22+G22) -> 1
A23: Non-Markovian Exciton-Phonon Interactions in Core-Shell Colloidal Quantum Dots at Femtosecond Timescales | B23: https://doi.org/10.1103/PhysRevLett.123.057403 | C23: U.S. Department of Energy; US Department of Energy; DOE; United States Department of Energy; Department of Energy; USDOE; Energy Department; ENERGY.GOV; USADOE; US DOE || Conselho Nacional de Desenvolvimento Científico e Tecnológico; National Council for Scientific and Technological Development; Brazilian National Council for Research and Development; CNPq || Fundação de Amparo à Pesquisa do Estado de São Paulo; São Paulo Research Foundation; Foundation for Research Support of the State of São Paulo; FAPESP; State of São Paulo Research Foundation | D23: https://openalex.org/funders/f4320306084 || https://openalex.org/funders/f4320322025 || https://openalex.org/funders/f4320320997 | E23: =sample_20250925!E23 -> 3 | F23: =IF(sample_20250925!$C23=C23,sample_20250925!F23, NA()) -> 3 | G23: =IF(sample_20250925!$C23=$C23,sample_20250925!G23, NA()) -> 0 | H23: Jacob | M23: =F23/E23 -> 1 | N23: =G23/E23 -> 0 | O23: =IFERROR(__xludf.DUMMYFUNCTION("INT(FILTER(GT(F23,0),ISNUMBER(F23)))"),1.0) -> 1 | P23: =F23/(F23+G23) -> 1 | Q23: =IFERROR(__xludf.DUMMYFUNCTION("INT(FILTER(EQ(E23,F23),ISNUMBER(E23),ISNUMBER(F23)))"),1.0) -> 1
A24: Nrf2 augments skeletal muscle regeneration after ischaemia-reperfusion injury | B24: https://doi.org/10.1002/path.4418 | C24: NOT MATCHED || NOT MATCHED || Deutsche Forschungsgemeinschaft; German Research Association; DFG; German Research Foundation | D24: https://openalex.org/funders/f4320320879 | E24: =sample_20250925!E24 -> 3 | F24: 1 | G24: 0 | H24: Jacob | M24: =F24/E24 -> 0.33333333 | N24: =G24/E24 -> 0 | O24: =IFERROR(__xludf.DUMMYFUNCTION("INT(FILTER(GT(F24,0),ISNUMBER(F24)))"),1.0) -> 1 | P24: =F24/(F24+G24) -> 1 | Q24: =IFERROR(__xludf.DUMMYFUNCTION("INT(FILTER(EQ(E24,F24),ISNUMBER(E24),ISNUMBER(F24)))"),0.0) -> 0
A25: INVESTMENT ACTIVITY OF NATURAL MONOPOLIES OF SARATOV REGION: PROBLEMS AND SOLUTIONS | B25: https://doi.org/10.15405/epsbs.2019.03.02.216 | C25: Russian Foundation for Basic Research; RFBR; РФФИ; Российский Фонд Фундаментальных Исследований || NOT MATCHED | D25: https://openalex.org/funders/f4320321079 | E25: =sample_20250925!E25 -> 2 | F25: 1 | G25: 0 | H25: Jacob | M25: =F25/E25 -> 0.5 | N25: =G25/E25 -> 0 | O25: =IFERROR(__xludf.DUMMYFUNCTION("INT(FILTER(GT(F25,0),ISNUMBER(F25)))"),1.0) -> 1 | P25: =F25/(F25+G25) -> 1 | Q25: =IFERROR(__xludf.DUMMYFUNCTION("INT(FILTER(EQ(E25,F25),ISNUMBER(E25),ISNUMBER(F25)))"),0.0) -> 0
A26: Mathematical Modelling and Electrical Analog Equivalent of the Human Cardiovascular System | B26: https://doi.org/10.1007/s10558-010-9093-0 | C26: Iran University of Science and Technology; Iran University of Science & Technology; IUST || NOT MATCHED | D26: https://openalex.org/funders/f4320324096 | E26: =sample_20250925!E26 -> 2 | F26: 1 | G26: 0 | H26: Jacob | M26: =F26/E26 -> 0.5 | N26: =G26/E26 -> 0 | O26: =IFERROR(__xludf.DUMMYFUNCTION("INT(FILTER(GT(F26,0),ISNUMBER(F26)))"),1.0) -> 1 | P26: =F26/(F26+G26) -> 1 | Q26: =IFERROR(__xludf.DUMMYFUNCTION("INT(FILTER(EQ(E26,F26),ISNUMBER(E26),ISNUMBER(F26)))"),0.0) -> 0
A27: Characterizing Serpinb2 as a Modulator of TCDD-Induced Suppression of the B Cell | B27: https://doi.org/10.1021/acs.chemrestox.8b00225 | C27: National Institute of Environmental Health Sciences; The National Institute of Environmental Health Sciences; NIH National Institute of Environmental Health Sciences; NIEHS || Michigan State University; Michigan State University Spartans; MSU || National Institute of Environmental Health Sciences; The National Institute of Environmental Health Sciences; NIH National Institute of Environmental Health Sciences; NIEHS || National Institute of Environmental Health Sciences; The National Institute of Environmental Health Sciences; NIH National Institute of Environmental Health Sciences; NIEHS | D27: https://openalex.org/funders/f4320337361 || https://openalex.org/funders/f4320310016 | E27: =sample_20250925!E27 -> 2 | F27: =IF(sample_20250925!$C27=C27,sample_20250925!F27, NA()) -> 1 | G27: =IF(sample_20250925!$C27=$C27,sample_20250925!G27, NA()) -> 0 | H27: Jacob | M27: =F27/E27 -> 0.5 | N27: =G27/E27 -> 0 | O27: =IFERROR(__xludf.DUMMYFUNCTION("INT(FILTER(GT(F27,0),ISNUMBER(F27)))"),1.0) -> 1 | P27: =F27/(F27+G27) -> 1 | Q27: =IFERROR(__xludf.DUMMYFUNCTION("INT(FILTER(EQ(E27,F27),ISNUMBER(E27),ISNUMBER(F27)))"),0.0) -> 0
A28: Targeting vulnerable households in urban Burkina Faso: effectiveness of geographical criteria but not of proxy-means testing | B28: https://doi.org/10.1093/heapol/czv104 | C28: World Food Programme; WFP; Programa Mundial de Alimentos; Programma Alimentare Mondiale; Programme Alimentaire Mondial || Institut de Recherche pour le Développement; IRD; Institute for development research IRD; French Research Institute for Development; Instituto de Investigación por el Desarrollo; Institute for development research; French National Research Institute for Sustainable Development | D28: https://openalex.org/institutions/i1295768896 || https://openalex.org/funders/f4320313932 | E28: =sample_20250925!E28 -> 2 | F28: 2 | G28: 0 | H28: Jacob | M28: =F28/E28 -> 1 | N28: =G28/E28 -> 0 | O28: =IFERROR(__xludf.DUMMYFUNCTION("INT(FILTER(GT(F28,0),ISNUMBER(F28)))"),1.0) -> 1 | P28: =F28/(F28+G28) -> 1 | Q28: =IFERROR(__xludf.DUMMYFUNCTION("INT(FILTER(EQ(E28,F28),ISNUMBER(E28),ISNUMBER(F28)))"),1.0) -> 1
A29: Onset of remission and relapse in depression: Testing operational criteria through course description in a second Dublin cohort of first-admission participants | B29: https://doi.org/10.1016/j.jad.2010.02.107 | C29: St. Patrick's Hospital; St. Patrick's University Hospital || Trinity College, University of Oxford; Trinity College | D29: https://openalex.org/funders/f4320334671 || https://openalex.org/institutions/i4210122413 | E29: =sample_20250925!E29 -> 2 | F29: =IF(sample_20250925!$C29=C29,sample_20250925!F29, NA()) -> 2 | G29: =IF(sample_20250925!$C29=$C29,sample_20250925!G29, NA()) -> 0 | H29: Jacob | M29: =F29/E29 -> 1 | N29: =G29/E29 -> 0 | O29: =IFERROR(__xludf.DUMMYFUNCTION("INT(FILTER(GT(F29,0),ISNUMBER(F29)))"),1.0) -> 1 | P29: =F29/(F29+G29) -> 1 | Q29: =IFERROR(__xludf.DUMMYFUNCTION("INT(FILTER(EQ(E29,F29),ISNUMBER(E29),ISNUMBER(F29)))"),1.0) -> 1
A30: Preparative isolation and purification of capsaicinoids from Capsicum frutescens using high-speed counter-current chromatography | B30: https://doi.org/10.1016/j.seppur.2008.10.005 | C30: National Natural Science Foundation of China; NNSF of China; Guójiā Zìrán Kēxué Jījīn Wěiyuánhuì; NSF of China; The National Natural Science Foundation of China; 国家自然科学基金委员会; National Nature Science Foundation of China; NSFC; National Science Foundation of China; Natural Science Foundation of China; NNSFC; Chinese National Science Foundation; NNSF || NOT MATCHED | D30: https://openalex.org/funders/f4320321001 | E30: =sample_20250925!E30 -> 2 | F30: 1 | G30: 0 | H30: Jacob | M30: =F30/E30 -> 0.5 | N30: =G30/E30 -> 0 | O30: =IFERROR(__xludf.DUMMYFUNCTION("INT(FILTER(GT(F30,0),ISNUMBER(F30)))"),1.0) -> 1 | P30: =F30/(F30+G30) -> 1 | Q30: =IFERROR(__xludf.DUMMYFUNCTION("INT(FILTER(EQ(E30,F30),ISNUMBER(E30),ISNUMBER(F30)))"),0.0) -> 0
A31: Clinical and ultrasonographic differences between cattle and buffaloes with various sequelae of traumatic reticuloperitonitis | B31: https://doi.org/10.17221/128/2009-VETMED | C31: Ministry of Higher Education; Ministry of Higher Education, Egypt; MOHE; Egyptian Ministry of Higher Education | D31: https://openalex.org/funders/f4320321147 | E31: =sample_20250925!E31 -> 1 | F31: =IF(sample_20250925!$C31=C31,sample_20250925!F31, NA()) -> 1 | G31: =IF(sample_20250925!$C31=$C31,sample_20250925!G31, NA()) -> 0 | H31: Jacob | M31: =F31/E31 -> 1 | N31: =G31/E31 -> 0 | O31: =IFERROR(__xludf.DUMMYFUNCTION("INT(FILTER(GT(F31,0),ISNUMBER(F31)))"),1.0) -> 1 | P31: =F31/(F31+G31) -> 1 | Q31: =IFERROR(__xludf.DUMMYFUNCTION("INT(FILTER(EQ(E31,F31),ISNUMBER(E31),ISNUMBER(F31)))"),1.0) -> 1
A32: Influence of grain type and oil concentration of dried corn distillers' grain with solubles on ruminal fermentation and in vitro gas production in cattle fed high-concentrate diets | B32: https://doi.org/10.1139/cjas-2018-0036 | C32: North Dakota Corn Utilization Council; North Dakota Corn; NDCUC; North Dakota Corn Council; ND Corn Council | D32: https://openalex.org/funders/f4320318963 | E32: =sample_20250925!E32 -> 1 | F32: =IF(sample_20250925!$C32=C32,sample_20250925!F32, NA()) -> 1 | G32: =IF(sample_20250925!$C32=$C32,sample_20250925!G32, NA()) -> 0 | H32: Jacob | M32: =F32/E32 -> 1 | N32: =G32/E32 -> 0 | O32: =IFERROR(__xludf.DUMMYFUNCTION("INT(FILTER(GT(F32,0),ISNUMBER(F32)))"),1.0) -> 1 | P32: =F32/(F32+G32) -> 1 | Q32: =IFERROR(__xludf.DUMMYFUNCTION("INT(FILTER(EQ(E32,F32),ISNUMBER(E32),ISNUMBER(F32)))"),1.0) -> 1
A33: IIx myosin heavy chain promoter regulation cannot be characterized in vivo by direct gene transfer | B33: https://doi.org/10.1152/ajpcell.00221.2007 | C33: National Institute of Arthritis and Musculoskeletal and Skin Diseases; NIAMS; Instituto Nacional de Artritis y Enfermedades Musculoesqueléticas y de la Piel; NIH\/National Institute of Arthritis and Musculoskeletal and Skin Diseases; National Institute of Arthritis & Musculoskeletal & Skin Diseases; The National Institute of Arthritis and Musculoskeletal and Skin Diseases; NIH National Institute of Arthritis and Musculoskeletal and Skin Diseases || National Institute of Arthritis and Musculoskeletal and Skin Diseases; NIAMS; Instituto Nacional de Artritis y Enfermedades Musculoesqueléticas y de la Piel; NIH\/National Institute of Arthritis and Musculoskeletal and Skin Diseases; National Institute of Arthritis & Musculoskeletal & Skin Diseases; The National Institute of Arthritis and Musculoskeletal and Skin Diseases; NIH National Institute of Arthritis and Musculoskeletal and Skin Diseases | D33: https://openalex.org/funders/f4320337362 | E33: =sample_20250925!E33 -> 1 | F33: =IF(sample_20250925!$C33=C33,sample_20250925!F33, NA()) -> 1 | G33: =IF(sample_20250925!$C33=$C33,sample_20250925!G33, NA()) -> 0 | H33: Jacob | M33: =F33/E33 -> 1 | N33: =G33/E33 -> 0 | O33: =IFERROR(__xludf.DUMMYFUNCTION("INT(FILTER(GT(F33,0),ISNUMBER(F33)))"),1.0) -> 1 | P33: =F33/(F33+G33) -> 1
A34: Crash responses under multiple impacts and residual properties of CFRP and aluminum tubes | B34: https://doi.org/10.1016/j.compstruct.2018.04.001 | C34: National Natural Science Foundation of China; NNSF of China; Guójiā Zìrán Kēxué Jījīn Wěiyuánhuì; NSF of China; The National Natural Science Foundation of China; 国家自然科学基金委员会; National Nature Science Foundation of China; NSFC; National Science Foundation of China; Natural Science Foundation of China; NNSFC; Chinese National Science Foundation; NNSF || NOT MATCHED || Natural Science Foundation of Guangdong Province; Guangdong Natural Science Foundation; Guangdong Provincial Natural Science Foundation; Natural Science Foundation of Guangdong || Natural Science Foundation of Hunan Province; Hunan Provincial Natural Science Foundation || China Postdoctoral Science Foundation || NOT MATCHED | D34: https://openalex.org/funders/f4320322843 || https://openalex.org/funders/f4320321921 || https://openalex.org/funders/f4320321001 || https://openalex.org/funders/f4320321543 | E34: =sample_20250925!E34 -> 6 | F34: 4 | G34: 0 | H34: Jacob | M34: =F34/E34 -> 0.66666667 | N34: =G34/E34 -> 0 | O34: =IFERROR(__xludf.DUMMYFUNCTION("INT(FILTER(GT(F34,0),ISNUMBER(F34)))"),1.0) -> 1 | P34: =F34/(F34+G34) -> 1 | Q34: =IFERROR(__xludf.DUMMYFUNCTION("INT(FILTER(EQ(E34,F34),ISNUMBER(E34),ISNUMBER(F34)))"),0.0) -> 0
A35: Inactivation of a pathogenic NDM-1-positive Escherichia coli strain and the resistance gene bla(NDM-1) by TiO2/UVA photocatalysis | B35: https://doi.org/10.1016/j.scitotenv.2022.157369 | C35: Government of Jiangsu Province; Jiangsu Province || NOT MATCHED || National Natural Science Foundation of China; NNSF of China; Guójiā Zìrán Kēxué Jījīn Wěiyuánhuì; NSF of China; The National Natural Science Foundation of China; 国家自然科学基金委员会; National Nature Science Foundation of China; NSFC; National Science Foundation of China; Natural Science Foundation of China; NNSFC; Chinese National Science Foundation; NNSF | D35: https://openalex.org/funders/f4320321001 || https://openalex.org/funders/f4320321605 | E35: =sample_20250925!E35 -> 3 | F35: 2 | G35: 0 | H35: Jacob | M35: =F35/E35 -> 0.66666667 | N35: =G35/E35 -> 0 | O35: =IFERROR(__xludf.DUMMYFUNCTION("INT(FILTER(GT(F35,0),ISNUMBER(F35)))"),1.0) -> 1 | P35: =F35/(F35+G35) -> 1 | Q35: =IFERROR(__xludf.DUMMYFUNCTION("INT(FILTER(EQ(E35,F35),ISNUMBER(E35),ISNUMBER(F35)))"),0.0) -> 0
A36: Comparison of phase-shifting techniques for in vivo full-range, high-speed Fourier-domain optical coherence tomography | B36: https://doi.org/10.1117/1.3494556 | C36: National Eye Institute; NIH\/National Eye Institute; The National Eye Institute; NEI; Instituto Nacional del Ojo || Research to Prevent Blindness; Research to Prevent Blindness, Inc; Research To Prevent Blindness, Inc.; RESEARCH TO PREVENT BLINDNESS INC; RPB || National Eye Institute; NIH\/National Eye Institute; The National Eye Institute; NEI; Instituto Nacional del Ojo | D36: https://openalex.org/funders/f4320337350 || https://openalex.org/funders/f4320306811 | E36: =sample_20250925!E36 -> 2 | F36: =IF(sample_20250925!$C36=C36,sample_20250925!F36, NA()) -> 2 | G36: =IF(sample_20250925!$C36=$C36,sample_20250925!G36, NA()) -> 0 | H36: Jacob | M36: =F36/E36 -> 1 | N36: =G36/E36 -> 0 | O36: =IFERROR(__xludf.DUMMYFUNCTION("INT(FILTER(GT(F36,0),ISNUMBER(F36)))"),1.0) -> 1 | P36: =F36/(F36+G36) -> 1 | Q36: =IFERROR(__xludf.DUMMYFUNCTION("INT(FILTER(EQ(E36,F36),ISNUMBER(E36),ISNUMBER(F36)))"),1.0) -> 1
A37: Experience and Outcome of Children with Severe Acute Malnutrition Using Locally Prepared Therapeutic Diet | B37: https://doi.org/10.1007/s12098-015-1818-z | C37: UNICEF; United Nations Children's Emergency Fund | D37: https://openalex.org/funders/f4320309209 | E37: =sample_20250925!E37 -> 1 | F37: =IF(sample_20250925!$C37=C37,sample_20250925!F37, NA()) -> 1 | G37: =IF(sample_20250925!$C37=$C37,sample_20250925!G37, NA()) -> 0 | H37: Jacob | M37: =F37/E37 -> 1 | N37: =G37/E37 -> 0 | O37: =IFERROR(__xludf.DUMMYFUNCTION("INT(FILTER(GT(F37,0),ISNUMBER(F37)))"),1.0) -> 1 | P37: =F37/(F37+G37) -> 1 | Q37: =IFERROR(__xludf.DUMMYFUNCTION("INT(FILTER(EQ(E37,F37),ISNUMBER(E37),ISNUMBER(F37)))"),1.0) -> 1
A38: Analysis of EV Charging Coordination Efficiency in Presence of Cheating Customers | B38: https://doi.org/10.1109/ACCESS.2021.3128399 | C38: Qatar National Library; QNL; مكتبة قطر الوطنية; Qatar National Library, Doha, Qatar || NOT MATCHED | D38: https://openalex.org/funders/f4320334468 | E38: =sample_20250925!E38 -> 2 | F38: 1 | G38: 0 | H38: Jacob | M38: =F38/E38 -> 0.5 | N38: =G38/E38 -> 0 | O38: =IFERROR(__xludf.DUMMYFUNCTION("INT(FILTER(GT(F38,0),ISNUMBER(F38)))"),1.0) -> 1 | P38: =F38/(F38+G38) -> 1 | Q38: =IFERROR(__xludf.DUMMYFUNCTION("INT(FILTER(EQ(E38,F38),ISNUMBER(E38),ISNUMBER(F38)))"),0.0) -> 0
A39: Inhibitory Effects of Garcinia cambogia Extract on CYP2B6 Enzyme Activity | B39: https://doi.org/10.1055/s-0043-104934 | C39: National Research Foundation of Korea; NRF; 한국연구재단이 창의적 연구와 | D39: https://openalex.org/funders/f4320322120 | E39: 2 | F39: =IF(sample_20250925!$C39=C39,sample_20250925!F39, NA()) -> 1 | G39: =IF(sample_20250925!$C39=$C39,sample_20250925!G39, NA()) -> 0 | H39: Jacob | M39: =F39/E39 -> 0.5 | N39: =G39/E39 -> 0 | O39: =IFERROR(__xludf.DUMMYFUNCTION("INT(FILTER(GT(F39,0),ISNUMBER(F39)))"),1.0) -> 1 | P39: =F39/(F39+G39) -> 1 | Q39: =IFERROR(__xludf.DUMMYFUNCTION("INT(FILTER(EQ(E39,F39),ISNUMBER(E39),ISNUMBER(F39)))"),0.0) -> 0
A40: Preparation of platinum- and silver-incorporated TiO2 coatings in thin-film photoreactor for the photocatalytic decomposition of o-cresol | B40: https://doi.org/10.1080/09593330.2011.556670 | C40: Ministry of Science and Technology, Taiwan; Ministry of Science and Technology of Taiwan; MOST; Ministry of Science and Technology, R.O.C. (Taiwan) | D40: https://openalex.org/funders/f4320322795 | E40: =sample_20250925!E40 -> 1 | F40: 1 | G40: 0 | H40: Jacob | M40: =F40/E40 -> 1 | N40: =G40/E40 -> 0 | O40: =IFERROR(__xludf.DUMMYFUNCTION("INT(FILTER(GT(F40,0),ISNUMBER(F40)))"),1.0) -> 1 | P40: =F40/(F40+G40) -> 1 | Q40: =IFERROR(__xludf.DUMMYFUNCTION("INT(FILTER(EQ(E40,F40),ISNUMBER(E40),ISNUMBER(F40)))"),1.0) -> 1
A41: Nitrogen Dioxide Sensing Using Multilayer Structure of Reduced Graphene Oxide and alpha-Fe2O3 | B41: https://doi.org/10.3390/s21031011 | C41: Narodowym Centrum Nauki; NCN; National Science Centre; National Science Centre, Poland || Narodowe Centrum Nauki; National Science Centre; NCN | D41: https://openalex.org/funders/f4320322511 || https://openalex.org/funders/f4320322650 | E41: =sample_20250925!E41 -> 1 | F41: =IF(sample_20250925!$C41=C41,sample_20250925!F41, NA()) -> 1 | G41: =IF(sample_20250925!$C41=$C41,sample_20250925!G41, NA()) -> 0 | H41: Jacob | M41: =F41/E41 -> 1 | N41: =G41/E41 -> 0 | O41: =IFERROR(__xludf.DUMMYFUNCTION("INT(FILTER(GT(F41,0),ISNUMBER(F41)))"),1.0) -> 1 | P41: =F41/(F41+G41) -> 1 | Q41: =IFERROR(__xludf.DUMMYFUNCTION("INT(FILTER(EQ(E41,F41),ISNUMBER(E41),ISNUMBER(F41)))"),1.0) -> 1
A42: Infestation of Lithodes santolla (Decapoda: Lithodidae) by Pseudione tuberculata (Isopoda: Bopyridae) in San Jorge Gulf, Southwestern Atlantic Ocean | B42: https://doi.org/10.1080/17451000903478327 | C42: Consejo Nacional de Investigaciones Científicas y Técnicas; National Scientific and Technical Research Council; CONICET | D42: https://openalex.org/funders/f4320321594 | E42: =sample_20250925!E42 -> 1 | F42: =IF(sample_20250925!$C42=C42,sample_20250925!F42, NA()) -> 1 | G42: =IF(sample_20250925!$C42=$C42,sample_20250925!G42, NA()) -> 0 | H42: Jacob | M42: =F42/E42 -> 1 | N42: =G42/E42 -> 0 | O42: =IFERROR(__xludf.DUMMYFUNCTION("INT(FILTER(GT(F42,0),ISNUMBER(F42)))"),1.0) -> 1 | P42: =F42/(F42+G42) -> 1 | Q42: =IFERROR(__xludf.DUMMYFUNCTION("INT(FILTER(EQ(E42,F42),ISNUMBER(E42),ISNUMBER(F42)))"),1.0) -> 1
A43: A novel lateral shearing interferometer and its anti-vibration characteristic for on-machine precision surface measurement | B43: https://doi.org/10.1016/j.ijleo.2016.03.064 | C43: National Natural Science Foundation of China; NNSF of China; Guójiā Zìrán Kēxué Jījīn Wěiyuánhuì; NSF of China; The National Natural Science Foundation of China; 国家自然科学基金委员会; National Nature Science Foundation of China; NSFC; National Science Foundation of China; Natural Science Foundation of China; NNSFC; Chinese National Science Foundation; NNSF || Program for Changjiang Scholars and Innovative Research Team in University; 长江学者和创新团队发展计划资助资助; Program for Yangtze River Scholars and Innovative Research Team in University || Natural Science Foundation of Hubei Province; Hubei Provincial Natural Science Foundation | D43: https://openalex.org/funders/f4320338204 || https://openalex.org/funders/f4320321001 || https://openalex.org/funders/f4320322186 | E43: =sample_20250925!E43 -> 3 | F43: =IF(sample_20250925!$C43=C43,sample_20250925!F43, NA()) -> 3 | G43: =IF(sample_20250925!$C43=$C43,sample_20250925!G43, NA()) -> 0 | H43: Jacob | M43: =F43/E43 -> 1 | N43: =G43/E43 -> 0 | O43: =IFERROR(__xludf.DUMMYFUNCTION("INT(FILTER(GT(F43,0),ISNUMBER(F43)))"),1.0) -> 1 | P43: =F43/(F43+G43) -> 1 | Q43: =IFERROR(__xludf.DUMMYFUNCTION("INT(FILTER(EQ(E43,F43),ISNUMBER(E43),ISNUMBER(F43)))"),1.0) -> 1
A44: Development of antimigraine transdermal delivery systems of pizotifen malate | B44: https://doi.org/10.1016/j.ijpharm.2015.07.033 | C44: NOT MATCHED || Universidad Cardenal Herrera CEU; CEU-UCH; Universidad CEU Cardenal Herrera; CEU Cardenal Herrera University; CEU Universidad Cardenal Herrera; Cardenal Herrera CEU University; Universitat CEU Cardenal Herrera | D44: https://openalex.org/institutions/i2800982320 | E44: =sample_20250925!E44 -> 2 | F44: 1 | G44: 0 | H44: Jacob | M44: =F44/E44 -> 0.5 | N44: =G44/E44 -> 0 | O44: =IFERROR(__xludf.DUMMYFUNCTION("INT(FILTER(GT(F44,0),ISNUMBER(F44)))"),1.0) -> 1 | P44: =F44/(F44+G44) -> 1
A45: Elasmobranch capture by commercial small-scale fisheries in the Bijagos Archipelago, Guinea Bissau | B45: https://doi.org/10.1016/j.fishres.2015.03.018 | C45: NOT MATCHED || University College London; UCL || Parkes Foundation | D45: https://openalex.org/funders/f4320311462 || https://openalex.org/funders/f4320320286 | E45: 4 | F45: 2 | G45: 0 | H45: Jacob | M45: =F45/E45 -> 0.5 | N45: =G45/E45 -> 0 | O45: =IFERROR(__xludf.DUMMYFUNCTION("INT(FILTER(GT(F45,0),ISNUMBER(F45)))"),1.0) -> 1 | P45: =F45/(F45+G45) -> 1 | Q45: =IFERROR(__xludf.DUMMYFUNCTION("INT(FILTER(EQ(E45,F45),ISNUMBER(E45),ISNUMBER(F45)))"),0.0) -> 0
A46: Mechanisms of Se(IV) Co-precipitation with Ferrihydrite at Acidic and Alkaline Conditions and Its Behavior during Aging | B46: https://doi.org/10.1021/acs.est.8b00462 | C46: Nuclear Safety Research Association; 公益財団法人原子力安全研究協会; 原子力安全研究協会 || Nuclear Waste Management Organization; Société de Gestion des Déchets Nucléaires; NWMO | D46: https://openalex.org/institutions/i4406743227 || https://openalex.org/funders/f4320313659 | E46: 3 | F46: 1 | G46: 1 | H46: Jacob | M46: =F46/E46 -> 0.33333333 | N46: =G46/E46 -> 0.33333333 | O46: =IFERROR(__xludf.DUMMYFUNCTION("INT(FILTER(GT(F46,0),ISNUMBER(F46)))"),1.0) -> 1 | P46: =F46/(F46+G46) -> 0.5 | Q46: =IFERROR(__xludf.DUMMYFUNCTION("INT(FILTER(EQ(E46,F46),ISNUMBER(E46),ISNUMBER(F46)))"),0.0) -> 0
A47: Neural activity, neural connectivity, and the processing of emotionally valenced information in older adults: links with life satisfaction | B47: https://doi.org/10.3758/s13415-011-0039-9 | C47: National Institute on Aging; The National Institute on Aging; NIA; NIH NATIONAL INSTITUTE ON AGING; U.S. National Institute on Aging || National Institute on Aging; The National Institute on Aging; NIA; NIH NATIONAL INSTITUTE ON AGING; U.S. National Institute on Aging | D47: https://openalex.org/funders/f4320337337 | E47: =sample_20250925!E47 -> 1 | F47: =IF(sample_20250925!$C47=C47,sample_20250925!F47, NA()) -> 1 | G47: =IF(sample_20250925!$C47=$C47,sample_20250925!G47, NA()) -> 0 | H47: Jacob | M47: =F47/E47 -> 1 | N47: =G47/E47 -> 0 | O47: =IFERROR(__xludf.DUMMYFUNCTION("INT(FILTER(GT(F47,0),ISNUMBER(F47)))"),1.0) -> 1 | P47: =F47/(F47+G47) -> 1 | Q47: =IFERROR(__xludf.DUMMYFUNCTION("INT(FILTER(EQ(E47,F47),ISNUMBER(E47),ISNUMBER(F47)))"),1.0) -> 1
A48: On the Non-trivial Origin of Atomic-Scale Patterns in Friction Force Microscopy | B48: https://doi.org/10.1007/s11249-018-1127-6 | C48: European Research Council; ERC || Nederlandse Organisatie voor Wetenschappelijk Onderzoek; Dutch Research Council; Dutch National Scientific Foundation; Dutch National Science Foundation; NWO; Netherlands Organisation for Scientific Research | D48: https://openalex.org/funders/f4320321800 || https://openalex.org/funders/f4320334678 | E48: =sample_20250925!E48 -> 2 | F48: 2 | G48: 0 | H48: Jacob | M48: =F48/E48 -> 1 | N48: =G48/E48 -> 0 | O48: =IFERROR(__xludf.DUMMYFUNCTION("INT(FILTER(GT(F48,0),ISNUMBER(F48)))"),1.0) -> 1 | P48: =F48/(F48+G48) -> 1 | Q48: =IFERROR(__xludf.DUMMYFUNCTION("INT(FILTER(EQ(E48,F48),ISNUMBER(E48),ISNUMBER(F48)))"),1.0) -> 1
A49: Multicoil Shimming of the Mouse Brain | B49: https://doi.org/10.1002/mrm.22850 | C49: National Institutes of Health; US National Institutes of Health; Institutos Nacionales de la Salud; NIH || National Cancer Institute; NCI; Instituto Nacional del Cáncer || National Institute of Biomedical Imaging and Bioengineering; NIH National Institute of Biomedical Imaging & Bioengineering; National Institute of Biomedical Imaging & Bioengineering; The National Institute of Biomedical Imaging and Bioengineering; NIH National Institute of Biomedical Imaging and Bioengineering; Instituto Nacional de Imágenes Biomédicas y Bioingeniería; NIBIB || National Institute of Neurological Disorders and Stroke; National Institute of Neurological Disorders & Stroke; NIH\/National Institute of Neurological Disorders and Stroke; The National Institute of Neurological Disorders and Stroke; Instituto Nacional de Trastornos Neurológicos y Accidentes Cerebrovasculares; NIH National Institute of Neurological Disorders and Stroke; NINDS | D49: https://openalex.org/funders/f4320332161 || https://openalex.org/funders/f4320337351 || https://openalex.org/funders/f4320337359 || https://openalex.org/funders/f4320337363 | E49: =sample_20250925!E49 -> 4 | F49: =IF(sample_20250925!$C49=C49,sample_20250925!F49, NA()) -> 4 | G49: =IF(sample_20250925!$C49=$C49,sample_20250925!G49, NA()) -> 0 | H49: Jacob | M49: =F49/E49 -> 1 | N49: =G49/E49 -> 0 | O49: =IFERROR(__xludf.DUMMYFUNCTION("INT(FILTER(GT(F49,0),ISNUMBER(F49)))"),1.0) -> 1 | P49: =F49/(F49+G49) -> 1 | Q49: =IFERROR(__xludf.DUMMYFUNCTION("INT(FILTER(EQ(E49,F49),ISNUMBER(E49),ISNUMBER(F49)))"),1.0) -> 1
A50: The Suggestion of Revised Criteria for Endoscopic Resection of Differentiated-Type Submucosal Gastric Cancer | B50: https://doi.org/10.1245/s10434-019-08102-3 | C50: National Research Foundation of Korea; NRF; 한국연구재단이 창의적 연구와 | D50: https://openalex.org/funders/f4320322120 | E50: =sample_20250925!E50 -> 2 | F50: =IF(sample_20250925!$C50=C50,sample_20250925!F50, NA()) -> 1 | G50: =IF(sample_20250925!$C50=$C50,sample_20250925!G50, NA()) -> 0 | H50: Jacob | M50: =F50/E50 -> 0.5 | N50: =G50/E50 -> 0 | O50: =IFERROR(__xludf.DUMMYFUNCTION("INT(FILTER(GT(F50,0),ISNUMBER(F50)))"),1.0) -> 1 | P50: =F50/(F50+G50) -> 1 | Q50: =IFERROR(__xludf.DUMMYFUNCTION("INT(FILTER(EQ(E50,F50),ISNUMBER(E50),ISNUMBER(F50)))"),0.0) -> 0
A51: Professional identity research in the health professions-a scoping review | B51: https://doi.org/10.1007/s10459-022-10171-1 | C51: Research Triangle Park Foundation; RTP || Council of Australasian University Librarians; CAUL; Council of Australian University Librarians | D51: https://openalex.org/institutions/i1309191912 || https://openalex.org/institutions/i3009606475 | E51: =sample_20250925!E51 -> 2 | F51: 1 | G51: 1 | H51: Jacob | M51: =F51/E51 -> 0.5 | N51: =G51/E51 -> 0.5 | O51: =IFERROR(__xludf.DUMMYFUNCTION("INT(FILTER(GT(F51,0),ISNUMBER(F51)))"),1.0) -> 1 | P51: =F51/(F51+G51) -> 0.5 | Q51: =IFERROR(__xludf.DUMMYFUNCTION("INT(FILTER(EQ(E51,F51),ISNUMBER(E51),ISNUMBER(F51)))"),0.0) -> 0
A52: Preparation of hexagonal and amorphous chromium oxyhydroxides by facile hydrolysis of K x CrO y | B52: https://doi.org/10.1016/S1003-6326(20)65305-5 | C52: NOT MATCHED || Chongqing University of Arts and Sciences; CUAS || Natural Science Foundation of Chongqing; Chonqing Natural Science Foundation; Municipal Natural Science Foundation of Chongqing; Natural Science Foundation of Chongqing Municipality; 重庆市自然科学基金 || Chongqing Municipal Education Commission; Chongqing Municipality Education Commission; Education Commission of Chongqing Municipality; 重庆市教育委员会; CQMEC | D52: https://openalex.org/funders/f4320321551 || https://openalex.org/funders/f4320324805 || https://openalex.org/funders/f4320323172 | E52: =sample_20250925!E52 -> 4 | F52: 4 | G52: 0 | H52: Jacob | M52: =F52/E52 -> 1 | N52: =G52/E52 -> 0 | O52: =IFERROR(__xludf.DUMMYFUNCTION("INT(FILTER(GT(F52,0),ISNUMBER(F52)))"),1.0) -> 1 | P52: =F52/(F52+G52) -> 1 | Q52: =IFERROR(__xludf.DUMMYFUNCTION("INT(FILTER(EQ(E52,F52),ISNUMBER(E52),ISNUMBER(F52)))"),1.0) -> 1
A53: The Riemann-Hilbert Approach and N-Soliton Solutions of a Four-Component Nonlinear Schrodinger Equation | B53: https://doi.org/10.4208/eajam.100620.170920 | C53: Fundamental Research Funds for the Central Universities; Fundamental Research Funds for the Central Universities of China; Fundamental Research Fund for the Central Universities | D53: https://openalex.org/funders/f4320335787 | E53: =sample_20250925!E53 -> 7 | F53: =IF(sample_20250925!$C53=C53,sample_20250925!F53, NA()) -> 1 | G53: =IF(sample_20250925!$C53=$C53,sample_20250925!G53, NA()) -> 0 | H53: Jacob | M53: =F53/E53 -> 0.14285714 | N53: =G53/E53 -> 0 | O53: =IFERROR(__xludf.DUMMYFUNCTION("INT(FILTER(GT(F53,0),ISNUMBER(F53)))"),1.0) -> 1 | P53: =F53/(F53+G53) -> 1 | Q53: =IFERROR(__xludf.DUMMYFUNCTION("INT(FILTER(EQ(E53,F53),ISNUMBER(E53),ISNUMBER(F53)))"),0.0) -> 0
A54: Parental Life Span and Polygenic Risk Score of Longevity Are Associated With White Matter Hyperintensities | B54: https://doi.org/10.1093/gerona/glab323 | C54: National Health and Medical Research Council; NHMRC || NOT MATCHED || Australian Government; Federal Government; Commonwealth Government of Australia; Commonwealth Government; Government of Australia | D54: https://openalex.org/funders/f4320315885 || https://openalex.org/funders/f4320334705 | E54: 2 | F54: 2 | G54: 0 | H54: Jacob | M54: =F54/E54 -> 1 | N54: =G54/E54 -> 0 | O54: =IFERROR(__xludf.DUMMYFUNCTION("INT(FILTER(GT(F54,0),ISNUMBER(F54)))"),1.0) -> 1 | P54: =F54/(F54+G54) -> 1 | Q54: =IFERROR(__xludf.DUMMYFUNCTION("INT(FILTER(EQ(E54,F54),ISNUMBER(E54),ISNUMBER(F54)))"),1.0) -> 1
A55: Developing Concentration Index of Industrial and Occupational Accidents: The Case of European Countries | B55: https://doi.org/10.1016/j.shaw.2020.05.003 | C55: Ministry of Education; 교육부; MOE; Ministry of Education of the Republic of Korea || National Research Foundation of Korea; NRF; 한국연구재단이 창의적 연구와 | D55: https://openalex.org/funders/f4320321408 || https://openalex.org/funders/f4320322120 | E55: =sample_20250925!E55 -> 2 | F55: =IF(sample_20250925!$C55=C55,sample_20250925!F55, NA()) -> 2 | G55: =IF(sample_20250925!$C55=$C55,sample_20250925!G55, NA()) -> 0 | H55: Jacob | M55: =F55/E55 -> 1 | N55: =G55/E55 -> 0 | O55: =IFERROR(__xludf.DUMMYFUNCTION("INT(FILTER(GT(F55,0),ISNUMBER(F55)))"),1.0) -> 1 | P55: =F55/(F55+G55) -> 1
A56: Analysis of the Fee-to-Tax Reform on Water Resources in China | B56: https://doi.org/10.3389/fenrg.2021.752592 | C56: Guangdong Office of Philosophy and Social Science; Planning Office of Philosophy and Social Science of Guangdong Province; 广东省哲学社会科学; 广东省哲学社会科学规划领导小组办公室; GDPPLGOPSS; Guangdong Planning Office of Philosophy and Social Science; Guangdong Provincial Planning Office of Philosophy and Social Science | D56: https://openalex.org/funders/f4320326679 | E56: =sample_20250925!E56 -> 1 | F56: =IF(sample_20250925!$C56=C56,sample_20250925!F56, NA()) -> 1 | G56: =IF(sample_20250925!$C56=$C56,sample_20250925!G56, NA()) -> 0 | H56: Jacob | M56: =F56/E56 -> 1 | N56: =G56/E56 -> 0 | O56: =IFERROR(__xludf.DUMMYFUNCTION("INT(FILTER(GT(F56,0),ISNUMBER(F56)))"),1.0) -> 1 | P56: =F56/(F56+G56) -> 1 | Q56: =IFERROR(__xludf.DUMMYFUNCTION("INT(FILTER(EQ(E56,F56),ISNUMBER(E56),ISNUMBER(F56)))"),1.0) -> 1
A57: SNP Function Portal: a web database for exploring the function implication of SNP alleles | B57: https://doi.org/10.1093/bioinformatics/btl241 | C57: National Institute on Drug Abuse; NIDA; The National Institute on Drug Abuse; Instituto Nacional sobre el Abuso de Drogas; Instituto Nacional sobre el Abuso de Drogas de Estados Unidos || National Institute on Drug Abuse; NIDA; The National Institute on Drug Abuse; Instituto Nacional sobre el Abuso de Drogas; Instituto Nacional sobre el Abuso de Drogas de Estados Unidos | D57: https://openalex.org/funders/f4320337347 | E57: =sample_20250925!E57 -> 2 | F57: =IF(sample_20250925!$C57=C57,sample_20250925!F57, NA()) -> 1 | G57: =IF(sample_20250925!$C57=$C57,sample_20250925!G57, NA()) -> 0 | H57: Jacob | M57: =F57/E57 -> 0.5 | N57: =G57/E57 -> 0 | O57: =IFERROR(__xludf.DUMMYFUNCTION("INT(FILTER(GT(F57,0),ISNUMBER(F57)))"),1.0) -> 1 | P57: =F57/(F57+G57) -> 1 | Q57: =IFERROR(__xludf.DUMMYFUNCTION("INT(FILTER(EQ(E57,F57),ISNUMBER(E57),ISNUMBER(F57)))"),0.0) -> 0
A58: List-Based OMP and an Enhanced Model for DOA Estimation With Nonuniform Arrays | B58: https://doi.org/10.1109/TAES.2021.3087836 | C58: Pontifícia Universidade Católica do Rio de Janeiro; PUC-Rio; Pontifical Catholic University of Rio de Janeiro || Conselho Nacional de Desenvolvimento Científico e Tecnológico; National Council for Scientific and Technological Development; Brazilian National Council for Research and Development; CNPq || Fundação Carlos Chagas Filho de Amparo à Pesquisa do Estado do Rio de Janeiro; FAPERJ; Carlos Chagas Filho Foundation for Research Support in Rio de Janeiro; Research Support Foundation for the State of Rio de Janeiro; Fundação de Amparo à Pesquisa do Estado do Rio de Janeiro || Fundação de Amparo à Pesquisa do Estado de São Paulo; São Paulo Research Foundation; Foundation for Research Support of the State of São Paulo; FAPESP; State of São Paulo Research Foundation | D58: https://openalex.org/funders/f4320322025 || https://openalex.org/funders/f4320331129 || https://openalex.org/funders/f4320320997 || https://openalex.org/funders/f4320322749 | E58: =sample_20250925!E58 -> 4 | F58: 4 | G58: 0 | H58: Jacob | M58: =F58/E58 -> 1 | N58: =G58/E58 -> 0 | O58: =IFERROR(__xludf.DUMMYFUNCTION("INT(FILTER(GT(F58,0),ISNUMBER(F58)))"),1.0) -> 1 | P58: =F58/(F58+G58) -> 1 | Q58: =IFERROR(__xludf.DUMMYFUNCTION("INT(FILTER(EQ(E58,F58),ISNUMBER(E58),ISNUMBER(F58)))"),1.0) -> 1
A59: Reactions Leading to Controlled Hydrophilicity/Hydrophobicity of Surfaces | B59: https://doi.org/10.2174/1385272821666170428123013 | C59: National Center of Competence in Research Quantum Science and Technology; NCCR QSIT; NCCR "QSIT - Quantum Science and Technology"; NCCR Quantum Science and Technology; NCCR 'QSIT - Quantum Science and Technology | D59: https://openalex.org/funders/f4320335366 | E59: =sample_20250925!E59 -> 1 | F59: =IF(sample_20250925!$C59=C59,sample_20250925!F59, NA()) -> 0 | G59: =IF(sample_20250925!$C59=$C59,sample_20250925!G59, NA()) -> 1 | H59: Jacob | M59: =F59/E59 -> 0 | N59: =G59/E59 -> 1 | O59: =IFERROR(__xludf.DUMMYFUNCTION("INT(FILTER(GT(F59,0),ISNUMBER(F59)))"),0.0) -> 0 | P59: =F59/(F59+G59) -> 0 | Q59: =IFERROR(__xludf.DUMMYFUNCTION("INT(FILTER(EQ(E59,F59),ISNUMBER(E59),ISNUMBER(F59)))"),0.0) -> 0
A60: Text Image Deblurring Using Kernel Sparsity Prior | B60: https://doi.org/10.1109/TCYB.2018.2876511 | C60: National Natural Science Foundation of China; NNSF of China; Guójiā Zìrán Kēxué Jījīn Wěiyuánhuì; NSF of China; The National Natural Science Foundation of China; 国家自然科学基金委员会; National Nature Science Foundation of China; NSFC; National Science Foundation of China; Natural Science Foundation of China; NNSFC; Chinese National Science Foundation; NNSF || NOT MATCHED || NOT MATCHED || Natural Science Foundation of Beijing Municipality; Beijing Municipal Natural Science Foundation; Natural Science Foundation of Beijing; Beijing Natural Science Foundation | D60: https://openalex.org/funders/f4320322919 || https://openalex.org/funders/f4320321001 | E60: =sample_20250925!E60 -> 4 | F60: 2 | G60: 0 | H60: Jacob | M60: =F60/E60 -> 0.5 | N60: =G60/E60 -> 0 | O60: =IFERROR(__xludf.DUMMYFUNCTION("INT(FILTER(GT(F60,0),ISNUMBER(F60)))"),1.0) -> 1 | P60: =F60/(F60+G60) -> 1 | Q60: =IFERROR(__xludf.DUMMYFUNCTION("INT(FILTER(EQ(E60,F60),ISNUMBER(E60),ISNUMBER(F60)))"),0.0) -> 0
A61: Bifurcation Phenomena of Nonlinear Waves in a Generalized Zakharov-Kuznetsov Equation | B61: https://doi.org/10.1155/2013/812120 | C61: National Natural Science Foundation of China; NNSF of China; Guójiā Zìrán Kēxué Jījīn Wěiyuánhuì; NSF of China; The National Natural Science Foundation of China; 国家自然科学基金委员会; National Nature Science Foundation of China; NSFC; National Science Foundation of China; Natural Science Foundation of China; NNSFC; Chinese National Science Foundation; NNSF || NOT MATCHED | D61: https://openalex.org/funders/f4320321001 | E61: =sample_20250925!E61 -> 2 | F61: 1 | G61: 0 | H61: Jacob | M61: =F61/E61 -> 0.5 | N61: =G61/E61 -> 0 | O61: =IFERROR(__xludf.DUMMYFUNCTION("INT(FILTER(GT(F61,0),ISNUMBER(F61)))"),1.0) -> 1 | P61: =F61/(F61+G61) -> 1 | Q61: =IFERROR(__xludf.DUMMYFUNCTION("INT(FILTER(EQ(E61,F61),ISNUMBER(E61),ISNUMBER(F61)))"),0.0) -> 0
A62: Gall size of Dryocosmus kuriphilus limits down-regulation by native parasitoids | B62: https://doi.org/10.1007/s10530-020-02427-x | C62: Ministerio de Economía y Competitividad; MINECO; MEC; Ministry of Economy and Competitiveness | D62: https://openalex.org/funders/f4320321837 | E62: =sample_20250925!E62 -> 1 | F62: =IF(sample_20250925!$C62=C62,sample_20250925!F62, NA()) -> 1 | G62: =IF(sample_20250925!$C62=$C62,sample_20250925!G62, NA()) -> 0 | H62: Jacob | M62: =F62/E62 -> 1 | N62: =G62/E62 -> 0 | O62: =IFERROR(__xludf.DUMMYFUNCTION("INT(FILTER(GT(F62,0),ISNUMBER(F62)))"),1.0) -> 1 | P62: =F62/(F62+G62) -> 1 | Q62: =IFERROR(__xludf.DUMMYFUNCTION("INT(FILTER(EQ(E62,F62),ISNUMBER(E62),ISNUMBER(F62)))"),1.0) -> 1
A63: A multiplex serologic platform for diagnosis of tick-borne diseases | B63: https://doi.org/10.1038/s41598-018-21349-2 | C63: Steven and Alexandra Cohen Foundation; The Steven & Alexandra Cohen Foundation, Inc.; Steven & Alexandra Cohen Foundation; Steven & Alexandra Cohen Foundation, Inc. || NOT MATCHED || NOT MATCHED || National Institute of Allergy and Infectious Diseases; NIAID; Instituto Nacional de Alergias y Enfermedades Infecciosas | D63: https://openalex.org/funders/f4320316446 || https://openalex.org/funders/f4320337355 | E63: 3 | F63: 2 | G63: 0 | H63: Jacob | M63: =F63/E63 -> 0.66666667 | N63: =G63/E63 -> 0 | O63: =IFERROR(__xludf.DUMMYFUNCTION("INT(FILTER(GT(F63,0),ISNUMBER(F63)))"),1.0) -> 1 | P63: =F63/(F63+G63) -> 1 | Q63: =IFERROR(__xludf.DUMMYFUNCTION("INT(FILTER(EQ(E63,F63),ISNUMBER(E63),ISNUMBER(F63)))"),0.0) -> 0
A64: Coordinated energy management for an islanded microgrid with multi-energy and multi-storage units | B64: https://doi.org/10.1016/j.egyr.2021.11.131 | C64: National Natural Science Foundation of China; NNSF of China; Guójiā Zìrán Kēxué Jījīn Wěiyuánhuì; NSF of China; The National Natural Science Foundation of China; 国家自然科学基金委员会; National Nature Science Foundation of China; NSFC; National Science Foundation of China; Natural Science Foundation of China; NNSFC; Chinese National Science Foundation; NNSF | D64: https://openalex.org/funders/f4320321001 | E64: =sample_20250925!E64 -> 1 | F64: =IF(sample_20250925!$C64=C64,sample_20250925!F64, NA()) -> 1 | G64: =IF(sample_20250925!$C64=$C64,sample_20250925!G64, NA()) -> 0 | H64: Jacob | M64: =F64/E64 -> 1 | N64: =G64/E64 -> 0 | O64: =IFERROR(__xludf.DUMMYFUNCTION("INT(FILTER(GT(F64,0),ISNUMBER(F64)))"),1.0) -> 1 | P64: =F64/(F64+G64) -> 1 | Q64: =IFERROR(__xludf.DUMMYFUNCTION("INT(FILTER(EQ(E64,F64),ISNUMBER(E64),ISNUMBER(F64)))"),1.0) -> 1
A65: Dynamic Characteristics Analysis of ISD Suspension System under Different Working Conditions | B65: https://doi.org/10.3390/math9121345 | C65: State Key Laboratory of Automotive Simulation and Control; State Key Lab of Automotive Simulation and Control; 汽车动态模拟国家重点实验室; State Key Laboratory of Automobile Simulation and Control; 汽车仿真与控制国家重点实验室; State Key Lab of Automobile Simulation and Control || National Natural Science Foundation of China; NNSF of China; Guójiā Zìrán Kēxué Jījīn Wěiyuánhuì; NSF of China; The National Natural Science Foundation of China; 国家自然科学基金委员会; National Nature Science Foundation of China; NSFC; National Science Foundation of China; Natural Science Foundation of China; NNSFC; Chinese National Science Foundation; NNSF | D65: https://openalex.org/institutions/i4392738231 || https://openalex.org/funders/f4320321001 | E65: =sample_20250925!E65 -> 2 | F65: 2 | G65: 0 | H65: Jacob | M65: =F65/E65 -> 1 | N65: =G65/E65 -> 0 | O65: =IFERROR(__xludf.DUMMYFUNCTION("INT(FILTER(GT(F65,0),ISNUMBER(F65)))"),1.0) -> 1 | P65: =F65/(F65+G65) -> 1 | Q65: =IFERROR(__xludf.DUMMYFUNCTION("INT(FILTER(EQ(E65,F65),ISNUMBER(E65),ISNUMBER(F65)))"),1.0) -> 1
A66: Effects of Prunella vulgaris on the Mice Immune Function | B66: https://doi.org/10.1371/journal.pone.0077355 | C66: National High-tech Research and Development Program; National High-tech R&D Program (863 Program); State High-Tech Development Plan; 863 Program || Natural Science Foundation of Guangdong Province; Guangdong Natural Science Foundation; Guangdong Provincial Natural Science Foundation; Natural Science Foundation of Guangdong || Science and Technology Planning Project of Guangdong Province; Key Project of Guangdong Province Science & Technology Plan; Science and Technology Program of Guangdong; Guangdong Science and Technology Foundation; Science and Technology Projects of Guangdong Province; Scientific and Technological Plan of Guangdong Province; S&T Project of Guangdong Province; Guangdong Science and Technology Program || NOT MATCHED | D66: https://openalex.org/funders/f4320335773 || https://openalex.org/funders/f4320321921 || https://openalex.org/funders/f4320335795 | E66: =sample_20250925!E66 -> 4 | F66: 3 | G66: 0 | H66: Jacob | M66: =F66/E66 -> 0.75 | N66: =G66/E66 -> 0 | O66: =IFERROR(__xludf.DUMMYFUNCTION("INT(FILTER(GT(F66,0),ISNUMBER(F66)))"),1.0) -> 1 | P66: =F66/(F66+G66) -> 1
A67: Dynamic covalent chemistry constrained diphenylethenes: control over reactivity and luminescence both in solution and in the solid state | B67: https://doi.org/10.1039/d2qo00057a | C67: National Natural Science Foundation of China; NNSF of China; Guójiā Zìrán Kēxué Jījīn Wěiyuánhuì; NSF of China; The National Natural Science Foundation of China; 国家自然科学基金委员会; National Nature Science Foundation of China; NSFC; National Science Foundation of China; Natural Science Foundation of China; NNSFC; Chinese National Science Foundation; NNSF || NOT MATCHED || NOT MATCHED || Science Fund for Distinguished Young Scholars of Fujian Province; 福建省杰出青年自然科学基金; NSF for Young Scholarsof Fujian Province; Science Funds for Distinguished Young Scientists of Fujian Province; Natural Science Foundation of Fujian Province for Distinguished Young Scientists; National Science Foundation for Distinguished Young Scholars of Fujian Province; Fujian Provincial Funds for Distinguished Young Scientists || NOT MATCHED | D67: https://openalex.org/funders/f4320336815 || https://openalex.org/funders/f4320321001 | E67: =sample_20250925!E67 -> 5 | F67: 2 | G67: 0 | H67: Jacob | M67: =F67/E67 -> 0.4 | N67: =G67/E67 -> 0 | O67: =IFERROR(__xludf.DUMMYFUNCTION("INT(FILTER(GT(F67,0),ISNUMBER(F67)))"),1.0) -> 1 | P67: =F67/(F67+G67) -> 1 | Q67: =IFERROR(__xludf.DUMMYFUNCTION("INT(FILTER(EQ(E67,F67),ISNUMBER(E67),ISNUMBER(F67)))"),0.0) -> 0
A68: Dynamic changes in positive interferon-gamma release assay in a dialysis population: An observational cohort study | B68: https://doi.org/10.1016/j.jinf.2013.07.029 | C68: NOT MATCHED || NOT MATCHED || National Science Council; National Science Council, Taiwan; National Science Council of Taiwan; NSC | D68: https://openalex.org/funders/f4320321040 | E68: =sample_20250925!E68 -> 3 | F68: 1 | G68: 0 | H68: Jacob | M68: =F68/E68 -> 0.33333333 | N68: =G68/E68 -> 0 | O68: =IFERROR(__xludf.DUMMYFUNCTION("INT(FILTER(GT(F68,0),ISNUMBER(F68)))"),1.0) -> 1 | P68: =F68/(F68+G68) -> 1 | Q68: =IFERROR(__xludf.DUMMYFUNCTION("INT(FILTER(EQ(E68,F68),ISNUMBER(E68),ISNUMBER(F68)))"),0.0) -> 0
A69: Cystathionine beta-synthase is required for body iron homeostasis | B69: https://doi.org/10.1002/hep.29499 | C69: National Natural Science Foundation of China; NNSF of China; Guójiā Zìrán Kēxué Jījīn Wěiyuánhuì; NSF of China; The National Natural Science Foundation of China; 国家自然科学基金委员会; National Nature Science Foundation of China; NSFC; National Science Foundation of China; Natural Science Foundation of China; NNSFC; Chinese National Science Foundation; NNSF || Research Grants Council, University Grants Committee; 研究資助局; 研究資助局 || NOT MATCHED | D69: https://openalex.org/funders/f4320321592 || https://openalex.org/funders/f4320321001 | E69: =sample_20250925!E69 -> 3 | F69: 2 | G69: 0 | H69: Jacob | M69: =F69/E69 -> 0.66666667 | N69: =G69/E69 -> 0 | O69: =IFERROR(__xludf.DUMMYFUNCTION("INT(FILTER(GT(F69,0),ISNUMBER(F69)))"),1.0) -> 1 | P69: =F69/(F69+G69) -> 1 | Q69: =IFERROR(__xludf.DUMMYFUNCTION("INT(FILTER(EQ(E69,F69),ISNUMBER(E69),ISNUMBER(F69)))"),0.0) -> 0
A70: Contribution of herd characteristics to best linear unbiased estimates of slaughter traits in beef cattle | B70: https://doi.org/10.1016/j.animal.2021.100321 | C70: NOT MATCHED || Science Foundation Ireland; SFI | D70: https://openalex.org/funders/f4320320847 | E70: =sample_20250925!E70 -> 2 | F70: 1 | G70: 0 | H70: Jacob | M70: =F70/E70 -> 0.5 | N70: =G70/E70 -> 0 | O70: =IFERROR(__xludf.DUMMYFUNCTION("INT(FILTER(GT(F70,0),ISNUMBER(F70)))"),1.0) -> 1 | P70: =F70/(F70+G70) -> 1 | Q70: =IFERROR(__xludf.DUMMYFUNCTION("INT(FILTER(EQ(E70,F70),ISNUMBER(E70),ISNUMBER(F70)))"),0.0) -> 0
A71: Non-commutative Iwasawa theory of elliptic curves at primes of multiplicative reduction | B71: https://doi.org/10.1017/S0305004112000564 | C71: Engineering and Physical Sciences Research Council; EPSRC || Engineering and Physical Sciences Research Council; EPSRC || Engineering and Physical Sciences Research Council; EPSRC | D71: https://openalex.org/funders/f4320334627 | E71: =sample_20250925!E71 -> 1 | F71: =IF(sample_20250925!$C71=C71,sample_20250925!F71, NA()) -> 1 | G71: =IF(sample_20250925!$C71=$C71,sample_20250925!G71, NA()) -> 0 | H71: Jacob | M71: =F71/E71 -> 1 | N71: =G71/E71 -> 0 | O71: =IFERROR(__xludf.DUMMYFUNCTION("INT(FILTER(GT(F71,0),ISNUMBER(F71)))"),1.0) -> 1 | P71: =F71/(F71+G71) -> 1 | Q71: =IFERROR(__xludf.DUMMYFUNCTION("INT(FILTER(EQ(E71,F71),ISNUMBER(E71),ISNUMBER(F71)))"),1.0) -> 1
A72: Enhancement of Vindoline and Catharanthine Accumulation, Antioxidant Enzymes Activities, and Gene Expression Levels in Catharanthus roseus Leaves by Chitooligosaccharides Elicitation | B72: https://doi.org/10.3390/md20030188 | C72: NOT MATCHED || NOT MATCHED | E72: =sample_20250925!E72 -> 2 | F72: 0 | G72: 0 | H72: Jacob | M72: =F72/E72 -> 0 | N72: =G72/E72 -> 0 | O72: =IFERROR(__xludf.DUMMYFUNCTION("INT(FILTER(GT(F72,0),ISNUMBER(F72)))"),0.0) -> 0 | P72: =F72/(F72+G72) -> #DIV/0! | Q72: =IFERROR(__xludf.DUMMYFUNCTION("INT(FILTER(EQ(E72,F72),ISNUMBER(E72),ISNUMBER(F72)))"),0.0) -> 0
A73: Accurate Electromagnetic Analysis of Interconnect Structures Based on a Mixed Method | B73: https://doi.org/10.1109/LMWC.2020.3008494 | C73: National Natural Science Foundation of China; NNSF of China; Guójiā Zìrán Kēxué Jījīn Wěiyuánhuì; NSF of China; The National Natural Science Foundation of China; 国家自然科学基金委员会; National Nature Science Foundation of China; NSFC; National Science Foundation of China; Natural Science Foundation of China; NNSFC; Chinese National Science Foundation; NNSF || NOT MATCHED | D73: https://openalex.org/funders/f4320321001 | E73: =sample_20250925!E73 -> 2 | F73: 1 | G73: 0 | H73: Jacob | M73: =F73/E73 -> 0.5 | N73: =G73/E73 -> 0 | O73: =IFERROR(__xludf.DUMMYFUNCTION("INT(FILTER(GT(F73,0),ISNUMBER(F73)))"),1.0) -> 1 | P73: =F73/(F73+G73) -> 1 | Q73: =IFERROR(__xludf.DUMMYFUNCTION("INT(FILTER(EQ(E73,F73),ISNUMBER(E73),ISNUMBER(F73)))"),0.0) -> 0
A74: Effect of MgO promoter on Ru/gamma-Al2O3 catalysts for tricyclopentadiene hydrogenation | B74: https://doi.org/10.1016/j.cattod.2020.01.003 | C74: Korea Institute of Energy Technology Evaluation and Planning; KETEP | D74: https://openalex.org/funders/f4320335199 | E74: =sample_20250925!E74 -> 1 | F74: =IF(sample_20250925!$C74=C74,sample_20250925!F74, NA()) -> 1 | G74: =IF(sample_20250925!$C74=$C74,sample_20250925!G74, NA()) -> 0 | H74: Jacob | M74: =F74/E74 -> 1 | N74: =G74/E74 -> 0 | O74: =IFERROR(__xludf.DUMMYFUNCTION("INT(FILTER(GT(F74,0),ISNUMBER(F74)))"),1.0) -> 1 | P74: =F74/(F74+G74) -> 1 | Q74: =IFERROR(__xludf.DUMMYFUNCTION("INT(FILTER(EQ(E74,F74),ISNUMBER(E74),ISNUMBER(F74)))"),1.0) -> 1
A75: General Three-Population Multi-Strategy Evolutionary Games for Long-Term On-Grid Bidding of Generation-Side Electricity Market | B75: https://doi.org/10.1109/ACCESS.2020.3046327 | C75: NOT MATCHED || NOT MATCHED || NOT MATCHED || Natural Science Foundation of Guangdong Province; Guangdong Natural Science Foundation; Guangdong Provincial Natural Science Foundation; Natural Science Foundation of Guangdong || Natural Science Foundation of Guangxi Province; Guangxi Natural Science Foundation | D75: https://openalex.org/funders/f4320322768 || https://openalex.org/funders/f4320321921 | E75: =sample_20250925!E75 -> 5 | F75: 2 | G75: 0 | H75: Jacob | M75: =F75/E75 -> 0.4 | N75: =G75/E75 -> 0 | O75: =IFERROR(__xludf.DUMMYFUNCTION("INT(FILTER(GT(F75,0),ISNUMBER(F75)))"),1.0) -> 1 | P75: =F75/(F75+G75) -> 1 | Q75: =IFERROR(__xludf.DUMMYFUNCTION("INT(FILTER(EQ(E75,F75),ISNUMBER(E75),ISNUMBER(F75)))"),0.0) -> 0
A76: Molnupiravir-A Novel Oral Anti-SARS-CoV-2 Agent | B76: https://doi.org/10.3390/antibiotics10111294 | C76: Ministry of Science and Technology; MOST; Ministry of Science and Technology of the Socialist Republic of Vietnam; Vietnamese Ministry of Science and Technology || Ministry of Health and Welfare; 衛生福利部; Ministry of Health and Welfare, Taiwan; MOHW || National Cheng Kung University Hospital; NCKU Hospital; NCKU | D76: https://openalex.org/funders/f4320309618 || https://openalex.org/funders/f4320322933 || https://openalex.org/funders/f4320310848 | E76: =sample_20250925!E76 -> 3 | F76: 2 | G76: 1 | H76: Jacob | M76: =F76/E76 -> 0.66666667 | N76: =G76/E76 -> 0.33333333 | O76: =IFERROR(__xludf.DUMMYFUNCTION("INT(FILTER(GT(F76,0),ISNUMBER(F76)))"),1.0) -> 1 | P76: =F76/(F76+G76) -> 0.66666667 | Q76: =IFERROR(__xludf.DUMMYFUNCTION("INT(FILTER(EQ(E76,F76),ISNUMBER(E76),ISNUMBER(F76)))"),0.0) -> 0
A77: Fractionalized Fermi liquid in a Kondo-Heisenberg model | B77: https://doi.org/10.1103/PhysRevB.94.165114 | C77: U.S. Department of Energy; US Department of Energy; DOE; United States Department of Energy; Department of Energy; USDOE; Energy Department; ENERGY.GOV; USADOE; US DOE | D77: https://openalex.org/funders/f4320306084 | E77: =sample_20250925!E77 -> 1 | F77: 1 | G77: 0 | H77: Jacob | M77: =F77/E77 -> 1 | N77: =G77/E77 -> 0 | O77: =IFERROR(__xludf.DUMMYFUNCTION("INT(FILTER(GT(F77,0),ISNUMBER(F77)))"),1.0) -> 1 | P77: =F77/(F77+G77) -> 1
A78: Features of a twin-arginine signal peptide required for recognition by a Tat proofreading chaperone | B78: https://doi.org/10.1016/j.febslet.2008.10.049 | C78: Biotechnology and Biological Sciences Research Council; BBSRC; The Biotechnology And Biological Sciences Research Council || NOT MATCHED || Biotechnology and Biological Sciences Research Council; BBSRC; The Biotechnology And Biological Sciences Research Council || Medical Research Council; MRC; UK Medical Research Council || Medical Research Council; MRC; UK Medical Research Council | D78: https://openalex.org/funders/f4320334626 || https://openalex.org/funders/f4320334629 | E78: =sample_20250925!E78 -> 2 | F78: 2 | G78: 0 | H78: Jacob | M78: =F78/E78 -> 1 | N78: =G78/E78 -> 0 | O78: =IFERROR(__xludf.DUMMYFUNCTION("INT(FILTER(GT(F78,0),ISNUMBER(F78)))"),1.0) -> 1 | P78: =F78/(F78+G78) -> 1 | Q78: =IFERROR(__xludf.DUMMYFUNCTION("INT(FILTER(EQ(E78,F78),ISNUMBER(E78),ISNUMBER(F78)))"),1.0) -> 1
A79: Comparison of Unilateral Versus Bilateral Upper Extremity Task Performance After Stroke | B79: https://doi.org/10.1310/tsr1904-294 | C79: National Institutes of Health; US National Institutes of Health; Institutos Nacionales de la Salud; NIH || Foundation for Physical Therapy; Foundation for Physical Therapy Research, Inc; Foundation for Physical Therapy Research; Foundation for Physical Therapy Inc; Foundation for Physical Therapy Research, Inc.; Foundation For Physical Therapy Research Inc; FPT; Foundation for Physical Therapy, Inc.; Foundation4PT; FPTR || Eunice Kennedy Shriver National Institute of Child Health and Human Development; NIH Eunice Kennedy Shriver National Institute of Child Health and Human Development; NIH Eunice Kennedy Shriver National Institute of Child Health & Human Development; Eunice Kennedy Shriver National Institute of Child Health and Human Development at the National Institutes of Health; NICHD; National Institutes of Health\/Eunice Kennedy Shriver National Institute of Child Health & Human Development; Eunice Kennedy Shriver National Institute of Child Health & Human Development; Instituto Nacional de Salud Infantil y Desarrollo Humano Eunice Kennedy Shriver; NIH\/NICHD; Eunice Kennedy Shriver National Institute of Child Health and Human Development of the National Institutes of Health; NIH\/Eunice Kennedy Shriver National Institute of Child Health and Human Development || Eunice Kennedy Shriver National Institute of Child Health and Human Development; NIH Eunice Kennedy Shriver National Institute of Child Health and Human Development; NIH Eunice Kennedy Shriver National Institute of Child Health & Human Development; Eunice Kennedy Shriver National Institute of Child Health and Human Development at the National Institutes of Health; NICHD; National Institutes of Health\/Eunice Kennedy Shriver National Institute of Child Health & Human Development; Eunice Kennedy Shriver National Institute of Child Health & Human Development; Instituto Nacional de Salud Infantil y Desarrollo Humano Eunice Kennedy Shriver; NIH\/NICHD; Eunice Kennedy Shriver National Institute of Child Health and Human Development of the National Institutes of Health; NIH\/Eunice Kennedy Shriver National Institute of Child Health and Human Development | D79: https://openalex.org/funders/f4320332161 || https://openalex.org/funders/f4320311480 || https://openalex.org/funders/f4320337611 | E79: =sample_20250925!E79 -> 3 | F79: =IF(sample_20250925!$C79=C79,sample_20250925!F79, NA()) -> 3 | G79: =IF(sample_20250925!$C79=$C79,sample_20250925!G79, NA()) -> 0 | H79: Jacob | M79: =F79/E79 -> 1 | N79: =G79/E79 -> 0 | O79: =IFERROR(__xludf.DUMMYFUNCTION("INT(FILTER(GT(F79,0),ISNUMBER(F79)))"),1.0) -> 1 | P79: =F79/(F79+G79) -> 1 | Q79: =IFERROR(__xludf.DUMMYFUNCTION("INT(FILTER(EQ(E79,F79),ISNUMBER(E79),ISNUMBER(F79)))"),1.0) -> 1
A80: In Helicobacter pylori auto-inducer-2, but not LuxS/MccAB catalysed reverse transsulphuration, regulates motility through modulation of flagellar gene transcription | B80: https://doi.org/10.1186/1471-2180-10-210 | C80: NOT MATCHED || NOT MATCHED || University of Nottingham; The University of Nottingham; University College, Nottingham; Nottingham University || Horowitz Foundation for Social Policy; The Horowitz Foundation for Social Policy; HFSP; Horowitz Foundation || Biotechnology and Biological Sciences Research Council; BBSRC; The Biotechnology And Biological Sciences Research Council | D80: https://openalex.org/funders/f4320311097 || https://openalex.org/funders/f4320334629 || https://openalex.org/funders/f4320320324 | E80: =sample_20250925!E80 -> 5 | F80: 2 | G80: 1 | H80: Jacob | M80: =F80/E80 -> 0.4 | N80: =G80/E80 -> 0.2 | O80: =IFERROR(__xludf.DUMMYFUNCTION("INT(FILTER(GT(F80,0),ISNUMBER(F80)))"),1.0) -> 1 | P80: =F80/(F80+G80) -> 0.66666667 | Q80: =IFERROR(__xludf.DUMMYFUNCTION("INT(FILTER(EQ(E80,F80),ISNUMBER(E80),ISNUMBER(F80)))"),0.0) -> 0
A81: Longitudinal Alterations of Frontoparietal and Frontotemporal Networks Predict Future Creative Cognitive Ability | B81: https://doi.org/10.1093/cercor/bhw353 | C81: National Natural Science Foundation of China; NNSF of China; Guójiā Zìrán Kēxué Jījīn Wěiyuánhuì; NSF of China; The National Natural Science Foundation of China; 国家自然科学基金委员会; National Nature Science Foundation of China; NSFC; National Science Foundation of China; Natural Science Foundation of China; NNSFC; Chinese National Science Foundation; NNSF || NOT MATCHED || NOT MATCHED || Fundamental Research Funds for the Central Universities; Fundamental Research Funds for the Central Universities of China; Fundamental Research Fund for the Central Universities || Natural Science Foundation of Chongqing; Chonqing Natural Science Foundation; Municipal Natural Science Foundation of Chongqing; Natural Science Foundation of Chongqing Municipality; 重庆市自然科学基金 || China Postdoctoral Science Foundation || NOT MATCHED || John Templeton Foundation; مؤسسة جون تمبلتون; Fundación John Templeton; Templeton Foundation; Fundação John Templeton; JTF; The John Templeton Foundation | D81: https://openalex.org/funders/f4320323172 || https://openalex.org/funders/f4320306193 || https://openalex.org/funders/f4320321543 || https://openalex.org/funders/f4320321001 || https://openalex.org/funders/f4320335787 | E81: =sample_20250925!E81 -> 8 | F81: 5 | G81: 0 | H81: Jacob | M81: =F81/E81 -> 0.625 | N81: =G81/E81 -> 0 | O81: =IFERROR(__xludf.DUMMYFUNCTION("INT(FILTER(GT(F81,0),ISNUMBER(F81)))"),1.0) -> 1 | P81: =F81/(F81+G81) -> 1 | Q81: =IFERROR(__xludf.DUMMYFUNCTION("INT(FILTER(EQ(E81,F81),ISNUMBER(E81),ISNUMBER(F81)))"),0.0) -> 0
A82: University Students' Knowledge, Attitudes, and Sources of Information About Zika Virus | B82: https://doi.org/10.1007/s10900-017-0463-z | C82: NOT MATCHED || California Health and Human Services Agency; CHHS || NOT MATCHED | D82: https://openalex.org/institutions/i1291847170 | E82: =sample_20250925!E82 -> 1 | F82: 0 | G82: 1 | H82: Jacob | M82: =F82/E82 -> 0 | N82: =G82/E82 -> 1 | O82: =IFERROR(__xludf.DUMMYFUNCTION("INT(FILTER(GT(F82,0),ISNUMBER(F82)))"),0.0) -> 0 | P82: =F82/(F82+G82) -> 0 | Q82: =IFERROR(__xludf.DUMMYFUNCTION("INT(FILTER(EQ(E82,F82),ISNUMBER(E82),ISNUMBER(F82)))"),0.0) -> 0
A83: Tailoring modulus and hardness of in-situ formed beta-Ti in bulk metallic glass composites by precipitation of isothermal omega-Ti | B83: https://doi.org/10.1016/j.matdes.2017.07.062 | C83: National Natural Science Foundation of China; NNSF of China; Guójiā Zìrán Kēxué Jījīn Wěiyuánhuì; NSF of China; The National Natural Science Foundation of China; 国家自然科学基金委员会; National Nature Science Foundation of China; NSFC; National Science Foundation of China; Natural Science Foundation of China; NNSFC; Chinese National Science Foundation; NNSF || NOT MATCHED || Science and Technology Planning Project of Guangdong Province; Key Project of Guangdong Province Science & Technology Plan; Science and Technology Program of Guangdong; Guangdong Science and Technology Foundation; Science and Technology Projects of Guangdong Province; Scientific and Technological Plan of Guangdong Province; S&T Project of Guangdong Province; Guangdong Science and Technology Program || NOT MATCHED | D83: https://openalex.org/funders/f4320335795 || https://openalex.org/funders/f4320321001 | E83: =sample_20250925!E83 -> 4 | F83: 2 | G83: 0 | H83: Jacob | M83: =F83/E83 -> 0.5 | N83: =G83/E83 -> 0 | O83: =IFERROR(__xludf.DUMMYFUNCTION("INT(FILTER(GT(F83,0),ISNUMBER(F83)))"),1.0) -> 1 | P83: =F83/(F83+G83) -> 1 | Q83: =IFERROR(__xludf.DUMMYFUNCTION("INT(FILTER(EQ(E83,F83),ISNUMBER(E83),ISNUMBER(F83)))"),0.0) -> 0
A84: Comparative genomics of extrachromosomal elements in Bacillus thuringiensis subsp israelensis | B84: https://doi.org/10.1016/j.resmic.2016.10.008 | C84: Agence Nationale de la Recherche; ANR; French National Research Agency || Fonds De La Recherche Scientifique - FNRS; Belgian National Fund for Scientific Research; Fund for Scientific Research - FNRS; F.R.S. - FNRS; FNRS || Fonds De La Recherche Scientifique - FNRS; Belgian National Fund for Scientific Research; Fund for Scientific Research - FNRS; F.R.S. - FNRS; FNRS || Université Catholique de Louvain; University of Louvain; UCLouvain; Universite catholique de Louvain; Catholic University of Louvain; UCL; Louvain University; University of Louvain-la-Neuve; Catholic University of Louvain-la-Neuve; UC Louvain; uclouvain.be; Université catholique de Belgique | D84: https://openalex.org/funders/f4320321390 || https://openalex.org/funders/f4320320883 || https://openalex.org/funders/f4320309729 | E84: =sample_20250925!E84 -> 3 | F84: 3 | G84: 0 | H84: Jacob | M84: =F84/E84 -> 1 | N84: =G84/E84 -> 0 | O84: =IFERROR(__xludf.DUMMYFUNCTION("INT(FILTER(GT(F84,0),ISNUMBER(F84)))"),1.0) -> 1 | P84: =F84/(F84+G84) -> 1 | Q84: =IFERROR(__xludf.DUMMYFUNCTION("INT(FILTER(EQ(E84,F84),ISNUMBER(E84),ISNUMBER(F84)))"),1.0) -> 1
A85: Bicarbonate-based cultivation of Dunaliella salina for enhancing carbon utilization efficiency | B85: https://doi.org/10.1016/j.biortech.2017.04.009 | C85: Advanced Biomass R&D Center (South Korea); ABC || Korea Electric Power Corporation; KEPCO; 한국전력공사 | D85: https://openalex.org/funders/f4320326258 || https://openalex.org/institutions/i4210088693 | E85: =sample_20250925!E85 -> 2 | F85: =IF(sample_20250925!$C85=C85,sample_20250925!F85, NA()) -> 2 | G85: =IF(sample_20250925!$C85=$C85,sample_20250925!G85, NA()) -> 0 | H85: Jacob | M85: =F85/E85 -> 1 | N85: =G85/E85 -> 0 | O85: =IFERROR(__xludf.DUMMYFUNCTION("INT(FILTER(GT(F85,0),ISNUMBER(F85)))"),1.0) -> 1 | P85: =F85/(F85+G85) -> 1 | Q85: =IFERROR(__xludf.DUMMYFUNCTION("INT(FILTER(EQ(E85,F85),ISNUMBER(E85),ISNUMBER(F85)))"),1.0) -> 1
A86: Polysaccharides from chayote enhance lipid efflux and regulate NLRP3 inflammasome priming in macrophage-like THP-1 cells exposed to cholesterol crystals | B86: https://doi.org/10.1016/j.ijbiomac.2019.01.048 | C86: Fundação de Amparo à Pesquisa do Estado de São Paulo; São Paulo Research Foundation; Foundation for Research Support of the State of São Paulo; FAPESP; State of São Paulo Research Foundation || Coordenação de Aperfeiçoamento de Pessoal de Nível Superior; Coordination for the Improvement of Higher Education Personnel; CAPES; Brazilian Federal Agency for the Support and Evaluation of Graduate Education || Fundação de Amparo à Pesquisa do Estado de São Paulo; São Paulo Research Foundation; Foundation for Research Support of the State of São Paulo; FAPESP; State of São Paulo Research Foundation || Conselho Nacional de Desenvolvimento Científico e Tecnológico; National Council for Scientific and Technological Development; Brazilian National Council for Research and Development; CNPq | D86: https://openalex.org/funders/f4320321091 || https://openalex.org/funders/f4320322025 || https://openalex.org/funders/f4320320997 | E86: =sample_20250925!E86 -> 3 | F86: =IF(sample_20250925!$C86=C86,sample_20250925!F86, NA()) -> 3 | G86: =IF(sample_20250925!$C86=$C86,sample_20250925!G86, NA()) -> 0 | H86: Jacob | M86: =F86/E86 -> 1 | N86: =G86/E86 -> 0 | O86: =IFERROR(__xludf.DUMMYFUNCTION("INT(FILTER(GT(F86,0),ISNUMBER(F86)))"),1.0) -> 1 | P86: =F86/(F86+G86) -> 1 | Q86: =IFERROR(__xludf.DUMMYFUNCTION("INT(FILTER(EQ(E86,F86),ISNUMBER(E86),ISNUMBER(F86)))"),1.0) -> 1
A87: Mineral assemblage transformation of a metakaolin-based waste form after geopolymer encapsulation | B87: https://doi.org/10.1016/j.jnucmat.2015.12.023 | C87: Biological and Environmental Research; BER; Biological & Environmental Research; DOE Office of Science's Biological and Environmental Research; Office of Biological and Environmental Research; Department of Energy's Office of Biological and Environmental Research | D87: https://openalex.org/funders/f4320337509 | E87: =sample_20250925!E87 -> 1 | F87: =IF(sample_20250925!$C87=C87,sample_20250925!F87, NA()) -> 1 | G87: =IF(sample_20250925!$C87=$C87,sample_20250925!G87, NA()) -> 0 | H87: Jacob | M87: =F87/E87 -> 1 | N87: =G87/E87 -> 0 | O87: =IFERROR(__xludf.DUMMYFUNCTION("INT(FILTER(GT(F87,0),ISNUMBER(F87)))"),1.0) -> 1 | P87: =F87/(F87+G87) -> 1 | Q87: =IFERROR(__xludf.DUMMYFUNCTION("INT(FILTER(EQ(E87,F87),ISNUMBER(E87),ISNUMBER(F87)))"),1.0) -> 1
A88: Life Cycle-Based Sustainability and Circularity Indicators for the Tourism Industry: A Literature Review | B88: https://doi.org/10.3390/su132111853 | C88: European Social Fund; ESF; The European Social Fund; Europäische Sozialfonds; Fondo Sociale Europeo; Fonds Social Européen; Fondo Social Europeo || NOT MATCHED | D88: https://openalex.org/funders/f4320338080 | E88: =sample_20250925!E88 -> 2 | F88: 1 | G88: 0 | H88: Jacob | M88: =F88/E88 -> 0.5 | N88: =G88/E88 -> 0 | O88: =IFERROR(__xludf.DUMMYFUNCTION("INT(FILTER(GT(F88,0),ISNUMBER(F88)))"),1.0) -> 1 | P88: =F88/(F88+G88) -> 1
A89: Microbial quest for food in vivo: "Nutritional virulence' as an emerging paradigm | B89: https://doi.org/10.1111/cmi.12138 | C89: NOT MATCHED || NOT MATCHED || Schweizerischer Nationalfonds zur Förderung der Wissenschaftlichen Forschung; Fondo Nazionale Svizzero; Fonds National Suisse; Schweizerische Nationalfonds; Fondo Nazionale Svizzero per la Ricerca Scientifica; SNSF; Fonds National Suisse de la Recherche Scientifique; Swiss National Science Foundation; FNS; SNF; Schweizerischer Nationalfonds || NOT MATCHED || NOT MATCHED || National Institute of Allergy and Infectious Diseases; NIAID; Instituto Nacional de Alergias y Enfermedades Infecciosas | D89: https://openalex.org/funders/f4320320924 || https://openalex.org/funders/f4320337355 | E89: =sample_20250925!E89 -> 5 | F89: 2 | G89: 0 | H89: Jacob | M89: =F89/E89 -> 0.4 | N89: =G89/E89 -> 0 | O89: =IFERROR(__xludf.DUMMYFUNCTION("INT(FILTER(GT(F89,0),ISNUMBER(F89)))"),1.0) -> 1 | P89: =F89/(F89+G89) -> 1 | Q89: =IFERROR(__xludf.DUMMYFUNCTION("INT(FILTER(EQ(E89,F89),ISNUMBER(E89),ISNUMBER(F89)))"),0.0) -> 0
A90: Location and Setting of the Mars InSight Lander, Instruments, and Landing Site | B90: https://doi.org/10.1029/2020EA001248 | C90: Jet Propulsion Laboratory; NASA Jet Propulsion Laboratory; NASA Jet Propulsion Lab; NASA JPL; JPL || National Aeronautics and Space Administration; US National Aeronautics & Space Administration; United States National Aeronautics and Space Administration; NASA; National Aeronautics & Space Administration || National Aeronautics and Space Administration; US National Aeronautics & Space Administration; United States National Aeronautics and Space Administration; NASA; National Aeronautics & Space Administration | D90: https://openalex.org/funders/f4320306101 || https://openalex.org/funders/f4320332375 | E90: =sample_20250925!E90 -> 2 | F90: =IF(sample_20250925!$C90=C90,sample_20250925!F90, NA()) -> 2 | G90: =IF(sample_20250925!$C90=$C90,sample_20250925!G90, NA()) -> 0 | H90: Jacob | M90: =F90/E90 -> 1 | N90: =G90/E90 -> 0 | O90: =IFERROR(__xludf.DUMMYFUNCTION("INT(FILTER(GT(F90,0),ISNUMBER(F90)))"),1.0) -> 1 | P90: =F90/(F90+G90) -> 1 | Q90: =IFERROR(__xludf.DUMMYFUNCTION("INT(FILTER(EQ(E90,F90),ISNUMBER(E90),ISNUMBER(F90)))"),1.0) -> 1
A91: Effects of zirconium silicate reinforcement on expandable graphite based intumescent fire retardant coating | B91: https://doi.org/10.1016/j.polymdegradstab.2014.02.016 | C91: Universiti Teknologi Petronas; UTP; Petronas Technology University | D91: https://openalex.org/funders/f4320323380 | E91: =sample_20250925!E91 -> 1 | F91: =IF(sample_20250925!$C91=C91,sample_20250925!F91, NA()) -> 1 | G91: =IF(sample_20250925!$C91=$C91,sample_20250925!G91, NA()) -> 0 | H91: Jacob | M91: =F91/E91 -> 1 | N91: =G91/E91 -> 0 | O91: =IFERROR(__xludf.DUMMYFUNCTION("INT(FILTER(GT(F91,0),ISNUMBER(F91)))"),1.0) -> 1 | P91: =F91/(F91+G91) -> 1 | Q91: =IFERROR(__xludf.DUMMYFUNCTION("INT(FILTER(EQ(E91,F91),ISNUMBER(E91),ISNUMBER(F91)))"),1.0) -> 1
A92: Nonlinear Process Fault Detection Based on Multi-Scale Sparse Kernel Classifier | B92: https://doi.org/10.1007/978-3-642-38524-7_17 | C92: Natural Science Foundation of Shandong Province; Natural Science Foundation of Shandong; Shandong Province Natural Science Foundation; Shandong Provincial Natural Science Foundation || National Natural Science Foundation of China; NNSF of China; Guójiā Zìrán Kēxué Jījīn Wěiyuánhuì; NSF of China; The National Natural Science Foundation of China; 国家自然科学基金委员会; National Nature Science Foundation of China; NSFC; National Science Foundation of China; Natural Science Foundation of China; NNSFC; Chinese National Science Foundation; NNSF || Fundamental Research Funds for the Central Universities; Fundamental Research Funds for the Central Universities of China; Fundamental Research Fund for the Central Universities | D92: https://openalex.org/funders/f4320335787 || https://openalex.org/funders/f4320321001 || https://openalex.org/funders/f4320324174 | E92: =sample_20250925!E92 -> 3 | F92: =IF(sample_20250925!$C92=C92,sample_20250925!F92, NA()) -> 3 | G92: =IF(sample_20250925!$C92=$C92,sample_20250925!G92, NA()) -> 0 | H92: Jacob | M92: =F92/E92 -> 1 | N92: =G92/E92 -> 0 | O92: =IFERROR(__xludf.DUMMYFUNCTION("INT(FILTER(GT(F92,0),ISNUMBER(F92)))"),1.0) -> 1 | P92: =F92/(F92+G92) -> 1 | Q92: =IFERROR(__xludf.DUMMYFUNCTION("INT(FILTER(EQ(E92,F92),ISNUMBER(E92),ISNUMBER(F92)))"),1.0) -> 1
A93: Energy Landscapes of Dynamic Ensembles of Rolling Triplet Repeat Bulge Loops: Implications for DNA Expansion Associated with Disease States | B93: https://doi.org/10.1021/ja3010896 | C93: National Institutes of Health; US National Institutes of Health; Institutos Nacionales de la Salud; NIH || NOT MATCHED || National Cancer Institute; NCI; Instituto Nacional del Cáncer || National Institute of General Medical Sciences; NIGMS; U.S. National Institute of General Medical Sciences | D93: https://openalex.org/funders/f4320332161 || https://openalex.org/funders/f4320337351 || https://openalex.org/funders/f4320337354 | E93: =sample_20250925!E93 -> 3 | F93: 2 | G93: 0 | H93: Jacob | M93: =F93/E93 -> 0.66666667 | N93: =G93/E93 -> 0 | O93: =IFERROR(__xludf.DUMMYFUNCTION("INT(FILTER(GT(F93,0),ISNUMBER(F93)))"),1.0) -> 1 | P93: =F93/(F93+G93) -> 1 | Q93: =IFERROR(__xludf.DUMMYFUNCTION("INT(FILTER(EQ(E93,F93),ISNUMBER(E93),ISNUMBER(F93)))"),0.0) -> 0
A94: AN EXCEPTIONAL CHOICE? How Young New Zealand Women Talk about Abortion | B94: https://doi.org/10.1080/08164649.2015.1046305 | C94: University of Otago; Te Whare Wānanga o Otāgo; Te Whare Wānanga o Ōtākou | D94: https://openalex.org/funders/f4320310371 | E94: =sample_20250925!E94 -> 1 | F94: =IF(sample_20250925!$C94=C94,sample_20250925!F94, NA()) -> 1 | G94: =IF(sample_20250925!$C94=$C94,sample_20250925!G94, NA()) -> 0 | H94: Jacob | M94: =F94/E94 -> 1 | N94: =G94/E94 -> 0 | O94: =IFERROR(__xludf.DUMMYFUNCTION("INT(FILTER(GT(F94,0),ISNUMBER(F94)))"),1.0) -> 1 | P94: =F94/(F94+G94) -> 1 | Q94: =IFERROR(__xludf.DUMMYFUNCTION("INT(FILTER(EQ(E94,F94),ISNUMBER(E94),ISNUMBER(F94)))"),1.0) -> 1
A95: Highly Efficient CdS Quantum Dot-Sensitized Solar Cells Based on a Modified Polysulfide Electrolyte | B95: https://doi.org/10.1021/ja201841p | C95: National Natural Science Foundation of China; NNSF of China; Guójiā Zìrán Kēxué Jījīn Wěiyuánhuì; NSF of China; The National Natural Science Foundation of China; 国家自然科学基金委员会; National Nature Science Foundation of China; NSFC; National Science Foundation of China; Natural Science Foundation of China; NNSFC; Chinese National Science Foundation; NNSF || NOT MATCHED || National Key Research and Development Program of China; NKRDPC; Special Fund for the National Key Research and Development Plan; 973 Program; National Basic Research Program of China; NKPs; National Plan on Key Basic Research and Development; National Program on Key Basic Research Project (973 Program); National Key Research and Development of China; 重点基础研究发展计划; National Key R&D Program of China; National Key R&D Programmes of China; China's National Key R&D Programmes; National Basic Research Program; National Basic Research Program of China (973 Program); China National Key Research and Development Plan Project; National Key Research and Development Program || Ministry of Science and Technology, Taiwan; Ministry of Science and Technology of Taiwan; MOST; Ministry of Science and Technology, R.O.C. (Taiwan) || Energimyndigheten; Swedish Energy Agency || Knut och Alice Wallenbergs Stiftelse; Knut and Alice Wallenberg Foundation || State Key Laboratory of Fine Chemicals; 精细化工国家重点实验室; State Key Lab of Fine Chemicals | D95: https://openalex.org/institutions/i4391767660 || https://openalex.org/funders/f4320321001 || https://openalex.org/funders/f4320335777 || https://openalex.org/funders/f4320322795 || https://openalex.org/funders/f4320322711 || https://openalex.org/funders/f4320322327 | E95: =sample_20250925!E95 -> 7 | F95: 5 | G95: 1 | H95: Jacob | M95: =F95/E95 -> 0.71428571 | N95: =G95/E95 -> 0.14285714 | O95: =IFERROR(__xludf.DUMMYFUNCTION("INT(FILTER(GT(F95,0),ISNUMBER(F95)))"),1.0) -> 1 | P95: =F95/(F95+G95) -> 0.83333333 | Q95: =IFERROR(__xludf.DUMMYFUNCTION("INT(FILTER(EQ(E95,F95),ISNUMBER(E95),ISNUMBER(F95)))"),0.0) -> 0
A96: Perceived barriers to multiprofessional team briefings in operating theatres: a qualitative study | B96: https://doi.org/10.1136/bmjopen-2019-032351 | C96: Department of Health, Government of Western Australia; WA Health; WA Department of Health | D96: https://openalex.org/funders/f4320323612 | E96: =sample_20250925!E96 -> 1 | F96: 1 | G96: 0 | H96: Jacob | M96: =F96/E96 -> 1 | N96: =G96/E96 -> 0 | O96: =IFERROR(__xludf.DUMMYFUNCTION("INT(FILTER(GT(F96,0),ISNUMBER(F96)))"),1.0) -> 1 | P96: =F96/(F96+G96) -> 1 | Q96: =IFERROR(__xludf.DUMMYFUNCTION("INT(FILTER(EQ(E96,F96),ISNUMBER(E96),ISNUMBER(F96)))"),1.0) -> 1
A97: Identifying Galactic PeVatrons with neutrinos | B97: https://doi.org/10.1016/j.astropartphys.2009.05.002 | C97: National Science Foundation; U.S. National Science Foundation; USA NSF; USNSF; NSF; US National Science Foundation; US NSF || U.S. Department of Energy; US Department of Energy; DOE; United States Department of Energy; Department of Energy; USDOE; Energy Department; ENERGY.GOV; USADOE; US DOE || Wisconsin Alumni Research Foundation; THE WISCONSIN ALUMNI RESEARCH FOUNDATION; WARF || NOT MATCHED || Institució Catalana de Recerca i Estudis Avançats; ICREA; Catalan Institution for Research and Advanced Studies | D97: https://openalex.org/funders/f4320306076 || https://openalex.org/funders/f4320306084 || https://openalex.org/funders/f4320322121 || https://openalex.org/funders/f4320306555 | E97: 5 | F97: 4 | G97: 0 | H97: Jacob | M97: =F97/E97 -> 0.8 | N97: =G97/E97 -> 0 | O97: =IFERROR(__xludf.DUMMYFUNCTION("INT(FILTER(GT(F97,0),ISNUMBER(F97)))"),1.0) -> 1 | P97: =F97/(F97+G97) -> 1 | Q97: =IFERROR(__xludf.DUMMYFUNCTION("INT(FILTER(EQ(E97,F97),ISNUMBER(E97),ISNUMBER(F97)))"),0.0) -> 0
A98: Female Labour Force Participation and the Reduction in Son Preference in China | B98: https://doi.org/10.1080/10357823.2022.2111547 | C98: NOT MATCHED || National Social Science Fund of China; National Social Science Foundation of China; Chinese National Funding of Social Sciences; 国家社会科学基金; National Social Science Foundation; NSSFC || NOT MATCHED | D98: https://openalex.org/funders/f4320335869 | E98: =sample_20250925!E98 -> 3 | F98: 1 | G98: 0 | H98: Jacob | M98: =F98/E98 -> 0.33333333 | N98: =G98/E98 -> 0 | O98: =IFERROR(__xludf.DUMMYFUNCTION("INT(FILTER(GT(F98,0),ISNUMBER(F98)))"),1.0) -> 1 | P98: =F98/(F98+G98) -> 1 | Q98: =IFERROR(__xludf.DUMMYFUNCTION("INT(FILTER(EQ(E98,F98),ISNUMBER(E98),ISNUMBER(F98)))"),0.0) -> 0
A99: A HIGHLY LINEAR AND EFFICIENT THREE-WAY DOHERTY AMPLIFIER USING TWO-STAGE GaN HEMT CELLS FOR REPEATER SYSTEMS | B99: https://doi.org/10.1002/mop.24748 | C99: Institute of BioMed-IT, Energy-IT and Smart-IT Technology (Best), Yonsei University; BK21+ BEST; BK21PLUS BEST || NOT MATCHED | D99: https://openalex.org/funders/f4320336052 | E99: =sample_20250925!E99 -> 2 | F99: 1 | G99: 0 | H99: Jacob | M99: =F99/E99 -> 0.5 | N99: =G99/E99 -> 0 | O99: =IFERROR(__xludf.DUMMYFUNCTION("INT(FILTER(GT(F99,0),ISNUMBER(F99)))"),1.0) -> 1 | P99: =F99/(F99+G99) -> 1
A100: Mechanochemical Synthesis of Ketones via Chemoselective Suzuki-Miyaura Cross-Coupling of Acyl Chlorides | B100: https://doi.org/10.1021/acs.orglett.2c00519 | C100: National Natural Science Foundation of China; NNSF of China; Guójiā Zìrán Kēxué Jījīn Wěiyuánhuì; NSF of China; The National Natural Science Foundation of China; 国家自然科学基金委员会; National Nature Science Foundation of China; NSFC; National Science Foundation of China; Natural Science Foundation of China; NNSFC; Chinese National Science Foundation; NNSF || Rutgers, The State University of New Jersey; RU; Universitas Rutgersensis Civitatis Novae Caesareae; Rutgers University || National Science Foundation; U.S. National Science Foundation; USA NSF; USNSF; NSF; US National Science Foundation; US NSF | D100: https://openalex.org/funders/f4320306076 || https://openalex.org/funders/f4320312581 || https://openalex.org/funders/f4320321001 | E100: =sample_20250925!E100 -> 3 | F100: =IF(sample_20250925!$C100=C100,sample_20250925!F100, NA()) -> 3 | G100: =IF(sample_20250925!$C100=$C100,sample_20250925!G100, NA()) -> 0 | H100: Jacob | M100: =F100/E100 -> 1 | N100: =G100/E100 -> 0 | O100: =IFERROR(__xludf.DUMMYFUNCTION("INT(FILTER(GT(F100,0),ISNUMBER(F100)))"),1.0) -> 1 | P100: =F100/(F100+G100) -> 1 | Q100: =IFERROR(__xludf.DUMMYFUNCTION("INT(FILTER(EQ(E100,F100),ISNUMBER(E100),ISNUMBER(F100)))"),1.0) -> 1
...

Sheet Openalex
A1: title | B1: DOI | C1: funder_display_name | D1: Number of Funders Indicated by Paper | E1: Number of Correct Matches | F1: Number of Wrong Matches | G1: Coder | H1: Avg. Recall | I1: Avg error rate | J1: Hit rate | K1: Avg. Precision | L1: Paper level recall | M1: Paper level error rate | N1: Paper level hit rate | O1: Paper level precision | P1: Paper is complete hit
A2: Integral-Type Fractional Equations with a Proportional Riemann-Liouville Derivative | B2: https://doi.org/10.1155/2021/9990439 | C2: Prince Sultan University | D2: =VLOOKUP(A2,'Web_of_Science_20251015 '!A:E,5,0) -> 1 | E2: 1 | F2: 0 | G2: Jacob | H2: =IFERROR(__xludf.DUMMYFUNCTION("AVERAGE(FILTER(L2:L101,ISNUMBER(L2:L101)))"),0.6838099415204678) -> 0.68380994 | I2: =IFERROR(__xludf.DUMMYFUNCTION("AVERAGE(FILTER(M2:M101,ISNUMBER(M2:M101)))"),0.050277777777777775) -> 0.050277778 | J2: =IFERROR(__xludf.DUMMYFUNCTION("AVERAGE(FILTER(N2:N101,ISNUMBER(N2:N101)))"),0.95) -> 0.95 | K2: =IFERROR(__xludf.DUMMYFUNCTION("AVERAGE(FILTER(O2:O101,ISNUMBER(O2:O101)))"),0.9358333333333333) -> 0.93583333 | L2: =E2/D2 -> 1 | M2: =F2/D2 -> 0 | N2: =IFERROR(__xludf.DUMMYFUNCTION("INT(FILTER(GT(E2,0),ISNUMBER(E2)))"),1.0) -> 1 | O2: =E2/(E2+F2) -> 1 | P2: =IFERROR(__xludf.DUMMYFUNCTION("INT(FILTER(EQ(D2,E2),ISNUMBER(D2),ISNUMBER(E2)))"),1.0) -> 1
A3: Enzymatic Hydrolysis of Softwood Derived Paper Sludge by an In Vitro Recombinant Cellulase Cocktail for the Production of Fermentable Sugars | B3: https://doi.org/10.3390/catal10070775 | C3: Universiteit Stellenbosch;National Agricultural Research Foundation;Rhodes University | D3: =VLOOKUP(A3,'Web_of_Science_20251015 '!A:E,5,0) -> 4 | E3: 2 | F3: 1 | G3: Jacob | H3: Recall | I3: Error rate | J3: Complete hits | K3: Precision | L3: =E3/D3 -> 0.5 | M3: =F3/D3 -> 0.25 | N3: =IFERROR(__xludf.DUMMYFUNCTION("INT(FILTER(GT(E3,0),ISNUMBER(E3)))"),1.0) -> 1 | O3: =E3/(E3+F3) -> 0.66666667 | P3: =IFERROR(__xludf.DUMMYFUNCTION("INT(FILTER(EQ(D3,E3),ISNUMBER(D3),ISNUMBER(E3)))"),0.0) -> 0
A4: Synthesis of 2-Vinylbenzofurans via the Copper-Catalyzed Multicomponent Reactions Involving an Oxa-Michael/Arylation/Vinylation Cascade | B4: https://doi.org/10.1021/ol502506g | C4: Education Department of Jiangxi Province;National Natural Science Foundation of China | D4: =VLOOKUP(A4,'Web_of_Science_20251015 '!A:E,5,0) -> 2 | E4: 2 | F4: 0 | G4: Jacob | H4: =IFERROR(__xludf.DUMMYFUNCTION("SUM(FILTER(E2:E101,ISNUMBER(E2:E101)))/SUM(FILTER(D2:D101,ISNUMBER(E2:E101)))"),0.6392857142857142) -> 0.63928571 | I4: =IFERROR(__xludf.DUMMYFUNCTION("SUM(FILTER(F2:F101,ISNUMBER(F2:F101)))/SUM(FILTER(D2:D101,ISNUMBER(F2:F101)))"),0.03571428571428571) -> 0.035714286 | J4: =IFERROR(__xludf.DUMMYFUNCTION("AVERAGE(FILTER(P2:P101,ISNUMBER(P2:P101)))"),0.4175824175824176) -> 0.41758242 | K4: =IFERROR(__xludf.DUMMYFUNCTION("SUM(FILTER(E2:E101,ISNUMBER(E2:E101)))/(SUM(FILTER(E2:E101,ISNUMBER(E2:E101)))+SUM(FILTER(F2:F101,ISNUMBER(E2:E101))))"),0.9470899470899471) -> 0.94708995 | L4: =E4/D4 -> 1 | M4: =F4/D4 -> 0 | N4: =IFERROR(__xludf.DUMMYFUNCTION("INT(FILTER(GT(E4,0),ISNUMBER(E4)))"),1.0) -> 1 | O4: =E4/(E4+F4) -> 1 | P4: =IFERROR(__xludf.DUMMYFUNCTION("INT(FILTER(EQ(D4,E4),ISNUMBER(D4),ISNUMBER(E4)))"),1.0) -> 1
A5: Nrf2 augments skeletal muscle regeneration after ischaemia-reperfusion injury | B5: https://doi.org/10.1002/path.4418 | C5: Deutsche Forschungsgemeinschaft | D5: =VLOOKUP(A5,'Web_of_Science_20251015 '!A:E,5,0) -> 3 | E5: 1 | F5: 0 | G5: Jacob | L5: =E5/D5 -> 0.33333333 | M5: =F5/D5 -> 0 | N5: =IFERROR(__xludf.DUMMYFUNCTION("INT(FILTER(GT(E5,0),ISNUMBER(E5)))"),1.0) -> 1 | O5: =E5/(E5+F5) -> 1 | P5: =IFERROR(__xludf.DUMMYFUNCTION("INT(FILTER(EQ(D5,E5),ISNUMBER(D5),ISNUMBER(E5)))"),0.0) -> 0
A6: Crash responses under multiple impacts and residual properties of CFRP and aluminum tubes | B6: https://doi.org/10.1016/j.compstruct.2018.04.001 | C6: China Postdoctoral Science Foundation;National Natural Science Foundation of China;Natural Science Foundation of Guangdong Province;Natural Science Foundation of Hainan Province | D6: =VLOOKUP(A6,'Web_of_Science_20251015 '!A:E,5,0) -> 6 | E6: 3 | F6: 1 | G6: Jacob | L6: =E6/D6 -> 0.5 | M6: =F6/D6 -> 0.16666667 | N6: =IFERROR(__xludf.DUMMYFUNCTION("INT(FILTER(GT(E6,0),ISNUMBER(E6)))"),1.0) -> 1 | O6: =E6/(E6+F6) -> 0.75 | P6: =IFERROR(__xludf.DUMMYFUNCTION("INT(FILTER(EQ(D6,E6),ISNUMBER(D6),ISNUMBER(E6)))"),0.0) -> 0
A7: Inactivation of a pathogenic NDM-1-positive Escherichia coli strain and the resistance gene bla(NDM-1) by TiO2/UVA photocatalysis | B7: https://doi.org/10.1016/j.scitotenv.2022.157369 | C7: National Natural Science Foundation of China;Xuzhou Science and Technology Bureau;Jiangsu Provincial Department of Education | D7: =VLOOKUP(A7,'Web_of_Science_20251015 '!A:E,5,0) -> 3 | E7: 3 | F7: 0 | G7: Jacob | L7: =E7/D7 -> 1 | M7: =F7/D7 -> 0 | N7: =IFERROR(__xludf.DUMMYFUNCTION("INT(FILTER(GT(E7,0),ISNUMBER(E7)))"),1.0) -> 1 | O7: =E7/(E7+F7) -> 1 | P7: =IFERROR(__xludf.DUMMYFUNCTION("INT(FILTER(EQ(D7,E7),ISNUMBER(D7),ISNUMBER(E7)))"),1.0) -> 1
A8: Nitrogen Dioxide Sensing Using Multilayer Structure of Reduced Graphene Oxide and alpha-Fe2O3 | B8: https://doi.org/10.3390/s21031011 | C8: Narodowe Centrum Nauki | D8: =VLOOKUP(A8,'Web_of_Science_20251015 '!A:E,5,0) -> 1 | E8: 1 | F8: 0 | G8: Jacob | L8: =E8/D8 -> 1 | M8: =F8/D8 -> 0 | N8: =IFERROR(__xludf.DUMMYFUNCTION("INT(FILTER(GT(E8,0),ISNUMBER(E8)))"),1.0) -> 1 | O8: =E8/(E8+F8) -> 1 | P8: =IFERROR(__xludf.DUMMYFUNCTION("INT(FILTER(EQ(D8,E8),ISNUMBER(D8),ISNUMBER(E8)))"),1.0) -> 1
A9: A novel lateral shearing interferometer and its anti-vibration characteristic for on-machine precision surface measurement | B9: https://doi.org/10.1016/j.ijleo.2016.03.064 | C9: National Natural Science Foundation of China | D9: =VLOOKUP(A9,'Web_of_Science_20251015 '!A:E,5,0) -> 3 | E9: 1 | F9: 0 | G9: Jacob | L9: =E9/D9 -> 0.33333333 | M9: =F9/D9 -> 0 | N9: =IFERROR(__xludf.DUMMYFUNCTION("INT(FILTER(GT(E9,0),ISNUMBER(E9)))"),1.0) -> 1 | O9: =E9/(E9+F9) -> 1 | P9: =IFERROR(__xludf.DUMMYFUNCTION("INT(FILTER(EQ(D9,E9),ISNUMBER(D9),ISNUMBER(E9)))"),0.0) -> 0
A10: On the Non-trivial Origin of Atomic-Scale Patterns in Friction Force Microscopy | B10: https://doi.org/10.1007/s11249-018-1127-6 | C10: European Research Council;Foundation for Fundamental Research on Matter | D10: =VLOOKUP(A10,'Web_of_Science_20251015 '!A:E,5,0) -> 2 | E10: 2 | F10: 0 | G10: Jacob | L10: =E10/D10 -> 1 | M10: =F10/D10 -> 0 | N10: =IFERROR(__xludf.DUMMYFUNCTION("INT(FILTER(GT(E10,0),ISNUMBER(E10)))"),1.0) -> 1 | O10: =E10/(E10+F10) -> 1 | P10: =IFERROR(__xludf.DUMMYFUNCTION("INT(FILTER(EQ(D10,E10),ISNUMBER(D10),ISNUMBER(E10)))"),1.0) -> 1
A11: Professional identity research in the health professions-a scoping review | B11: https://doi.org/10.1007/s10459-022-10171-1 | C11: Monash University | D11: =VLOOKUP(A11,'Web_of_Science_20251015 '!A:E,5,0) -> 2 | E11: 0 | F11: 1 | G11: Jacob | L11: =E11/D11 -> 0 | M11: =F11/D11 -> 0.5 | N11: =IFERROR(__xludf.DUMMYFUNCTION("INT(FILTER(GT(E11,0),ISNUMBER(E11)))"),0.0) -> 0 | O11: =E11/(E11+F11) -> 0
A12: Parental Life Span and Polygenic Risk Score of Longevity Are Associated With White Matter Hyperintensities | B12: https://doi.org/10.1093/gerona/glab323 | C12: National Health and Medical Research Council | D12: =VLOOKUP(A12,'Web_of_Science_20251015 '!A:E,5,0) -> 2 | E12: 1 | F12: 0 | G12: Jacob | L12: =E12/D12 -> 0.5 | M12: =F12/D12 -> 0 | N12: =IFERROR(__xludf.DUMMYFUNCTION("INT(FILTER(GT(E12,0),ISNUMBER(E12)))"),1.0) -> 1 | O12: =E12/(E12+F12) -> 1 | P12: =IFERROR(__xludf.DUMMYFUNCTION("INT(FILTER(EQ(D12,E12),ISNUMBER(D12),ISNUMBER(E12)))"),0.0) -> 0
A13: Developing Concentration Index of Industrial and Occupational Accidents: The Case of European Countries | B13: https://doi.org/10.1016/j.shaw.2020.05.003 | C13: National Research Foundation of Korea | D13: =VLOOKUP(A13,'Web_of_Science_20251015 '!A:E,5,0) -> 2 | E13: 1 | F13: 0 | G13: Jacob | L13: =E13/D13 -> 0.5 | M13: =F13/D13 -> 0 | N13: =IFERROR(__xludf.DUMMYFUNCTION("INT(FILTER(GT(E13,0),ISNUMBER(E13)))"),1.0) -> 1 | O13: =E13/(E13+F13) -> 1 | P13: =IFERROR(__xludf.DUMMYFUNCTION("INT(FILTER(EQ(D13,E13),ISNUMBER(D13),ISNUMBER(E13)))"),0.0) -> 0
A14: Analysis of the Fee-to-Tax Reform on Water Resources in China | B14: https://doi.org/10.3389/fenrg.2021.752592 | C14: Guangdong Office of Philosophy and Social Science | D14: =VLOOKUP(A14,'Web_of_Science_20251015 '!A:E,5,0) -> 1 | E14: 1 | F14: 0 | G14: Jacob | L14: =E14/D14 -> 1 | M14: =F14/D14 -> 0 | N14: =IFERROR(__xludf.DUMMYFUNCTION("INT(FILTER(GT(E14,0),ISNUMBER(E14)))"),1.0) -> 1 | O14: =E14/(E14+F14) -> 1 | P14: =IFERROR(__xludf.DUMMYFUNCTION("INT(FILTER(EQ(D14,E14),ISNUMBER(D14),ISNUMBER(E14)))"),1.0) -> 1
A15: Bifurcation Phenomena of Nonlinear Waves in a Generalized Zakharov-Kuznetsov Equation | B15: https://doi.org/10.1155/2013/812120 | C15: National Natural Science Foundation of China | D15: =VLOOKUP(A15,'Web_of_Science_20251015 '!A:E,5,0) -> 2 | E15: 1 | F15: 0 | G15: Jacob | L15: =E15/D15 -> 0.5 | M15: =F15/D15 -> 0 | N15: =IFERROR(__xludf.DUMMYFUNCTION("INT(FILTER(GT(E15,0),ISNUMBER(E15)))"),1.0) -> 1 | O15: =E15/(E15+F15) -> 1 | P15: =IFERROR(__xludf.DUMMYFUNCTION("INT(FILTER(EQ(D15,E15),ISNUMBER(D15),ISNUMBER(E15)))"),0.0) -> 0
A16: Gall size of Dryocosmus kuriphilus limits down-regulation by native parasitoids | B16: https://doi.org/10.1007/s10530-020-02427-x | C16: Ministerio de Asuntos Económicos y Transformación Digital, Gobierno de España | D16: =VLOOKUP(A16,'Web_of_Science_20251015 '!A:E,5,0) -> 1 | E16: 1 | F16: 0 | G16: Jacob | L16: =E16/D16 -> 1 | M16: =F16/D16 -> 0 | N16: =IFERROR(__xludf.DUMMYFUNCTION("INT(FILTER(GT(E16,0),ISNUMBER(E16)))"),1.0) -> 1 | O16: =E16/(E16+F16) -> 1 | P16: =IFERROR(__xludf.DUMMYFUNCTION("INT(FILTER(EQ(D16,E16),ISNUMBER(D16),ISNUMBER(E16)))"),1.0) -> 1
A17: Dynamic Characteristics Analysis of ISD Suspension System under Different Working Conditions | B17: https://doi.org/10.3390/math9121345 | C17: National Natural Science Foundation of China | D17: =VLOOKUP(A17,'Web_of_Science_20251015 '!A:E,5,0) -> 2 | E17: 1 | F17: 0 | G17: Jacob | L17: =E17/D17 -> 0.5 | M17: =F17/D17 -> 0 | N17: =IFERROR(__xludf.DUMMYFUNCTION("INT(FILTER(GT(E17,0),ISNUMBER(E17)))"),1.0) -> 1 | O17: =E17/(E17+F17) -> 1 | P17: =IFERROR(__xludf.DUMMYFUNCTION("INT(FILTER(EQ(D17,E17),ISNUMBER(D17),ISNUMBER(E17)))"),0.0) -> 0
A18: Dynamic covalent chemistry constrained diphenylethenes: control over reactivity and luminescence both in solution and in the solid state | B18: https://doi.org/10.1039/d2qo00057a | C18: Key Research Program of Frontier Science, Chinese Academy of Sciences;Natural Science Foundation of Fujian Province;National Natural Science Foundation of China | D18: =VLOOKUP(A18,'Web_of_Science_20251015 '!A:E,5,0) -> 5 | E18: 3 | F18: 0 | G18: Jacob | L18: =E18/D18 -> 0.6 | M18: =F18/D18 -> 0 | N18: =IFERROR(__xludf.DUMMYFUNCTION("INT(FILTER(GT(E18,0),ISNUMBER(E18)))"),1.0) -> 1 | O18: =E18/(E18+F18) -> 1 | P18: =IFERROR(__xludf.DUMMYFUNCTION("INT(FILTER(EQ(D18,E18),ISNUMBER(D18),ISNUMBER(E18)))"),0.0) -> 0
A19: Dynamic changes in positive interferon-gamma release assay in a dialysis population: An observational cohort study | B19: https://doi.org/10.1016/j.jinf.2013.07.029 | C19: National Research Program for Biopharmaceuticals | D19: =VLOOKUP(A19,'Web_of_Science_20251015 '!A:E,5,0) -> 3 | E19: 1 | F19: 0 | G19: Jacob | L19: =E19/D19 -> 0.33333333 | M19: =F19/D19 -> 0 | N19: =IFERROR(__xludf.DUMMYFUNCTION("INT(FILTER(GT(E19,0),ISNUMBER(E19)))"),1.0) -> 1 | O19: =E19/(E19+F19) -> 1 | P19: =IFERROR(__xludf.DUMMYFUNCTION("INT(FILTER(EQ(D19,E19),ISNUMBER(D19),ISNUMBER(E19)))"),0.0) -> 0
A20: Molnupiravir-A Novel Oral Anti-SARS-CoV-2 Agent | B20: https://doi.org/10.3390/antibiotics10111294 | C20: Ministry of Health and Welfare;Ministry of Science and Technology, Taiwan;National Cheng Kung University Hospital | D20: =VLOOKUP(A20,'Web_of_Science_20251015 '!A:E,5,0) -> 3 | E20: 3 | F20: 0 | G20: Jacob | L20: =E20/D20 -> 1 | M20: =F20/D20 -> 0 | N20: =IFERROR(__xludf.DUMMYFUNCTION("INT(FILTER(GT(E20,0),ISNUMBER(E20)))"),1.0) -> 1 | O20: =E20/(E20+F20) -> 1 | P20: =IFERROR(__xludf.DUMMYFUNCTION("INT(FILTER(EQ(D20,E20),ISNUMBER(D20),ISNUMBER(E20)))"),1.0) -> 1
A21: Tailoring modulus and hardness of in-situ formed beta-Ti in bulk metallic glass composites by precipitation of isothermal omega-Ti | B21: https://doi.org/10.1016/j.matdes.2017.07.062 | C21: National Natural Science Foundation of China | D21: =VLOOKUP(A21,'Web_of_Science_20251015 '!A:E,5,0) -> 4 | E21: 1 | F21: 0 | G21: Jacob | L21: =E21/D21 -> 0.25 | M21: =F21/D21 -> 0 | N21: =IFERROR(__xludf.DUMMYFUNCTION("INT(FILTER(GT(E21,0),ISNUMBER(E21)))"),1.0) -> 1 | O21: =E21/(E21+F21) -> 1 | P21: =IFERROR(__xludf.DUMMYFUNCTION("INT(FILTER(EQ(D21,E21),ISNUMBER(D21),ISNUMBER(E21)))"),0.0) -> 0
A22: Comparative genomics of extrachromosomal elements in Bacillus thuringiensis subsp israelensis | B22: https://doi.org/10.1016/j.resmic.2016.10.008 | C22: Fonds De La Recherche Scientifique - FNRS;Agence Nationale de la Recherche;Université Catholique de Louvain | D22: =VLOOKUP(A22,'Web_of_Science_20251015 '!A:E,5,0) -> 3 | E22: 3 | F22: 0 | G22: Jacob | L22: =E22/D22 -> 1 | M22: =F22/D22 -> 0 | N22: =IFERROR(__xludf.DUMMYFUNCTION("INT(FILTER(GT(E22,0),ISNUMBER(E22)))"),1.0) -> 1 | O22: =E22/(E22+F22) -> 1
A23: Bicarbonate-based cultivation of Dunaliella salina for enhancing carbon utilization efficiency | B23: https://doi.org/10.1016/j.biortech.2017.04.009 | C23: Korea Electric Power Corporation | D23: =VLOOKUP(A23,'Web_of_Science_20251015 '!A:E,5,0) -> 2 | E23: 1 | F23: 0 | G23: Jacob | L23: =E23/D23 -> 0.5 | M23: =F23/D23 -> 0 | N23: =IFERROR(__xludf.DUMMYFUNCTION("INT(FILTER(GT(E23,0),ISNUMBER(E23)))"),1.0) -> 1 | O23: =E23/(E23+F23) -> 1 | P23: =IFERROR(__xludf.DUMMYFUNCTION("INT(FILTER(EQ(D23,E23),ISNUMBER(D23),ISNUMBER(E23)))"),0.0) -> 0
A24: Polysaccharides from chayote enhance lipid efflux and regulate NLRP3 inflammasome priming in macrophage-like THP-1 cells exposed to cholesterol crystals | B24: https://doi.org/10.1016/j.ijbiomac.2019.01.048 | C24: Coordenação de Aperfeiçoamento de Pessoal de Nível Superior;Fundação de Amparo à Pesquisa do Estado de São Paulo;Conselho Nacional de Desenvolvimento Científico e Tecnológico | D24: =VLOOKUP(A24,'Web_of_Science_20251015 '!A:E,5,0) -> 3 | E24: 3 | F24: 0 | G24: Jacob | L24: =E24/D24 -> 1 | M24: =F24/D24 -> 0 | N24: =IFERROR(__xludf.DUMMYFUNCTION("INT(FILTER(GT(E24,0),ISNUMBER(E24)))"),1.0) -> 1 | O24: =E24/(E24+F24) -> 1 | P24: =IFERROR(__xludf.DUMMYFUNCTION("INT(FILTER(EQ(D24,E24),ISNUMBER(D24),ISNUMBER(E24)))"),1.0) -> 1
A25: Mineral assemblage transformation of a metakaolin-based waste form after geopolymer encapsulation | B25: https://doi.org/10.1016/j.jnucmat.2015.12.023 | C25: Office of Environmental Management;Biological and Environmental Research | D25: =VLOOKUP(A25,'Web_of_Science_20251015 '!A:E,5,0) -> 1 | E25: 1 | F25: 0 | G25: Jacob | L25: =E25/D25 -> 1 | M25: =F25/D25 -> 0 | N25: =IFERROR(__xludf.DUMMYFUNCTION("INT(FILTER(GT(E25,0),ISNUMBER(E25)))"),1.0) -> 1 | O25: =E25/(E25+F25) -> 1 | P25: =IFERROR(__xludf.DUMMYFUNCTION("INT(FILTER(EQ(D25,E25),ISNUMBER(D25),ISNUMBER(E25)))"),1.0) -> 1
A26: Effects of zirconium silicate reinforcement on expandable graphite based intumescent fire retardant coating | B26: https://doi.org/10.1016/j.polymdegradstab.2014.02.016 | C26: Universiti Teknologi Petronas | D26: =VLOOKUP(A26,'Web_of_Science_20251015 '!A:E,5,0) -> 1 | E26: 1 | F26: 0 | G26: Jacob | L26: =E26/D26 -> 1 | M26: =F26/D26 -> 0 | N26: =IFERROR(__xludf.DUMMYFUNCTION("INT(FILTER(GT(E26,0),ISNUMBER(E26)))"),1.0) -> 1 | O26: =E26/(E26+F26) -> 1 | P26: =IFERROR(__xludf.DUMMYFUNCTION("INT(FILTER(EQ(D26,E26),ISNUMBER(D26),ISNUMBER(E26)))"),1.0) -> 1
A27: Energy Landscapes of Dynamic Ensembles of Rolling Triplet Repeat Bulge Loops: Implications for DNA Expansion Associated with Disease States | B27: https://doi.org/10.1021/ja3010896 | C27: National Institutes of Health | D27: =VLOOKUP(A27,'Web_of_Science_20251015 '!A:E,5,0) -> 3 | E27: 1 | F27: 0 | G27: Jacob | L27: =E27/D27 -> 0.33333333 | M27: =F27/D27 -> 0 | N27: =IFERROR(__xludf.DUMMYFUNCTION("INT(FILTER(GT(E27,0),ISNUMBER(E27)))"),1.0) -> 1 | O27: =E27/(E27+F27) -> 1 | P27: =IFERROR(__xludf.DUMMYFUNCTION("INT(FILTER(EQ(D27,E27),ISNUMBER(D27),ISNUMBER(E27)))"),0.0) -> 0
A28: Mechanochemical Synthesis of Ketones via Chemoselective Suzuki-Miyaura Cross-Coupling of Acyl Chlorides | B28: https://doi.org/10.1021/acs.orglett.2c00519 | C28: National Natural Science Foundation of China;Division of Chemistry | D28: =VLOOKUP(A28,'Web_of_Science_20251015 '!A:E,5,0) -> 3 | E28: 2 | F28: 0 | G28: Jacob | L28: =E28/D28 -> 0.66666667 | M28: =F28/D28 -> 0 | N28: =IFERROR(__xludf.DUMMYFUNCTION("INT(FILTER(GT(E28,0),ISNUMBER(E28)))"),1.0) -> 1 | O28: =E28/(E28+F28) -> 1 | P28: =IFERROR(__xludf.DUMMYFUNCTION("INT(FILTER(EQ(D28,E28),ISNUMBER(D28),ISNUMBER(E28)))"),0.0) -> 0
A29: Model reduction: When singular perturbation analysis simplifies to partial equilibrium approximation | B29: https://doi.org/10.1016/j.combustflame.2014.09.022 | C29: European Social Fund;European Commission | D29: =VLOOKUP(A29,'Web_of_Science_20251015 '!A:E,5,0) -> 2 | E29: 1 | F29: 0 | G29: Jacob | L29: =E29/D29 -> 0.5 | M29: =F29/D29 -> 0 | N29: =IFERROR(__xludf.DUMMYFUNCTION("INT(FILTER(GT(E29,0),ISNUMBER(E29)))"),1.0) -> 1 | O29: =E29/(E29+F29) -> 1 | P29: =IFERROR(__xludf.DUMMYFUNCTION("INT(FILTER(EQ(D29,E29),ISNUMBER(D29),ISNUMBER(E29)))"),0.0) -> 0
A30: Proteomics and Phosphoproteomics Profiling of Drug-Addicted BRAFi-Resistant Melanoma Cells | B30: https://doi.org/10.1021/acs.jproteome.1c00331 | C30: China Scholarship Council;Nederlandse Organisatie voor Wetenschappelijk Onderzoek | D30: =VLOOKUP(A30,'Web_of_Science_20251015 '!A:E,5,0) -> 2 | E30: 2 | F30: 0 | G30: Jacob | L30: =E30/D30 -> 1 | M30: =F30/D30 -> 0 | N30: =IFERROR(__xludf.DUMMYFUNCTION("INT(FILTER(GT(E30,0),ISNUMBER(E30)))"),1.0) -> 1 | O30: =E30/(E30+F30) -> 1 | P30: =IFERROR(__xludf.DUMMYFUNCTION("INT(FILTER(EQ(D30,E30),ISNUMBER(D30),ISNUMBER(E30)))"),1.0) -> 1
A31: A multi-class SVM approach based on the l(1)-norm minimization of the distances between the reduced convex hulls | B31: https://doi.org/10.1016/j.patcog.2014.12.006 | C31: Fondo Nacional de Desarrollo Científico y Tecnológico | D31: =VLOOKUP(A31,'Web_of_Science_20251015 '!A:E,5,0) -> 2 | E31: 1 | F31: 0 | G31: Jacob | L31: =E31/D31 -> 0.5 | M31: =F31/D31 -> 0 | N31: =IFERROR(__xludf.DUMMYFUNCTION("INT(FILTER(GT(E31,0),ISNUMBER(E31)))"),1.0) -> 1 | O31: =E31/(E31+F31) -> 1 | P31: =IFERROR(__xludf.DUMMYFUNCTION("INT(FILTER(EQ(D31,E31),ISNUMBER(D31),ISNUMBER(E31)))"),0.0) -> 0
A32: Oxidative Dissolution of Arsenic-Bearing Sulfide Minerals inGroundwater: Impact of Hydrochemical and HydrodynamicConditions on Arsenic Release and Surface Evolution | B32: https://doi.org/10.1021/acs.est.2c00309 | C32: Danmarks Frie Forskningsfond;Villum Fonden | D32: =VLOOKUP(A32,'Web_of_Science_20251015 '!A:E,5,0) -> 2 | E32: 2 | F32: 0 | G32: Jacob | L32: =E32/D32 -> 1 | M32: =F32/D32 -> 0 | N32: =IFERROR(__xludf.DUMMYFUNCTION("INT(FILTER(GT(E32,0),ISNUMBER(E32)))"),1.0) -> 1 | O32: =E32/(E32+F32) -> 1 | P32: =IFERROR(__xludf.DUMMYFUNCTION("INT(FILTER(EQ(D32,E32),ISNUMBER(D32),ISNUMBER(E32)))"),1.0) -> 1
A33: Classification Method and Determination of Mountainous Area Types at Township Scales: A Case Study of Yuxi City, Yunnan Province | B33: https://doi.org/10.1155/2020/3484568 | C33: National Natural Science Foundation of China | D33: =VLOOKUP(A33,'Web_of_Science_20251015 '!A:E,5,0) -> 3 | E33: 1 | F33: 0 | G33: Jacob | L33: =E33/D33 -> 0.33333333 | M33: =F33/D33 -> 0 | N33: =IFERROR(__xludf.DUMMYFUNCTION("INT(FILTER(GT(E33,0),ISNUMBER(E33)))"),1.0) -> 1 | O33: =E33/(E33+F33) -> 1
A34: A new twist for Stork-Danheiser products enabled by visible light mediated trans-cyclohexene formation; access to acyclic distal enones | B34: https://doi.org/10.1039/d1sc03774a | C34: Herman Frasch Foundation for Chemical Research;National Science Foundation;National Institute of General Medical Sciences | D34: =VLOOKUP(A34,'Web_of_Science_20251015 '!A:E,5,0) -> 4 | E34: 3 | F34: 0 | G34: Jacob | L34: =E34/D34 -> 0.75 | M34: =F34/D34 -> 0 | N34: =IFERROR(__xludf.DUMMYFUNCTION("INT(FILTER(GT(E34,0),ISNUMBER(E34)))"),1.0) -> 1 | O34: =E34/(E34+F34) -> 1 | P34: =IFERROR(__xludf.DUMMYFUNCTION("INT(FILTER(EQ(D34,E34),ISNUMBER(D34),ISNUMBER(E34)))"),0.0) -> 0
A35: Effect of Sodium Sulfite, Sodium Dodecyl Sulfate, and Urea on the Molecular Interactions and Properties of Whey Protein Isolate-Based Films | B35: https://doi.org/10.3389/fchem.2016.00049 | C35: Karlsruhe Institute of Technology;Bundesministerium für Bildung und Forschung;Seventh Framework Programme | D35: =VLOOKUP(A35,'Web_of_Science_20251015 '!A:E,5,0) -> 4 | E35: 2 | F35: 0 | G35: Jacob | L35: =E35/D35 -> 0.5 | M35: =F35/D35 -> 0 | N35: =IFERROR(__xludf.DUMMYFUNCTION("INT(FILTER(GT(E35,0),ISNUMBER(E35)))"),1.0) -> 1 | O35: =E35/(E35+F35) -> 1 | P35: =IFERROR(__xludf.DUMMYFUNCTION("INT(FILTER(EQ(D35,E35),ISNUMBER(D35),ISNUMBER(E35)))"),0.0) -> 0
A36: Efficient, adaptive energy stable schemes for the incompressible Cahn-Hilliard Navier-Stokes phase-field models | B36: https://doi.org/10.1016/j.jcp.2015.12.006 | C36: National Science Foundation;Air Force Office of Scientific Research | D36: =VLOOKUP(A36,'Web_of_Science_20251015 '!A:E,5,0) -> 2 | E36: 2 | F36: 0 | G36: Jacob | L36: =E36/D36 -> 1 | M36: =F36/D36 -> 0 | N36: =IFERROR(__xludf.DUMMYFUNCTION("INT(FILTER(GT(E36,0),ISNUMBER(E36)))"),1.0) -> 1 | O36: =E36/(E36+F36) -> 1 | P36: =IFERROR(__xludf.DUMMYFUNCTION("INT(FILTER(EQ(D36,E36),ISNUMBER(D36),ISNUMBER(E36)))"),1.0) -> 1
A37: Relationship between tree height and landslide characteristics obtained by GIS assessment | B37: https://doi.org/10.1002/esp.4964 | C37: Japan Society for the Promotion of Science | D37: =VLOOKUP(A37,'Web_of_Science_20251015 '!A:E,5,0) -> 1 | E37: 1 | F37: 0 | G37: Jacob | L37: =E37/D37 -> 1 | M37: =F37/D37 -> 0 | N37: =IFERROR(__xludf.DUMMYFUNCTION("INT(FILTER(GT(E37,0),ISNUMBER(E37)))"),1.0) -> 1 | O37: =E37/(E37+F37) -> 1 | P37: =IFERROR(__xludf.DUMMYFUNCTION("INT(FILTER(EQ(D37,E37),ISNUMBER(D37),ISNUMBER(E37)))"),1.0) -> 1
A38: Extensions and applications of equitable decompositions for graphs with symmetries | B38: https://doi.org/10.1016/j.laa.2017.06.045 | C38: U.S. Department of Defense | D38: =VLOOKUP(A38,'Web_of_Science_20251015 '!A:E,5,0) -> 1 | E38: 1 | F38: 0 | G38: Jacob | L38: =E38/D38 -> 1 | M38: =F38/D38 -> 0 | N38: =IFERROR(__xludf.DUMMYFUNCTION("INT(FILTER(GT(E38,0),ISNUMBER(E38)))"),1.0) -> 1 | O38: =E38/(E38+F38) -> 1 | P38: =IFERROR(__xludf.DUMMYFUNCTION("INT(FILTER(EQ(D38,E38),ISNUMBER(D38),ISNUMBER(E38)))"),1.0) -> 1
A39: Versatile Synthesis of rac- and meso-Hydroxymethyl Cyclohexenoids Containing Phenyl Groups: alpha-/beta-Glucosidase Activities, Inhibition Kinetics and Molecular Docking Studies | B39: https://doi.org/10.1002/ejoc.202200165 | C39: Türkiye Bilimsel ve Teknolojik Araştırma Kurumu;Sakarya Üniversitesi | D39: =VLOOKUP(A39,'Web_of_Science_20251015 '!A:E,5,0) -> 2 | E39: 2 | F39: 0 | G39: Jacob | L39: =E39/D39 -> 1 | M39: =F39/D39 -> 0 | N39: =IFERROR(__xludf.DUMMYFUNCTION("INT(FILTER(GT(E39,0),ISNUMBER(E39)))"),1.0) -> 1 | O39: =E39/(E39+F39) -> 1 | P39: =IFERROR(__xludf.DUMMYFUNCTION("INT(FILTER(EQ(D39,E39),ISNUMBER(D39),ISNUMBER(E39)))"),1.0) -> 1
A40: Multi-Emitter MAP-Elites | B40: https://doi.org/10.1145/3449639.3459326 | C40: Engineering and Physical Sciences Research Council | D40: =VLOOKUP(A40,'Web_of_Science_20251015 '!A:E,5,0) -> 1 | E40: 1 | F40: 0 | G40: Jacob | L40: =E40/D40 -> 1 | M40: =F40/D40 -> 0 | N40: =IFERROR(__xludf.DUMMYFUNCTION("INT(FILTER(GT(E40,0),ISNUMBER(E40)))"),1.0) -> 1 | O40: =E40/(E40+F40) -> 1 | P40: =IFERROR(__xludf.DUMMYFUNCTION("INT(FILTER(EQ(D40,E40),ISNUMBER(D40),ISNUMBER(E40)))"),1.0) -> 1
A41: Total synthesis of naturally occurring chiral cyclopropane fatty acids and related compounds | B41: https://doi.org/10.1016/j.tetlet.2019.03.043 | C41: Japan Society for the Promotion of Science | D41: =VLOOKUP(A41,'Web_of_Science_20251015 '!A:E,5,0) -> 1 | E41: 1 | F41: 0 | G41: Jacob | L41: =E41/D41 -> 1 | M41: =F41/D41 -> 0 | N41: =IFERROR(__xludf.DUMMYFUNCTION("INT(FILTER(GT(E41,0),ISNUMBER(E41)))"),1.0) -> 1 | O41: =E41/(E41+F41) -> 1 | P41: =IFERROR(__xludf.DUMMYFUNCTION("INT(FILTER(EQ(D41,E41),ISNUMBER(D41),ISNUMBER(E41)))"),1.0) -> 1
A42: High gene flow and complex treeline dynamics of Larix Mill. stands on the Taymyr Peninsula (north-central Siberia) revealed by nuclear microsatellites | B42: https://doi.org/10.1007/s11295-018-1235-3 | C42: Deutsche Forschungsgemeinschaft;Helmholtz-Gemeinschaft | D42: =VLOOKUP(A42,'Web_of_Science_20251015 '!A:E,5,0) -> 2 | E42: 2 | F42: 0 | G42: Jacob | L42: =E42/D42 -> 1 | M42: =F42/D42 -> 0 | N42: =IFERROR(__xludf.DUMMYFUNCTION("INT(FILTER(GT(E42,0),ISNUMBER(E42)))"),1.0) -> 1 | O42: =E42/(E42+F42) -> 1 | P42: =IFERROR(__xludf.DUMMYFUNCTION("INT(FILTER(EQ(D42,E42),ISNUMBER(D42),ISNUMBER(E42)))"),1.0) -> 1
A43: Nitrogen differentially modulates photosynthesis, carbon allocation and yield related traits in two contrasting Capsicum chinense cultivars | B43: https://doi.org/10.1016/j.plantsci.2019.02.014 | C43: Fundação de Amparo à Pesquisa do Estado de Minas Gerais;Conselho Nacional de Desenvolvimento Científico e Tecnológico | D43: =VLOOKUP(A43,'Web_of_Science_20251015 '!A:E,5,0) -> 3 | E43: 2 | F43: 0 | G43: Jacob | L43: =E43/D43 -> 0.66666667 | M43: =F43/D43 -> 0 | N43: =IFERROR(__xludf.DUMMYFUNCTION("INT(FILTER(GT(E43,0),ISNUMBER(E43)))"),1.0) -> 1 | O43: =E43/(E43+F43) -> 1 | P43: =IFERROR(__xludf.DUMMYFUNCTION("INT(FILTER(EQ(D43,E43),ISNUMBER(D43),ISNUMBER(E43)))"),0.0) -> 0
A44: Prevalence of Trading Sex Among High School Students in Minnesota: Demographics, Relevant Adverse Experiences, and Health-Related Statuses | B44: https://doi.org/10.1016/j.jadohealth.2020.08.021 | C44: Women's Foundation of Minnesota | D44: =VLOOKUP(A44,'Web_of_Science_20251015 '!A:E,5,0) -> 2 | E44: 1 | F44: 0 | G44: Jacob | L44: =E44/D44 -> 0.5 | M44: =F44/D44 -> 0 | N44: =IFERROR(__xludf.DUMMYFUNCTION("INT(FILTER(GT(E44,0),ISNUMBER(E44)))"),1.0) -> 1 | O44: =E44/(E44+F44) -> 1
A45: Effect of Complex Surface Treatment on Morphology and Electrochemical Properties of La-Mg-Ni-Based Alloys | B45: https://doi.org/10.1149/2.1281712jes | C45: National Natural Science Foundation of China | D45: =VLOOKUP(A45,'Web_of_Science_20251015 '!A:E,5,0) -> 2 | E45: 1 | F45: 0 | G45: Jacob | L45: =E45/D45 -> 0.5 | M45: =F45/D45 -> 0 | N45: =IFERROR(__xludf.DUMMYFUNCTION("INT(FILTER(GT(E45,0),ISNUMBER(E45)))"),1.0) -> 1 | O45: =E45/(E45+F45) -> 1 | P45: =IFERROR(__xludf.DUMMYFUNCTION("INT(FILTER(EQ(D45,E45),ISNUMBER(D45),ISNUMBER(E45)))"),0.0) -> 0
A46: A protein that controls the onset of a Salmonella virulence program | B46: https://doi.org/10.15252/embj.201796977 | C46: National Institutes of Health | D46: =VLOOKUP(A46,'Web_of_Science_20251015 '!A:E,5,0) -> 1 | E46: 1 | F46: 0 | G46: Jacob | L46: =E46/D46 -> 1 | M46: =F46/D46 -> 0 | N46: =IFERROR(__xludf.DUMMYFUNCTION("INT(FILTER(GT(E46,0),ISNUMBER(E46)))"),1.0) -> 1 | O46: =E46/(E46+F46) -> 1 | P46: =IFERROR(__xludf.DUMMYFUNCTION("INT(FILTER(EQ(D46,E46),ISNUMBER(D46),ISNUMBER(E46)))"),1.0) -> 1
A47: Single Infrared Image-Based Stripe Nonuniformity Correction via a Two-Stage Filtering Method | B47: https://doi.org/10.3390/s18124299 | C47: National Natural Science Foundation of China | D47: =VLOOKUP(A47,'Web_of_Science_20251015 '!A:E,5,0) -> 2 | E47: 0 | F47: 1 | G47: Jacob | L47: =E47/D47 -> 0 | M47: =F47/D47 -> 0.5 | N47: =IFERROR(__xludf.DUMMYFUNCTION("INT(FILTER(GT(E47,0),ISNUMBER(E47)))"),0.0) -> 0 | O47: =E47/(E47+F47) -> 0 | P47: =IFERROR(__xludf.DUMMYFUNCTION("INT(FILTER(EQ(D47,E47),ISNUMBER(D47),ISNUMBER(E47)))"),0.0) -> 0
A48: Effect of different drying techniques on drying kinetics, nutritional components, antioxidant capacity, physical properties and microstructure of edamame | B48: https://doi.org/10.1016/j.foodchem.2021.131412 | C48: Foundation for Innovative Research Groups of the National Natural Science Foundation of China | D48: =VLOOKUP(A48,'Web_of_Science_20251015 '!A:E,5,0) -> 2 | E48: 0 | F48: 1 | G48: Jacob | L48: =E48/D48 -> 0 | M48: =F48/D48 -> 0.5 | N48: =IFERROR(__xludf.DUMMYFUNCTION("INT(FILTER(GT(E48,0),ISNUMBER(E48)))"),0.0) -> 0 | O48: =E48/(E48+F48) -> 0 | P48: =IFERROR(__xludf.DUMMYFUNCTION("INT(FILTER(EQ(D48,E48),ISNUMBER(D48),ISNUMBER(E48)))"),0.0) -> 0
A49: Structural Transformation of Li-Excess Cathode Materials via Facile Preparation and Assembly of Sonication-Induced Colloidal Nanocrystals for Enhanced Lithium Storage Performance | B49: https://doi.org/10.1021/acsami.7b09981 | C49: China Postdoctoral Science Foundation;Government of Jiangsu Province;Division of Chemical, Bioengineering, Environmental, and Transport Systems;Louisiana Space Consortium;National Natural Science Foundation of China | D49: =VLOOKUP(A49,'Web_of_Science_20251015 '!A:E,5,0) -> 5 | E49: 5 | F49: 0 | G49: Jacob | L49: =E49/D49 -> 1 | M49: =F49/D49 -> 0 | N49: =IFERROR(__xludf.DUMMYFUNCTION("INT(FILTER(GT(E49,0),ISNUMBER(E49)))"),1.0) -> 1 | O49: =E49/(E49+F49) -> 1 | P49: =IFERROR(__xludf.DUMMYFUNCTION("INT(FILTER(EQ(D49,E49),ISNUMBER(D49),ISNUMBER(E49)))"),1.0) -> 1
A50: The influence of microwave treatment on the mode I fracture toughness of granite | B50: https://doi.org/10.1016/j.engfracmech.2021.107768 | C50: National Natural Science Foundation of China | D50: =VLOOKUP(A50,'Web_of_Science_20251015 '!A:E,5,0) -> 1 | E50: 1 | F50: 0 | G50: Jacob | L50: =E50/D50 -> 1 | M50: =F50/D50 -> 0 | N50: =IFERROR(__xludf.DUMMYFUNCTION("INT(FILTER(GT(E50,0),ISNUMBER(E50)))"),1.0) -> 1 | O50: =E50/(E50+F50) -> 1 | P50: =IFERROR(__xludf.DUMMYFUNCTION("INT(FILTER(EQ(D50,E50),ISNUMBER(D50),ISNUMBER(E50)))"),1.0) -> 1
A51: Dual Role of Lithium on the Structure and Self-Healing Ability of PMMA-Silica Coatings on AA7075 Alloy | B51: https://doi.org/10.1021/acsami.9b13839 | C51: Coordenação de Aperfeiçoamento de Pessoal de Nível Superior;Fundação de Amparo à Pesquisa do Estado de São Paulo;Conselho Nacional de Desenvolvimento Científico e Tecnológico;Fonds Wetenschappelijk Onderzoek | D51: =VLOOKUP(A51,'Web_of_Science_20251015 '!A:E,5,0) -> 6 | E51: 4 | F51: 0 | G51: Jacob | L51: =E51/D51 -> 0.66666667 | M51: =F51/D51 -> 0 | N51: =IFERROR(__xludf.DUMMYFUNCTION("INT(FILTER(GT(E51,0),ISNUMBER(E51)))"),1.0) -> 1 | O51: =E51/(E51+F51) -> 1 | P51: =IFERROR(__xludf.DUMMYFUNCTION("INT(FILTER(EQ(D51,E51),ISNUMBER(D51),ISNUMBER(E51)))"),0.0) -> 0
A52: Astragaloside IV Alleviates Brain Injury Induced by Hypoxia via the Calpain-1 Signaling Pathway | B52: https://doi.org/10.1155/2022/6509981 | C52: National Natural Science Foundation of China | D52: =VLOOKUP(A52,'Web_of_Science_20251015 '!A:E,5,0) -> 2 | E52: 1 | F52: 0 | G52: Jacob | L52: =E52/D52 -> 0.5 | M52: =F52/D52 -> 0 | N52: =IFERROR(__xludf.DUMMYFUNCTION("INT(FILTER(GT(E52,0),ISNUMBER(E52)))"),1.0) -> 1 | O52: =E52/(E52+F52) -> 1 | P52: =IFERROR(__xludf.DUMMYFUNCTION("INT(FILTER(EQ(D52,E52),ISNUMBER(D52),ISNUMBER(E52)))"),0.0) -> 0
A53: Correlation measurements between flow harmonics in Au plus Au collisions at RHIC | B53: https://doi.org/10.1016/j.physletb.2018.05.076 | C53: State Atomic Energy Corporation ROSATOM;National Natural Science Foundation of China;Department of Science and Technology, Ministry of Science and Technology, India;Nuclear Physics;Ministry of Education of the People's Republic of China;Ministry of Science and Technology of the People's Republic of China;Ministry of Education and Science of the Russian Federation;Ministarstvo Znanosti, Obrazovanja i Sporta;Department of Atomic Energy, Government of India;National Science Foundation;Helmholtz Association;Bundesministerium für Bildung und Forschung;Chinese Academy of Sciences;National Research Foundation of Korea;Narodowe Centrum Nauki | D53: =VLOOKUP(A53,'Web_of_Science_20251015 '!A:E,5,0) -> 19 | E53: 16 | F53: 0 | G53: Jacob | L53: =E53/D53 -> 0.84210526 | M53: =F53/D53 -> 0 | N53: =IFERROR(__xludf.DUMMYFUNCTION("INT(FILTER(GT(E53,0),ISNUMBER(E53)))"),1.0) -> 1 | O53: =E53/(E53+F53) -> 1 | P53: =IFERROR(__xludf.DUMMYFUNCTION("INT(FILTER(EQ(D53,E53),ISNUMBER(D53),ISNUMBER(E53)))"),0.0) -> 0
A54: Dy(III)-Based Metal-Organic Framework as a Fluorescent Probe for Highly Selective Detection of Picric Acid in Aqueous Medium | B54: https://doi.org/10.1021/acs.inorgchem.9b02611 | C54: Council of Scientific and Industrial Research, India;Science and Engineering Research Board;Indian Institute of Technology Indore;Ministry of Education, India | D54: =VLOOKUP(A54,'Web_of_Science_20251015 '!A:E,5,0) -> 5 | E54: 4 | F54: 0 | G54: Jin | L54: =E54/D54 -> 0.8 | M54: =F54/D54 -> 0 | N54: =IFERROR(__xludf.DUMMYFUNCTION("INT(FILTER(GT(E54,0),ISNUMBER(E54)))"),1.0) -> 1 | O54: =E54/(E54+F54) -> 1 | P54: =IFERROR(__xludf.DUMMYFUNCTION("INT(FILTER(EQ(D54,E54),ISNUMBER(D54),ISNUMBER(E54)))"),0.0) -> 0
A55: Protonic and Electronic Transport in Hydrated Thin Films of the Pigment Eumelanin | B55: https://doi.org/10.1021/cm502939r | C55: Consejo Nacional de Ciencia y Tecnología;Canada Foundation for Innovation;Natural Sciences and Engineering Research Council of Canada;Directorate-General for Research and Innovation;Fonds Québécois de la Recherche sur la Nature et les Technologies;Division of Materials Research | D55: =VLOOKUP(A55,'Web_of_Science_20251015 '!A:E,5,0) -> 9 | E55: 5 | F55: 1 | G55: Jin | L55: =E55/D55 -> 0.55555556 | M55: =F55/D55 -> 0.11111111 | N55: =IFERROR(__xludf.DUMMYFUNCTION("INT(FILTER(GT(E55,0),ISNUMBER(E55)))"),1.0) -> 1 | O55: =E55/(E55+F55) -> 0.83333333
A56: Hydrophilic directional slippery rough surfaces for water harvesting | B56: https://doi.org/10.1126/sciadv.aaq0919 | C56: Office of Naval Research;Advanced Research Projects Agency - Energy;National Science Foundation | D56: =VLOOKUP(A56,'Web_of_Science_20251015 '!A:E,5,0) -> 6 | E56: 3 | F56: 0 | G56: Jin | L56: =E56/D56 -> 0.5 | M56: =F56/D56 -> 0 | N56: =IFERROR(__xludf.DUMMYFUNCTION("INT(FILTER(GT(E56,0),ISNUMBER(E56)))"),1.0) -> 1 | O56: =E56/(E56+F56) -> 1 | P56: =IFERROR(__xludf.DUMMYFUNCTION("INT(FILTER(EQ(D56,E56),ISNUMBER(D56),ISNUMBER(E56)))"),0.0) -> 0
A57: Er-Xian Decoction Stimulates Osteoblastic Differentiation of Bone Mesenchymal Stem Cells in Ovariectomized Mice and Its Gene Profile Analysis | B57: https://doi.org/10.1155/2016/4079210 | C57: National Natural Science Foundation of China | D57: =VLOOKUP(A57,'Web_of_Science_20251015 '!A:E,5,0) -> 4 | E57: 1 | F57: 0 | G57: Jin | L57: =E57/D57 -> 0.25 | M57: =F57/D57 -> 0 | N57: =IFERROR(__xludf.DUMMYFUNCTION("INT(FILTER(GT(E57,0),ISNUMBER(E57)))"),1.0) -> 1 | O57: =E57/(E57+F57) -> 1 | P57: =IFERROR(__xludf.DUMMYFUNCTION("INT(FILTER(EQ(D57,E57),ISNUMBER(D57),ISNUMBER(E57)))"),0.0) -> 0
A58: Graphitic carbon nitride derivative with large mesopores as sorbent for solid-phase microextraction of polycyclic aromatic hydrocarbons | B58: https://doi.org/10.1016/j.talanta.2019.120541 | C58: National Natural Science Foundation of China;Natural Science Foundation of Fujian Province | D58: =VLOOKUP(A58,'Web_of_Science_20251015 '!A:E,5,0) -> 4 | E58: 2 | F58: 0 | G58: Jin | L58: =E58/D58 -> 0.5 | M58: =F58/D58 -> 0 | N58: =IFERROR(__xludf.DUMMYFUNCTION("INT(FILTER(GT(E58,0),ISNUMBER(E58)))"),1.0) -> 1 | O58: =E58/(E58+F58) -> 1 | P58: =IFERROR(__xludf.DUMMYFUNCTION("INT(FILTER(EQ(D58,E58),ISNUMBER(D58),ISNUMBER(E58)))"),0.0) -> 0
A59: Evolving tRNA(Sec) for Efficient Canonical Incorporation of Selenocysteine | B59: https://doi.org/10.1021/ja510695g | C59: Welch Foundation;Division of Chemistry | D59: =VLOOKUP(A59,'Web_of_Science_20251015 '!A:E,5,0) -> 2 | E59: 2 | F59: 1 | G59: Jin | L59: =E59/D59 -> 1 | M59: =F59/D59 -> 0.5 | N59: =IFERROR(__xludf.DUMMYFUNCTION("INT(FILTER(GT(E59,0),ISNUMBER(E59)))"),1.0) -> 1 | O59: =E59/(E59+F59) -> 0.66666667 | P59: =IFERROR(__xludf.DUMMYFUNCTION("INT(FILTER(EQ(D59,E59),ISNUMBER(D59),ISNUMBER(E59)))"),1.0) -> 1
A60: CRISPR babies: a view from the centre of the storm | B60: https://doi.org/10.1242/dev.175778 | C60: Cancer Research UK;Wellcome;Medical Research Council | D60: =VLOOKUP(A60,'Web_of_Science_20251015 '!A:E,5,0) -> 4 | E60: 3 | F60: 0 | G60: Jin | L60: =E60/D60 -> 0.75 | M60: =F60/D60 -> 0 | N60: =IFERROR(__xludf.DUMMYFUNCTION("INT(FILTER(GT(E60,0),ISNUMBER(E60)))"),1.0) -> 1 | O60: =E60/(E60+F60) -> 1 | P60: =IFERROR(__xludf.DUMMYFUNCTION("INT(FILTER(EQ(D60,E60),ISNUMBER(D60),ISNUMBER(E60)))"),0.0) -> 0
A61: Energy Efficient Sleep Schedule with Service Coverage Guarantee in Wireless Sensor Networks | B61: https://doi.org/10.1007/s10922-015-9361-9 | C61: Fundamental Research Funds for the Central Universities;National Natural Science Foundation of China | D61: =VLOOKUP(A61,'Web_of_Science_20251015 '!A:E,5,0) -> 6 | E61: 2 | F61: 0 | G61: Jin | L61: =E61/D61 -> 0.33333333 | M61: =F61/D61 -> 0 | N61: =IFERROR(__xludf.DUMMYFUNCTION("INT(FILTER(GT(E61,0),ISNUMBER(E61)))"),1.0) -> 1 | O61: =E61/(E61+F61) -> 1 | P61: =IFERROR(__xludf.DUMMYFUNCTION("INT(FILTER(EQ(D61,E61),ISNUMBER(D61),ISNUMBER(E61)))"),0.0) -> 0
A62: Image fusion employing adaptive spectral-spatial gradient sparse regularization in UAV remote sensing | B62: https://doi.org/10.1016/j.sigpro.2019.107434 | C62: Fundamental Research Funds for the Central Universities;National Natural Science Foundation of China;Natural Science Foundation of Hubei Province | D62: =VLOOKUP(A62,'Web_of_Science_20251015 '!A:E,5,0) -> 3 | E62: 3 | F62: 0 | G62: Jin | L62: =E62/D62 -> 1 | M62: =F62/D62 -> 0 | N62: =IFERROR(__xludf.DUMMYFUNCTION("INT(FILTER(GT(E62,0),ISNUMBER(E62)))"),1.0) -> 1 | O62: =E62/(E62+F62) -> 1 | P62: =IFERROR(__xludf.DUMMYFUNCTION("INT(FILTER(EQ(D62,E62),ISNUMBER(D62),ISNUMBER(E62)))"),1.0) -> 1
A63: Protein interactions of FAM134B with EB1 and APC/beta-catenin in vitro in colon carcinoma | B63: https://doi.org/10.1002/mc.22871 | C63: Griffith University | D63: =VLOOKUP(A63,'Web_of_Science_20251015 '!A:E,5,0) -> 1 | E63: 1 | F63: 0 | G63: Jin | L63: =E63/D63 -> 1 | M63: =F63/D63 -> 0 | N63: =IFERROR(__xludf.DUMMYFUNCTION("INT(FILTER(GT(E63,0),ISNUMBER(E63)))"),1.0) -> 1 | O63: =E63/(E63+F63) -> 1 | P63: =IFERROR(__xludf.DUMMYFUNCTION("INT(FILTER(EQ(D63,E63),ISNUMBER(D63),ISNUMBER(E63)))"),1.0) -> 1
A64: Use of isotope exchange for determining series of elementary steps in electrocatalysis and heterogeneous catalysis | B64: https://doi.org/10.1016/j.ssi.2016.11.012 | C64: Israel Science Foundation | D64: =VLOOKUP(A64,'Web_of_Science_20251015 '!A:E,5,0) -> 1 | E64: 1 | F64: 0 | G64: Jin | L64: =E64/D64 -> 1 | M64: =F64/D64 -> 0 | N64: =IFERROR(__xludf.DUMMYFUNCTION("INT(FILTER(GT(E64,0),ISNUMBER(E64)))"),1.0) -> 1 | O64: =E64/(E64+F64) -> 1 | P64: =IFERROR(__xludf.DUMMYFUNCTION("INT(FILTER(EQ(D64,E64),ISNUMBER(D64),ISNUMBER(E64)))"),1.0) -> 1
A65: GCdiscrimination: identification of gastric cancer based on a milliliter of blood | B65: https://doi.org/10.1093/bib/bbaa006 | C65: National Natural Science Foundation of China;Lanzhou University | D65: =VLOOKUP(A65,'Web_of_Science_20251015 '!A:E,5,0) -> 3 | E65: 2 | F65: 0 | G65: Jin | L65: =E65/D65 -> 0.66666667 | M65: =F65/D65 -> 0 | N65: =IFERROR(__xludf.DUMMYFUNCTION("INT(FILTER(GT(E65,0),ISNUMBER(E65)))"),1.0) -> 1 | O65: =E65/(E65+F65) -> 1 | P65: =IFERROR(__xludf.DUMMYFUNCTION("INT(FILTER(EQ(D65,E65),ISNUMBER(D65),ISNUMBER(E65)))"),0.0) -> 0
A66: Self-Organized Fission Control for Flocking System | B66: https://doi.org/10.1155/2015/321781 | C66: National Natural Science Foundation of China | D66: =VLOOKUP(A66,'Web_of_Science_20251015 '!A:E,5,0) -> 1 | E66: 1 | F66: 0 | G66: Jin | L66: =E66/D66 -> 1 | M66: =F66/D66 -> 0 | N66: =IFERROR(__xludf.DUMMYFUNCTION("INT(FILTER(GT(E66,0),ISNUMBER(E66)))"),1.0) -> 1 | O66: =E66/(E66+F66) -> 1
A67: Emerging approaches to stabilise photocorrodible electrodes and catalysts for solar fuel applications | B67: https://doi.org/10.1039/c7ee00777a | C67: Christian Doppler Forschungsgesellschaft;European Commission | D67: =VLOOKUP(A67,'Web_of_Science_20251015 '!A:E,5,0) -> 3 | E67: 2 | F67: 0 | G67: Jin | L67: =E67/D67 -> 0.66666667 | M67: =F67/D67 -> 0 | N67: =IFERROR(__xludf.DUMMYFUNCTION("INT(FILTER(GT(E67,0),ISNUMBER(E67)))"),1.0) -> 1 | O67: =E67/(E67+F67) -> 1 | P67: =IFERROR(__xludf.DUMMYFUNCTION("INT(FILTER(EQ(D67,E67),ISNUMBER(D67),ISNUMBER(E67)))"),0.0) -> 0
A68: Intracellular TRPA1 mediates Ca2+ release from lysosomes in dorsal root ganglion neurons | B68: https://doi.org/10.1083/jcb.201603081 | C68: National Natural Science Foundation of China;National Institutes of Health | D68: =VLOOKUP(A68,'Web_of_Science_20251015 '!A:E,5,0) -> 4 | E68: 2 | F68: 0 | G68: Jin | L68: =E68/D68 -> 0.5 | M68: =F68/D68 -> 0 | N68: =IFERROR(__xludf.DUMMYFUNCTION("INT(FILTER(GT(E68,0),ISNUMBER(E68)))"),1.0) -> 1 | O68: =E68/(E68+F68) -> 1 | P68: =IFERROR(__xludf.DUMMYFUNCTION("INT(FILTER(EQ(D68,E68),ISNUMBER(D68),ISNUMBER(E68)))"),0.0) -> 0
A69: Structure optimization for improving the strength and ductility of heterogeneous carbon nanotube/Al-Cu-Mg composites | B69: https://doi.org/10.1016/j.carbon.2021.03.006 | C69: National Natural Science Foundation of China;Youth Innovation Promotion Association of the Chinese Academy of Sciences | D69: =VLOOKUP(A69,'Web_of_Science_20251015 '!A:E,5,0) -> 5 | E69: 2 | F69: 0 | G69: Jin | L69: =E69/D69 -> 0.4 | M69: =F69/D69 -> 0 | N69: =IFERROR(__xludf.DUMMYFUNCTION("INT(FILTER(GT(E69,0),ISNUMBER(E69)))"),1.0) -> 1 | O69: =E69/(E69+F69) -> 1 | P69: =IFERROR(__xludf.DUMMYFUNCTION("INT(FILTER(EQ(D69,E69),ISNUMBER(D69),ISNUMBER(E69)))"),0.0) -> 0
A70: Study on the bending behavior of biodegradable metal cerebral vascular stents using finite element analysis | B70: https://doi.org/10.1016/j.jbiomech.2020.109856 | C70: National Key Research and Development Program of China;National Natural Science Foundation of China;Fundamental Research Funds for the Central Universities | D70: =VLOOKUP(A70,'Web_of_Science_20251015 '!A:E,5,0) -> 4 | E70: 3 | F70: 0 | G70: Jin | L70: =E70/D70 -> 0.75 | M70: =F70/D70 -> 0 | N70: =IFERROR(__xludf.DUMMYFUNCTION("INT(FILTER(GT(E70,0),ISNUMBER(E70)))"),1.0) -> 1 | O70: =E70/(E70+F70) -> 1 | P70: =IFERROR(__xludf.DUMMYFUNCTION("INT(FILTER(EQ(D70,E70),ISNUMBER(D70),ISNUMBER(E70)))"),0.0) -> 0
A71: Northern hardwood regeneration dynamics 10 years after irregular shelterwood and mechanical control of understory American beech | B71: https://doi.org/10.1016/j.foreco.2022.120142 | C71: Ministère des Forêts, de la Faune et des Parcs | D71: =VLOOKUP(A71,'Web_of_Science_20251015 '!A:E,5,0) -> 1 | E71: 1 | F71: 0 | G71: Jin | L71: =E71/D71 -> 1 | M71: =F71/D71 -> 0 | N71: =IFERROR(__xludf.DUMMYFUNCTION("INT(FILTER(GT(E71,0),ISNUMBER(E71)))"),1.0) -> 1 | O71: =E71/(E71+F71) -> 1 | P71: =IFERROR(__xludf.DUMMYFUNCTION("INT(FILTER(EQ(D71,E71),ISNUMBER(D71),ISNUMBER(E71)))"),1.0) -> 1
A72: A translational EEG-based approach to assess modulation of long-lasting NMDAR-dependent synaptic plasticity | B72: https://doi.org/10.1007/s00213-019-05341-w | C72: National Institutes of Health;National Institute of Mental Health | D72: =VLOOKUP(A72,'Web_of_Science_20251015 '!A:E,5,0) -> 2 | E72: 2 | F72: 0 | G72: Jin | L72: =E72/D72 -> 1 | M72: =F72/D72 -> 0 | N72: =IFERROR(__xludf.DUMMYFUNCTION("INT(FILTER(GT(E72,0),ISNUMBER(E72)))"),1.0) -> 1 | O72: =E72/(E72+F72) -> 1 | P72: =IFERROR(__xludf.DUMMYFUNCTION("INT(FILTER(EQ(D72,E72),ISNUMBER(D72),ISNUMBER(E72)))"),1.0) -> 1
A73: Repeated ethanol production from sweet sorghum juice concentrated by membrane separation | B73: https://doi.org/10.1016/j.biortech.2015.03.127 | C73: Ministry of Education, Culture, Sports, Science and Technology | D73: =VLOOKUP(A73,'Web_of_Science_20251015 '!A:E,5,0) -> 2 | E73: 1 | F73: 0 | G73: Jin | L73: =E73/D73 -> 0.5 | M73: =F73/D73 -> 0 | N73: =IFERROR(__xludf.DUMMYFUNCTION("INT(FILTER(GT(E73,0),ISNUMBER(E73)))"),1.0) -> 1 | O73: =E73/(E73+F73) -> 1 | P73: =IFERROR(__xludf.DUMMYFUNCTION("INT(FILTER(EQ(D73,E73),ISNUMBER(D73),ISNUMBER(E73)))"),0.0) -> 0
A74: High buffering capability of silicon-polymer photonic-crystal coupled cavity waveguide | B74: https://doi.org/10.1080/17455030.2021.1879406 | C74: National Natural Science Foundation of China | D74: =VLOOKUP(A74,'Web_of_Science_20251015 '!A:E,5,0) -> 3 | E74: 1 | F74: 0 | G74: Jin | L74: =E74/D74 -> 0.33333333 | M74: =F74/D74 -> 0 | N74: =IFERROR(__xludf.DUMMYFUNCTION("INT(FILTER(GT(E74,0),ISNUMBER(E74)))"),1.0) -> 1 | O74: =E74/(E74+F74) -> 1 | P74: =IFERROR(__xludf.DUMMYFUNCTION("INT(FILTER(EQ(D74,E74),ISNUMBER(D74),ISNUMBER(E74)))"),0.0) -> 0
A75: Cognitive-Behavioral Therapy Plus Hypnosis for Distress During Breast Radiotherapy: A Randomized Trial | B75: https://doi.org/10.1080/00029157.2017.1335635 | C75: National Center for Complementary and Integrative Health;National Cancer Institute | D75: =VLOOKUP(A75,'Web_of_Science_20251015 '!A:E,5,0) -> 2 | E75: 2 | F75: 0 | G75: Jin | L75: =E75/D75 -> 1 | M75: =F75/D75 -> 0 | N75: =IFERROR(__xludf.DUMMYFUNCTION("INT(FILTER(GT(E75,0),ISNUMBER(E75)))"),1.0) -> 1 | O75: =E75/(E75+F75) -> 1 | P75: =IFERROR(__xludf.DUMMYFUNCTION("INT(FILTER(EQ(D75,E75),ISNUMBER(D75),ISNUMBER(E75)))"),1.0) -> 1
A76: Arsenic and diabetes: Current perspectives | B76: https://doi.org/10.1016/j.kjms.2011.05.008 | C76: National Science Council | D76: =VLOOKUP(A76,'Web_of_Science_20251015 '!A:E,5,0) -> 3 | E76: 1 | F76: 0 | G76: Jin | L76: =E76/D76 -> 0.33333333 | M76: =F76/D76 -> 0 | N76: =IFERROR(__xludf.DUMMYFUNCTION("INT(FILTER(GT(E76,0),ISNUMBER(E76)))"),1.0) -> 1 | O76: =E76/(E76+F76) -> 1 | P76: =IFERROR(__xludf.DUMMYFUNCTION("INT(FILTER(EQ(D76,E76),ISNUMBER(D76),ISNUMBER(E76)))"),0.0) -> 0
A77: Impact of p53 and PDGFR-beta Expression on Metastasis and Prognosis of Patients with Pancreatic Cancer | B77: https://doi.org/10.1007/s00268-016-3477-2 | C77: Ministry of Health, Labour and Welfare | D77: =VLOOKUP(A77,'Web_of_Science_20251015 '!A:E,5,0) -> 2 | E77: 2 | F77: 0 | G77: Jin | L77: =E77/D77 -> 1 | M77: =F77/D77 -> 0 | N77: =IFERROR(__xludf.DUMMYFUNCTION("INT(FILTER(GT(E77,0),ISNUMBER(E77)))"),1.0) -> 1 | O77: =E77/(E77+F77) -> 1
A78: Nanostructured hydrophobic polyampholytes: self-assembly, stimuli-sensitivity, and application | B78: https://doi.org/10.1007/s42114-018-0059-9 | C78: American Chemical Society Petroleum Research Fund;Ministry of Education and Science of the Republic of Kazakhstan | D78: =VLOOKUP(A78,'Web_of_Science_20251015 '!A:E,5,0) -> 2 | E78: 2 | F78: 0 | G78: Jin | L78: =E78/D78 -> 1 | M78: =F78/D78 -> 0 | N78: =IFERROR(__xludf.DUMMYFUNCTION("INT(FILTER(GT(E78,0),ISNUMBER(E78)))"),1.0) -> 1 | O78: =E78/(E78+F78) -> 1 | P78: =IFERROR(__xludf.DUMMYFUNCTION("INT(FILTER(EQ(D78,E78),ISNUMBER(D78),ISNUMBER(E78)))"),1.0) -> 1
A79: LiBi3S5-A lithium bismuth sulfide with strong cation disorder | B79: https://doi.org/10.1016/j.jssc.2016.03.010 | C79: Deutsche Forschungsgemeinschaft | D79: =VLOOKUP(A79,'Web_of_Science_20251015 '!A:E,5,0) -> 3 | E79: 1 | F79: 0 | G79: Jin | L79: =E79/D79 -> 0.33333333 | M79: =F79/D79 -> 0 | N79: =IFERROR(__xludf.DUMMYFUNCTION("INT(FILTER(GT(E79,0),ISNUMBER(E79)))"),1.0) -> 1 | O79: =E79/(E79+F79) -> 1 | P79: =IFERROR(__xludf.DUMMYFUNCTION("INT(FILTER(EQ(D79,E79),ISNUMBER(D79),ISNUMBER(E79)))"),0.0) -> 0
A80: The role of Mn on twinning behavior and tensile properties of coarse- and fine-grained Fe-Mn-C twinning-induced plasticity steels | B80: https://doi.org/10.1016/j.msea.2020.139586 | C80: Natural Science Foundation of Hebei Province;National Natural Science Foundation of China | D80: =VLOOKUP(A80,'Web_of_Science_20251015 '!A:E,5,0) -> 2 | E80: 2 | F80: 0 | G80: Jin | L80: =E80/D80 -> 1 | M80: =F80/D80 -> 0 | N80: =IFERROR(__xludf.DUMMYFUNCTION("INT(FILTER(GT(E80,0),ISNUMBER(E80)))"),1.0) -> 1 | O80: =E80/(E80+F80) -> 1 | P80: =IFERROR(__xludf.DUMMYFUNCTION("INT(FILTER(EQ(D80,E80),ISNUMBER(D80),ISNUMBER(E80)))"),1.0) -> 1
A81: Forecasting Daily and Monthly Exchange Rates with Machine Learning Techniques | B81: https://doi.org/10.1002/for.2354 | C81: European Social Fund | D81: 2 | E81: 1 | F81: 0 | G81: Jin | L81: =E81/D81 -> 0.5 | M81: =F81/D81 -> 0 | N81: =IFERROR(__xludf.DUMMYFUNCTION("INT(FILTER(GT(E81,0),ISNUMBER(E81)))"),1.0) -> 1 | O81: =E81/(E81+F81) -> 1 | P81: =IFERROR(__xludf.DUMMYFUNCTION("INT(FILTER(EQ(D81,E81),ISNUMBER(D81),ISNUMBER(E81)))"),0.0) -> 0
A82: Green and facile procedure for the preparation of liquid and gel-like polyurethanes based on castor oil and lignin: Effect of processing conditions on the rheological properties | B82: https://doi.org/10.1016/j.jclepro.2020.123367 | C82: Ministerio de Educación, Cultura y Deporte;Federación Española de Enfermedades Raras;Académie de recherche et d'enseignement supérieur | D82: 2 | E82: 2 | F82: 1 | G82: Jin | L82: =E82/D82 -> 1 | M82: =F82/D82 -> 0.5 | N82: =IFERROR(__xludf.DUMMYFUNCTION("INT(FILTER(GT(E82,0),ISNUMBER(E82)))"),1.0) -> 1 | O82: =E82/(E82+F82) -> 0.66666667 | P82: =IFERROR(__xludf.DUMMYFUNCTION("INT(FILTER(EQ(D82,E82),ISNUMBER(D82),ISNUMBER(E82)))"),1.0) -> 1
A83: Delineation of Urban Growth Boundaries with SD and CLUE-s Models under Multi-Scenarios in Chengdu Metropolitan Area | B83: https://doi.org/10.3390/su11215919 | C83: National Natural Science Foundation of China-Yunnan Joint Fund | D83: 1 | E83: 0 | F83: 1 | G83: Jin | L83: =E83/D83 -> 0 | M83: =F83/D83 -> 1 | N83: =IFERROR(__xludf.DUMMYFUNCTION("INT(FILTER(GT(E83,0),ISNUMBER(E83)))"),0.0) -> 0 | O83: =E83/(E83+F83) -> 0 | P83: =IFERROR(__xludf.DUMMYFUNCTION("INT(FILTER(EQ(D83,E83),ISNUMBER(D83),ISNUMBER(E83)))"),0.0) -> 0
A84: Long non-coding RNA nuclear-enriched abundant transcript 1 inhibition blunts myocardial ischemia reperfusion injury via autophagic flux arrest and apoptosis in streptozotocin-induced diabetic rats | B84: https://doi.org/10.1016/j.atherosclerosis.2018.08.031 | C84: National Natural Science Foundation of China | D84: 2 | E84: 1 | F84: 0 | G84: Jin | L84: =E84/D84 -> 0.5 | M84: =F84/D84 -> 0 | N84: =IFERROR(__xludf.DUMMYFUNCTION("INT(FILTER(GT(E84,0),ISNUMBER(E84)))"),1.0) -> 1 | O84: =E84/(E84+F84) -> 1 | P84: =IFERROR(__xludf.DUMMYFUNCTION("INT(FILTER(EQ(D84,E84),ISNUMBER(D84),ISNUMBER(E84)))"),0.0) -> 0
A85: Swash saturation: an assessment of available models | B85: https://doi.org/10.1007/s10236-018-1170-8 | C85: Australian Research Council | D85: 2 | E85: 1 | F85: 0 | G85: Jin | L85: =E85/D85 -> 0.5 | M85: =F85/D85 -> 0 | N85: =IFERROR(__xludf.DUMMYFUNCTION("INT(FILTER(GT(E85,0),ISNUMBER(E85)))"),1.0) -> 1 | O85: =E85/(E85+F85) -> 1 | P85: =IFERROR(__xludf.DUMMYFUNCTION("INT(FILTER(EQ(D85,E85),ISNUMBER(D85),ISNUMBER(E85)))"),0.0) -> 0
A86: Specific gene expression profiles are associated with a pathologic complete response to neoadjuvant therapy in esophageal adenocarcinoma | B86: https://doi.org/10.1016/j.amjsurg.2017.03.024 | C86: National Center for Advancing Translational Sciences | D86: 4 | E86: 1 | F86: 0 | G86: Jin | L86: =E86/D86 -> 0.25 | M86: =F86/D86 -> 0 | N86: =IFERROR(__xludf.DUMMYFUNCTION("INT(FILTER(GT(E86,0),ISNUMBER(E86)))"),1.0) -> 1 | O86: =E86/(E86+F86) -> 1 | P86: =IFERROR(__xludf.DUMMYFUNCTION("INT(FILTER(EQ(D86,E86),ISNUMBER(D86),ISNUMBER(E86)))"),0.0) -> 0
A87: A systematic survey of randomised trials that stopped early for reasons of futility | B87: https://doi.org/10.1186/s12874-020-0899-1 | C87: Natural Sciences and Engineering Research Council of Canada | D87: 1 | E87: 1 | F87: 0 | G87: Jin | L87: =E87/D87 -> 1 | M87: =F87/D87 -> 0 | N87: =IFERROR(__xludf.DUMMYFUNCTION("INT(FILTER(GT(E87,0),ISNUMBER(E87)))"),1.0) -> 1 | O87: =E87/(E87+F87) -> 1 | P87: =IFERROR(__xludf.DUMMYFUNCTION("INT(FILTER(EQ(D87,E87),ISNUMBER(D87),ISNUMBER(E87)))"),1.0) -> 1
A88: Kinetic and regeneration studies of photocatalytic magnetic separable beads for chromium (VI) reduction under sunlight | B88: https://doi.org/10.1016/j.jhazmat.2010.11.101 | C88: Ministerio de Ciencia, Tecnología y Medio Ambiente | D88: 1 | E88: 1 | F88: 0 | G88: Jin | L88: =E88/D88 -> 1 | M88: =F88/D88 -> 0 | N88: =IFERROR(__xludf.DUMMYFUNCTION("INT(FILTER(GT(E88,0),ISNUMBER(E88)))"),1.0) -> 1 | O88: =E88/(E88+F88) -> 1
A89: Using regime analysis to identify the contribution of clouds to surface temperature errors in weather and climate models | B89: https://doi.org/10.1002/qj.2603 | C89: Met Office | D89: 1 | E89: 0 | F89: 1 | G89: Jin | L89: =E89/D89 -> 0 | M89: =F89/D89 -> 1 | N89: =IFERROR(__xludf.DUMMYFUNCTION("INT(FILTER(GT(E89,0),ISNUMBER(E89)))"),0.0) -> 0 | O89: =E89/(E89+F89) -> 0 | P89: =IFERROR(__xludf.DUMMYFUNCTION("INT(FILTER(EQ(D89,E89),ISNUMBER(D89),ISNUMBER(E89)))"),0.0) -> 0
A90: Diversifying growth forms in tropical forest restoration: Enrichment with vascular epiphytes | B90: https://doi.org/10.1016/j.foreco.2017.06.063 | C90: Conselho Nacional de Desenvolvimento Científico e Tecnológico;Fundação de Amparo à Pesquisa do Estado de São Paulo | D90: 2 | E90: 2 | F90: 0 | G90: Jin | L90: =E90/D90 -> 1 | M90: =F90/D90 -> 0 | N90: =IFERROR(__xludf.DUMMYFUNCTION("INT(FILTER(GT(E90,0),ISNUMBER(E90)))"),1.0) -> 1 | O90: =E90/(E90+F90) -> 1 | P90: =IFERROR(__xludf.DUMMYFUNCTION("INT(FILTER(EQ(D90,E90),ISNUMBER(D90),ISNUMBER(E90)))"),1.0) -> 1
A91: Relatedness of Cu and Fe speciation to chalcopyrite bioleaching by Acidithiobacillus ferrooxidans | B91: https://doi.org/10.1016/j.hydromet.2015.05.013 | C91: Hunan Provincial Innovation Foundation for Postgraduate;National Natural Science Foundation of China | D91: 4 | E91: 2 | F91: 0 | G91: Jin | L91: =E91/D91 -> 0.5 | M91: =F91/D91 -> 0 | N91: =IFERROR(__xludf.DUMMYFUNCTION("INT(FILTER(GT(E91,0),ISNUMBER(E91)))"),1.0) -> 1 | O91: =E91/(E91+F91) -> 1 | P91: =IFERROR(__xludf.DUMMYFUNCTION("INT(FILTER(EQ(D91,E91),ISNUMBER(D91),ISNUMBER(E91)))"),0.0) -> 0
A92: Precision orthotics: optimising ankle foot orthoses to improve gait in patients with neuromuscular diseases; protocol of the PROOF-AFO study, a prospective intervention study | B92: https://doi.org/10.1136/bmjopen-2016-013342 | C92: Prinses Beatrix Spierfonds | D92: 1 | E92: 1 | F92: 0 | G92: Jin | L92: =E92/D92 -> 1 | M92: =F92/D92 -> 0 | N92: =IFERROR(__xludf.DUMMYFUNCTION("INT(FILTER(GT(E92,0),ISNUMBER(E92)))"),1.0) -> 1 | O92: =E92/(E92+F92) -> 1 | P92: =IFERROR(__xludf.DUMMYFUNCTION("INT(FILTER(EQ(D92,E92),ISNUMBER(D92),ISNUMBER(E92)))"),1.0) -> 1
A93: Rock Mechanics Characteristics Test and Optimization of High-Efficiency Mining in Dajishan Tungsten Mine | B93: https://doi.org/10.1155/2018/8036540 | C93: National Natural Science Foundation of China | D93: 4 | E93: 1 | F93: 0 | G93: Jin | L93: =E93/D93 -> 0.25 | M93: =F93/D93 -> 0 | N93: =IFERROR(__xludf.DUMMYFUNCTION("INT(FILTER(GT(E93,0),ISNUMBER(E93)))"),1.0) -> 1 | O93: =E93/(E93+F93) -> 1 | P93: =IFERROR(__xludf.DUMMYFUNCTION("INT(FILTER(EQ(D93,E93),ISNUMBER(D93),ISNUMBER(E93)))"),0.0) -> 0
A94: miR-21 targets jnk and ccr7 to modulate the inflammatory response of grass carp following bacterial infection | B94: https://doi.org/10.1016/j.fsi.2019.09.022 | C94: China Agricultural Research System;National Natural Science Foundation of China | D94: 3 | E94: 2 | F94: 0 | G94: Jin | L94: =E94/D94 -> 0.66666667 | M94: =F94/D94 -> 0 | N94: =IFERROR(__xludf.DUMMYFUNCTION("INT(FILTER(GT(E94,0),ISNUMBER(E94)))"),1.0) -> 1 | O94: =E94/(E94+F94) -> 1 | P94: =IFERROR(__xludf.DUMMYFUNCTION("INT(FILTER(EQ(D94,E94),ISNUMBER(D94),ISNUMBER(E94)))"),0.0) -> 0
A95: Open-switch fault diagnosis in three-level rectifiers based on selective calculation method for instant voltage deviation | B95: https://doi.org/10.1049/pel2.12075 | C95: National Natural Science Foundation of China | D95: 3 | E95: 1 | F95: 0 | G95: Jin | L95: =E95/D95 -> 0.33333333 | M95: =F95/D95 -> 0 | N95: =IFERROR(__xludf.DUMMYFUNCTION("INT(FILTER(GT(E95,0),ISNUMBER(E95)))"),1.0) -> 1 | O95: =E95/(E95+F95) -> 1 | P95: =IFERROR(__xludf.DUMMYFUNCTION("INT(FILTER(EQ(D95,E95),ISNUMBER(D95),ISNUMBER(E95)))"),0.0) -> 0
A96: Detached-eddy and large-eddy simulations of wind effects on a high-rise structure | B96: https://doi.org/10.1016/j.compfluid.2017.02.009 | C96: National Natural Science Foundation of China | D96: 2 | E96: 1 | F96: 0 | G96: Jin | L96: =E96/D96 -> 0.5 | M96: =F96/D96 -> 0 | N96: =IFERROR(__xludf.DUMMYFUNCTION("INT(FILTER(GT(E96,0),ISNUMBER(E96)))"),1.0) -> 1 | O96: =E96/(E96+F96) -> 1 | P96: =IFERROR(__xludf.DUMMYFUNCTION("INT(FILTER(EQ(D96,E96),ISNUMBER(D96),ISNUMBER(E96)))"),0.0) -> 0
A97: SAS4P: Providing automatic smoking detection for a persuasive smoking cessation application | B97: https://doi.org/10.1177/1550147719888167 | C97: Fondo Nacional de Desarrollo Científico y Tecnológico | D97: 2 | E97: 1 | F97: 0 | G97: Jin | L97: =E97/D97 -> 0.5 | M97: =F97/D97 -> 0 | N97: =IFERROR(__xludf.DUMMYFUNCTION("INT(FILTER(GT(E97,0),ISNUMBER(E97)))"),1.0) -> 1 | O97: =E97/(E97+F97) -> 1 | P97: =IFERROR(__xludf.DUMMYFUNCTION("INT(FILTER(EQ(D97,E97),ISNUMBER(D97),ISNUMBER(E97)))"),0.0) -> 0
A98: Data-driven forecasting of high-dimensional chaotic systems with long short-term memory networks | B98: https://doi.org/10.1098/rspa.2017.0844 | C98: H2020 European Research Council;Office of Naval Research;Air Force Office of Scientific Research;Army Research Office | D98: 4 | E98: 4 | F98: 0 | G98: Jin | L98: =E98/D98 -> 1 | M98: =F98/D98 -> 0 | N98: =IFERROR(__xludf.DUMMYFUNCTION("INT(FILTER(GT(E98,0),ISNUMBER(E98)))"),1.0) -> 1 | O98: =E98/(E98+F98) -> 1 | P98: =IFERROR(__xludf.DUMMYFUNCTION("INT(FILTER(EQ(D98,E98),ISNUMBER(D98),ISNUMBER(E98)))"),1.0) -> 1
A99: Landscape evolution on the eastern part of Lombok (Indonesia) related to the 1257 CE eruption of the Samalas Volcano | B99: https://doi.org/10.1016/j.geomorph.2018.11.010 | C99: Australian Research Council;Centre National de la Recherche Scientifique | D99: 4 | E99: 2 | F99: 0 | G99: Jin | L99: =E99/D99 -> 0.5 | M99: =F99/D99 -> 0 | N99: =IFERROR(__xludf.DUMMYFUNCTION("INT(FILTER(GT(E99,0),ISNUMBER(E99)))"),1.0) -> 1 | O99: =E99/(E99+F99) -> 1
A100: CoCoA: conditional correlation models with association size | B100: https://doi.org/10.1093/biostatistics/kxac032 | C100: National Institutes of Health | D100: 1 | E100: 1 | F100: 0 | G100: Jin | L100: =E100/D100 -> 1 | M100: =F100/D100 -> 0 | N100: =IFERROR(__xludf.DUMMYFUNCTION("INT(FILTER(GT(E100,0),ISNUMBER(E100)))"),1.0) -> 1 | O100: =E100/(E100+F100) -> 1 | P100: =IFERROR(__xludf.DUMMYFUNCTION("INT(FILTER(EQ(D100,E100),ISNUMBER(D100),ISNUMBER(E100)))"),1.0) -> 1
...

Sheet Dimensions
A1: title | B1: DOI | C1: display_names | D1: WIKI_data_url | E1: Number of Funders Indicated by Paper | F1: Number of Correct Matches | G1: Number of Wrong Matches | H1: Coder | I1: Avg. Recall | J1: Avg error rate | K1: Hit rate | L1: Avg. Precision | M1: Paper level recall | N1: Paper level error rate | O1: Paper level hit rate | P1: Paper level precision | Q1: Paper is complete hit
A2: Enzymatic Hydrolysis of Softwood Derived Paper Sludge by an In Vitro Recombinant Cellulase Cocktail for the Production of Fermentable Sugars | B2: https://doi.org/10.3390/catal10070775 | C2: National Research Foundation;NRF||Department of Science and Innovation;Department of Science and Technology;DST;DSI | D2: https://en.wikipedia.org/wiki/Department_of_Science_and_Innovation||https://en.wikipedia.org/wiki/National_Research_Foundation_(South_Africa) | E2: =VLOOKUP(A2,'Web_of_Science_20251015 '!A:E,5,0) -> 4 | F2: 2 | G2: 0 | H2: Jacob | I2: =IFERROR(__xludf.DUMMYFUNCTION("AVERAGE(FILTER(M2:M100,ISNUMBER(M2:M100)))"),0.688876863876864) -> 0.68887686 | J2: =IFERROR(__xludf.DUMMYFUNCTION("AVERAGE(FILTER(N2:N100,ISNUMBER(N2:N100)))"),0.11683501683501682) -> 0.11683502 | K2: =IFERROR(__xludf.DUMMYFUNCTION("AVERAGE(FILTER(O2:O100,ISNUMBER(O2:O100)))"),0.9595959595959596) -> 0.95959596 | L2: =IFERROR(__xludf.DUMMYFUNCTION("AVERAGE(FILTER(P2:P100,ISNUMBER(P2:P100)))"),0.8882154882154882) -> 0.88821549 | M2: =F2/E2 -> 0.5 | N2: =G2/E2 -> 0 | O2: =IFERROR(__xludf.DUMMYFUNCTION("INT(FILTER(GT(F2,0),ISNUMBER(F2)))"),1.0) -> 1 | P2: =F2/(F2+G2) -> 1 | Q2: =IFERROR(__xludf.DUMMYFUNCTION("INT(FILTER(EQ(E2,F2),ISNUMBER(E2),ISNUMBER(F2)))"),0.0) -> 0
A3: IJCARS-IPCAI 2021 Special Issue: Information Processing for Computer-Assisted Interventions, 12th International Conference 2021-Part 1 | B3: https://doi.org/10.1007/s11548-021-02401-5 | C3: TU Darmstadt;Technical University of Darmstadt | D3: http://en.wikipedia.org/wiki/Technische_Universit%C3%A4t_Darmstadt | E3: =VLOOKUP(A3,'Web_of_Science_20251015 '!A:E,5,0) -> 1 | F3: 0 | G3: 1 | H3: Jacob | I3: Recall | J3: Error rate | K3: Complete hits | L3: Precision | M3: =F3/E3 -> 0 | N3: =G3/E3 -> 1 | O3: =IFERROR(__xludf.DUMMYFUNCTION("INT(FILTER(GT(F3,0),ISNUMBER(F3)))"),0.0) -> 0 | P3: =F3/(F3+G3) -> 0 | Q3: =IFERROR(__xludf.DUMMYFUNCTION("INT(FILTER(EQ(E3,F3),ISNUMBER(E3),ISNUMBER(F3)))"),0.0) -> 0
A4: Identification and partial characterization of a Salp15 homolog from Ixodes ricinus | B4: https://doi.org/10.1016/j.ttbdis.2013.12.004 | C4: European Commission;EC | D4: https://en.wikipedia.org/wiki/European_Commission | E4: =VLOOKUP(A4,'Web_of_Science_20251015 '!A:E,5,0) -> 1 | F4: 1 | G4: 0 | H4: Jacob | I4: =IFERROR(__xludf.DUMMYFUNCTION("SUM(FILTER(F2:F100,ISNUMBER(F2:F100)))/SUM(FILTER(E2:E100,ISNUMBER(F2:F100)))"),0.6068702290076335) -> 0.60687023 | J4: =IFERROR(__xludf.DUMMYFUNCTION("SUM(FILTER(G2:G100,ISNUMBER(G2:G100)))/SUM(FILTER(E2:E100,ISNUMBER(G2:G100)))"),0.08778625954198473) -> 0.08778626 | K4: =IFERROR(__xludf.DUMMYFUNCTION("AVERAGE(FILTER(Q2:Q100,ISNUMBER(Q2:Q100)))"),0.48148148148148145) -> 0.48148148 | L4: =IFERROR(__xludf.DUMMYFUNCTION("SUM(FILTER(F2:F100,ISNUMBER(F2:F100)))/(SUM(FILTER(F2:F100,ISNUMBER(F2:F100)))+SUM(FILTER(G2:G100,ISNUMBER(F2:F100))))"),0.8736263736263736) -> 0.87362637 | M4: =F4/E4 -> 1 | N4: =G4/E4 -> 0 | O4: =IFERROR(__xludf.DUMMYFUNCTION("INT(FILTER(GT(F4,0),ISNUMBER(F4)))"),1.0) -> 1 | P4: =F4/(F4+G4) -> 1 | Q4: =IFERROR(__xludf.DUMMYFUNCTION("INT(FILTER(EQ(E4,F4),ISNUMBER(E4),ISNUMBER(F4)))"),1.0) -> 1
A5: Constructing mentally ill inmates: nurses' discursive practices in corrections | B5: https://doi.org/10.1111/j.1440-1800.2011.00526.x | C5: Canadian Institutes of Health Research;CIHR | D5: http://en.wikipedia.org/wiki/Canadian_Institutes_of_Health_Research | E5: =VLOOKUP(A5,'Web_of_Science_20251015 '!A:E,5,0) -> 1 | F5: 1 | G5: 0 | H5: Jacob | M5: =F5/E5 -> 1 | N5: =G5/E5 -> 0 | O5: =IFERROR(__xludf.DUMMYFUNCTION("INT(FILTER(GT(F5,0),ISNUMBER(F5)))"),1.0) -> 1 | P5: =F5/(F5+G5) -> 1 | Q5: =IFERROR(__xludf.DUMMYFUNCTION("INT(FILTER(EQ(E5,F5),ISNUMBER(E5),ISNUMBER(F5)))"),1.0) -> 1
A6: An in vivo study on bone formation behavior of microporous granular calcium phosphate | B6: https://doi.org/10.1039/c7bm00162b | C6: Ministry of Economy, Industry and Competitiveness;MINECO||Coordenação de Aperfeicoamento de Pessoal de Nível Superior;CAPES | D6: https://en.wikipedia.org/wiki/Coordena%C3%A7%C3%A3o_de_Aperfeicoamento_de_Pessoal_de_N%C3%ADvel_Superior||https://en.wikipedia.org/wiki/Ministry_of_Economy_and_Enterprise | E6: =VLOOKUP(A6,'Web_of_Science_20251015 '!A:E,5,0) -> 2 | F6: 2 | G6: 0 | H6: Jacob | M6: =F6/E6 -> 1 | N6: =G6/E6 -> 0 | O6: =IFERROR(__xludf.DUMMYFUNCTION("INT(FILTER(GT(F6,0),ISNUMBER(F6)))"),1.0) -> 1 | P6: =F6/(F6+G6) -> 1 | Q6: =IFERROR(__xludf.DUMMYFUNCTION("INT(FILTER(EQ(E6,F6),ISNUMBER(E6),ISNUMBER(F6)))"),1.0) -> 1
A7: Self-directedly assembled porphyrin thin films with high photoactivity | B7: https://doi.org/10.1039/c5ra17015j | C7: National Natural Science Foundation of China;NSFC||Shanghai Municipal Education Commission;SHMEC | D7: https://en.wikipedia.org/wiki/National_Natural_Science_Foundation_of_China|| | E7: =VLOOKUP(A7,'Web_of_Science_20251015 '!A:E,5,0) -> 2 | F7: 2 | G7: 0 | H7: Jacob | M7: =F7/E7 -> 1 | N7: =G7/E7 -> 0 | O7: =IFERROR(__xludf.DUMMYFUNCTION("INT(FILTER(GT(F7,0),ISNUMBER(F7)))"),1.0) -> 1 | P7: =F7/(F7+G7) -> 1 | Q7: =IFERROR(__xludf.DUMMYFUNCTION("INT(FILTER(EQ(E7,F7),ISNUMBER(E7),ISNUMBER(F7)))"),1.0) -> 1
A8: STRUCTURAL ELUCIDATION OF A NEUTRAL WATER-SOLUBLE a-D-GLUCAN FROM THE FUNGUS OF HERICIUM ERINACEUS | B8: https://doi.org/10.1111/j.1745-4514.2010.00492.x | C8: National Natural Science Foundation of China;NSFC | D8: https://en.wikipedia.org/wiki/National_Natural_Science_Foundation_of_China | E8: =VLOOKUP(A8,'Web_of_Science_20251015 '!A:E,5,0) -> 2 | F8: 0 | G8: 1 | H8: Jacob | M8: =F8/E8 -> 0 | N8: =G8/E8 -> 0.5 | O8: =IFERROR(__xludf.DUMMYFUNCTION("INT(FILTER(GT(F8,0),ISNUMBER(F8)))"),0.0) -> 0 | P8: =F8/(F8+G8) -> 0 | Q8: =IFERROR(__xludf.DUMMYFUNCTION("INT(FILTER(EQ(E8,F8),ISNUMBER(E8),ISNUMBER(F8)))"),0.0) -> 0
A9: Localization of Free and Bound Metal Species through X-Ray Synchrotron Fluorescence Microscopy in the Rodent Brain and Their Relation to Behavior | B9: https://doi.org/10.3390/brainsci9040074 | C9: Office of Basic Energy Sciences;BES||Society for Neuroscience;SfN | D9: ||https://en.wikipedia.org/wiki/Society_for_Neuroscience | E9: =VLOOKUP(A9,'Web_of_Science_20251015 '!A:E,5,0) -> 1 | F9: 1 | G9: 1 | H9: Jacob | M9: =F9/E9 -> 1 | N9: =G9/E9 -> 1 | O9: =IFERROR(__xludf.DUMMYFUNCTION("INT(FILTER(GT(F9,0),ISNUMBER(F9)))"),1.0) -> 1 | P9: =F9/(F9+G9) -> 0.5 | Q9: =IFERROR(__xludf.DUMMYFUNCTION("INT(FILTER(EQ(E9,F9),ISNUMBER(E9),ISNUMBER(F9)))"),1.0) -> 1
A10: Establishment, Persistence, and Reactivation of Latent HIV-1 Infection in Renal Epithelial Cells | B10: https://doi.org/10.1128/jvi.00624-22 | C10: National Institute of Diabetes and Digestive and Kidney Diseases;NIDDK | D10: https://en.wikipedia.org/wiki/National_Institute_of_Diabetes_and_Digestive_and_Kidney_Diseases | E10: =VLOOKUP(A10,'Web_of_Science_20251015 '!A:E,5,0) -> 1 | F10: 1 | G10: 0 | H10: Jacob | M10: =F10/E10 -> 1 | N10: =G10/E10 -> 0 | O10: =IFERROR(__xludf.DUMMYFUNCTION("INT(FILTER(GT(F10,0),ISNUMBER(F10)))"),1.0) -> 1 | P10: =F10/(F10+G10) -> 1 | Q10: =IFERROR(__xludf.DUMMYFUNCTION("INT(FILTER(EQ(E10,F10),ISNUMBER(E10),ISNUMBER(F10)))"),1.0) -> 1
A11: Parallel ddRAD and Genome Skimming Analyses Reveal a Radiative and Reticulate Evolutionary History of the Temperate Bamboos | B11: https://doi.org/10.1093/sysbio/syaa076 | C11: National Natural Science Foundation of China;NSFC||Chinese Academy of Sciences;CAS | D11: https://en.wikipedia.org/wiki/National_Natural_Science_Foundation_of_China||http://en.wikipedia.org/wiki/Chinese_Academy_of_Sciences | E11: =VLOOKUP(A11,'Web_of_Science_20251015 '!A:E,5,0) -> 4 | F11: 2 | G11: 0 | H11: Jacob | M11: =F11/E11 -> 0.5 | N11: =G11/E11 -> 0 | O11: =IFERROR(__xludf.DUMMYFUNCTION("INT(FILTER(GT(F11,0),ISNUMBER(F11)))"),1.0) -> 1 | P11: =F11/(F11+G11) -> 1
A12: Synthesis of 2-Vinylbenzofurans via the Copper-Catalyzed Multicomponent Reactions Involving an Oxa-Michael/Arylation/Vinylation Cascade | B12: https://doi.org/10.1021/ol502506g | C12: National Natural Science Foundation of China;NSFC | D12: https://en.wikipedia.org/wiki/National_Natural_Science_Foundation_of_China | E12: =VLOOKUP(A12,'Web_of_Science_20251015 '!A:E,5,0) -> 2 | F12: 1 | G12: 0 | H12: Jacob | M12: =F12/E12 -> 0.5 | N12: =G12/E12 -> 0 | O12: =IFERROR(__xludf.DUMMYFUNCTION("INT(FILTER(GT(F12,0),ISNUMBER(F12)))"),1.0) -> 1 | P12: =F12/(F12+G12) -> 1 | Q12: =IFERROR(__xludf.DUMMYFUNCTION("INT(FILTER(EQ(E12,F12),ISNUMBER(E12),ISNUMBER(F12)))"),0.0) -> 0
A13: Nrf2 augments skeletal muscle regeneration after ischaemia-reperfusion injury | B13: https://doi.org/10.1002/path.4418 | C13: Deutsche Forschungsgemeinschaft;DFG | D13: http://en.wikipedia.org/wiki/Deutsche_Forschungsgemeinschaft | E13: =VLOOKUP(A13,'Web_of_Science_20251015 '!A:E,5,0) -> 3 | F13: 1 | G13: 0 | H13: Jacob | M13: =F13/E13 -> 0.33333333 | N13: =G13/E13 -> 0 | O13: =IFERROR(__xludf.DUMMYFUNCTION("INT(FILTER(GT(F13,0),ISNUMBER(F13)))"),1.0) -> 1 | P13: =F13/(F13+G13) -> 1 | Q13: =IFERROR(__xludf.DUMMYFUNCTION("INT(FILTER(EQ(E13,F13),ISNUMBER(E13),ISNUMBER(F13)))"),0.0) -> 0
A14: Characterizing Serpinb2 as a Modulator of TCDD-Induced Suppression of the B Cell | B14: https://doi.org/10.1021/acs.chemrestox.8b00225 | C14: National Institute of Food and Agriculture;NIFA||National Institute of Environmental Health Sciences;NIEHS | D14: http://en.wikipedia.org/wiki/National_Institute_of_Environmental_Health_Sciences||https://en.wikipedia.org/wiki/National_Institute_of_Food_and_Agriculture | E14: =VLOOKUP(A14,'Web_of_Science_20251015 '!A:E,5,0) -> 2 | F14: 1 | G14: 1 | H14: Jacob | M14: =F14/E14 -> 0.5 | N14: =G14/E14 -> 0.5 | O14: =IFERROR(__xludf.DUMMYFUNCTION("INT(FILTER(GT(F14,0),ISNUMBER(F14)))"),1.0) -> 1 | P14: =F14/(F14+G14) -> 0.5 | Q14: =IFERROR(__xludf.DUMMYFUNCTION("INT(FILTER(EQ(E14,F14),ISNUMBER(E14),ISNUMBER(F14)))"),0.0) -> 0
A15: Targeting vulnerable households in urban Burkina Faso: effectiveness of geographical criteria but not of proxy-means testing | B15: https://doi.org/10.1093/heapol/czv104 | C15: Institut de Recherche pour le Développement;IRD | D15: https://en.wikipedia.org/wiki/Institut_de_recherche_pour_le_d%C3%A9veloppement | E15: =VLOOKUP(A15,'Web_of_Science_20251015 '!A:E,5,0) -> 2 | F15: 1 | G15: 0 | H15: Jacob | M15: =F15/E15 -> 0.5 | N15: =G15/E15 -> 0 | O15: =IFERROR(__xludf.DUMMYFUNCTION("INT(FILTER(GT(F15,0),ISNUMBER(F15)))"),1.0) -> 1 | P15: =F15/(F15+G15) -> 1 | Q15: =IFERROR(__xludf.DUMMYFUNCTION("INT(FILTER(EQ(E15,F15),ISNUMBER(E15),ISNUMBER(F15)))"),0.0) -> 0
A16: Crash responses under multiple impacts and residual properties of CFRP and aluminum tubes | B16: https://doi.org/10.1016/j.compstruct.2018.04.001 | C16: China Postdoctoral Science Foundation||National Natural Science Foundation of China;NSFC | D16: ||https://en.wikipedia.org/wiki/National_Natural_Science_Foundation_of_China | E16: =VLOOKUP(A16,'Web_of_Science_20251015 '!A:E,5,0) -> 6 | F16: 2 | G16: 0 | H16: Jacob | M16: =F16/E16 -> 0.33333333 | N16: =G16/E16 -> 0 | O16: =IFERROR(__xludf.DUMMYFUNCTION("INT(FILTER(GT(F16,0),ISNUMBER(F16)))"),1.0) -> 1 | P16: =F16/(F16+G16) -> 1 | Q16: =IFERROR(__xludf.DUMMYFUNCTION("INT(FILTER(EQ(E16,F16),ISNUMBER(E16),ISNUMBER(F16)))"),0.0) -> 0
A17: Inactivation of a pathogenic NDM-1-positive Escherichia coli strain and the resistance gene bla(NDM-1) by TiO2/UVA photocatalysis | B17: https://doi.org/10.1016/j.scitotenv.2022.157369 | C17: National Natural Science Foundation of China;NSFC||Jiangsu Provincial Department of Education | D17: https://en.wikipedia.org/wiki/National_Natural_Science_Foundation_of_China|| | E17: =VLOOKUP(A17,'Web_of_Science_20251015 '!A:E,5,0) -> 3 | F17: 2 | G17: 0 | H17: Jacob | M17: =F17/E17 -> 0.66666667 | N17: =G17/E17 -> 0 | O17: =IFERROR(__xludf.DUMMYFUNCTION("INT(FILTER(GT(F17,0),ISNUMBER(F17)))"),1.0) -> 1 | P17: =F17/(F17+G17) -> 1 | Q17: =IFERROR(__xludf.DUMMYFUNCTION("INT(FILTER(EQ(E17,F17),ISNUMBER(E17),ISNUMBER(F17)))"),0.0) -> 0
A18: Comparison of phase-shifting techniques for in vivo full-range, high-speed Fourier-domain optical coherence tomography | B18: https://doi.org/10.1117/1.3494556 | C18: Research to Prevent Blindness;RPB||National Eye Institute;NEI | D18: https://en.wikipedia.org/wiki/Research_to_Prevent_Blindness||https://en.wikipedia.org/wiki/National_Eye_Institute | E18: =VLOOKUP(A18,'Web_of_Science_20251015 '!A:E,5,0) -> 2 | F18: 2 | G18: 0 | H18: Jacob | M18: =F18/E18 -> 1 | N18: =G18/E18 -> 0 | O18: =IFERROR(__xludf.DUMMYFUNCTION("INT(FILTER(GT(F18,0),ISNUMBER(F18)))"),1.0) -> 1 | P18: =F18/(F18+G18) -> 1 | Q18: =IFERROR(__xludf.DUMMYFUNCTION("INT(FILTER(EQ(E18,F18),ISNUMBER(E18),ISNUMBER(F18)))"),1.0) -> 1
A19: Inhibitory Effects of Garcinia cambogia Extract on CYP2B6 Enzyme Activity | B19: https://doi.org/10.1055/s-0043-104934 | C19: National Research Foundation of Korea;NRF||Japan Society for the Promotion of Science;Nihon Gakujutsu Shinkō Kai;JSPS | D19: https://en.wikipedia.org/wiki/National_Research_Foundation_of_Korea||http://en.wikipedia.org/wiki/Japan_Society_for_the_Promotion_of_Science | E19: =VLOOKUP(A19,'Web_of_Science_20251015 '!A:E,5,0) -> 2 | F19: 2 | G19: 0 | H19: Jacob | M19: =F19/E19 -> 1 | N19: =G19/E19 -> 0 | O19: =IFERROR(__xludf.DUMMYFUNCTION("INT(FILTER(GT(F19,0),ISNUMBER(F19)))"),1.0) -> 1 | P19: =F19/(F19+G19) -> 1 | Q19: =IFERROR(__xludf.DUMMYFUNCTION("INT(FILTER(EQ(E19,F19),ISNUMBER(E19),ISNUMBER(F19)))"),1.0) -> 1
A20: Preparation of platinum- and silver-incorporated TiO2 coatings in thin-film photoreactor for the photocatalytic decomposition of o-cresol | B20: https://doi.org/10.1080/09593330.2011.556670 | C20: National Science and Technology Council;National Science Council;Ministry of Science and Technology;MOST;NSC | D20: https://en.wikipedia.org/wiki/Ministry_of_Science_and_Technology_(Taiwan) | E20: =VLOOKUP(A20,'Web_of_Science_20251015 '!A:E,5,0) -> 1 | F20: 1 | G20: 0 | H20: Jacob | M20: =F20/E20 -> 1 | N20: =G20/E20 -> 0 | O20: =IFERROR(__xludf.DUMMYFUNCTION("INT(FILTER(GT(F20,0),ISNUMBER(F20)))"),1.0) -> 1 | P20: =F20/(F20+G20) -> 1 | Q20: =IFERROR(__xludf.DUMMYFUNCTION("INT(FILTER(EQ(E20,F20),ISNUMBER(E20),ISNUMBER(F20)))"),1.0) -> 1
A21: Nitrogen Dioxide Sensing Using Multilayer Structure of Reduced Graphene Oxide and alpha-Fe2O3 | B21: https://doi.org/10.3390/s21031011 | C21: National Science Center;Narodowe Centrum Nauki;NCN | D21: https://en.wikipedia.org/wiki/The_National_Science_Centre_(Poland) | E21: =VLOOKUP(A21,'Web_of_Science_20251015 '!A:E,5,0) -> 1 | F21: 1 | G21: 0 | H21: Jacob | M21: =F21/E21 -> 1 | N21: =G21/E21 -> 0 | O21: =IFERROR(__xludf.DUMMYFUNCTION("INT(FILTER(GT(F21,0),ISNUMBER(F21)))"),1.0) -> 1 | P21: =F21/(F21+G21) -> 1 | Q21: =IFERROR(__xludf.DUMMYFUNCTION("INT(FILTER(EQ(E21,F21),ISNUMBER(E21),ISNUMBER(F21)))"),1.0) -> 1
A22: Infestation of Lithodes santolla (Decapoda: Lithodidae) by Pseudione tuberculata (Isopoda: Bopyridae) in San Jorge Gulf, Southwestern Atlantic Ocean | B22: https://doi.org/10.1080/17451000903478327 | C22: National Scientific and Technical Research Council;CONICET | D22: https://en.wikipedia.org/wiki/National_Scientific_and_Technical_Research_Council | E22: =VLOOKUP(A22,'Web_of_Science_20251015 '!A:E,5,0) -> 1 | F22: 1 | G22: 0 | H22: Jacob | M22: =F22/E22 -> 1 | N22: =G22/E22 -> 0 | O22: =IFERROR(__xludf.DUMMYFUNCTION("INT(FILTER(GT(F22,0),ISNUMBER(F22)))"),1.0) -> 1 | P22: =F22/(F22+G22) -> 1
A23: A novel lateral shearing interferometer and its anti-vibration characteristic for on-machine precision surface measurement | B23: https://doi.org/10.1016/j.ijleo.2016.03.064 | C23: National Natural Science Foundation of China;NSFC||Ministry of Education of the People's Republic of China;Ministry of Education Central People's Government;State Education Commission;MOE | D23: https://en.wikipedia.org/wiki/National_Natural_Science_Foundation_of_China||http://en.wikipedia.org/wiki/Ministry_of_Education_of_the_People's_Republic_of_China | E23: =VLOOKUP(A23,'Web_of_Science_20251015 '!A:E,5,0) -> 3 | F23: 2 | G23: 0 | H23: Jacob | M23: =F23/E23 -> 0.66666667 | N23: =G23/E23 -> 0 | O23: =IFERROR(__xludf.DUMMYFUNCTION("INT(FILTER(GT(F23,0),ISNUMBER(F23)))"),1.0) -> 1 | P23: =F23/(F23+G23) -> 1 | Q23: =IFERROR(__xludf.DUMMYFUNCTION("INT(FILTER(EQ(E23,F23),ISNUMBER(E23),ISNUMBER(F23)))"),0.0) -> 0
A24: Development of antimigraine transdermal delivery systems of pizotifen malate | B24: https://doi.org/10.1016/j.ijpharm.2015.07.033 | C24: Instituto de Salud Carlos III;Carlos III Health Institute;ISCIII | D24: https://en.wikipedia.org/wiki/Carlos_III_Health_Institute | E24: =VLOOKUP(A24,'Web_of_Science_20251015 '!A:E,5,0) -> 2 | F24: 1 | G24: 0 | H24: Jacob | M24: =F24/E24 -> 0.5 | N24: =G24/E24 -> 0 | O24: =IFERROR(__xludf.DUMMYFUNCTION("INT(FILTER(GT(F24,0),ISNUMBER(F24)))"),1.0) -> 1 | P24: =F24/(F24+G24) -> 1 | Q24: =IFERROR(__xludf.DUMMYFUNCTION("INT(FILTER(EQ(E24,F24),ISNUMBER(E24),ISNUMBER(F24)))"),0.0) -> 0
A25: Elasmobranch capture by commercial small-scale fisheries in the Bijagos Archipelago, Guinea Bissau | B25: https://doi.org/10.1016/j.fishres.2015.03.018 | C25: Economic and Social Research Council;Social Science Research Council;ESRC||Parkes Foundation||Natural Environment Research Council;NERC||Zoological Society of London;ZSL||Fellowship Fund Inc;FFI | D25: http://en.wikipedia.org/wiki/Natural_Environment_Research_Council||http://en.wikipedia.org/wiki/Zoological_Society_of_London||https://en.wikipedia.org/wiki/Economic_and_Social_Research_Council|| | E25: =VLOOKUP(A25,'Web_of_Science_20251015 '!A:E,5,0) -> 4 | F25: 3 | G25: 2 | H25: Jacob | M25: =F25/E25 -> 0.75 | N25: =G25/E25 -> 0.5 | O25: =IFERROR(__xludf.DUMMYFUNCTION("INT(FILTER(GT(F25,0),ISNUMBER(F25)))"),1.0) -> 1 | P25: =F25/(F25+G25) -> 0.6 | Q25: =IFERROR(__xludf.DUMMYFUNCTION("INT(FILTER(EQ(E25,F25),ISNUMBER(E25),ISNUMBER(F25)))"),0.0) -> 0
A26: Mechanisms of Se(IV) Co-precipitation with Ferrihydrite at Acidic and Alkaline Conditions and Its Behavior during Aging | B26: https://doi.org/10.1021/acs.est.8b00462 | C26: Japan Atomic Energy Agency;JAEA||Japan Society for the Promotion of Science;Nihon Gakujutsu Shinkō Kai;JSPS||RIKEN;Institute of Physical and Chemical Research | D26: http://en.wikipedia.org/wiki/Japan_Society_for_the_Promotion_of_Science||http://en.wikipedia.org/wiki/RIKEN||https://en.wikipedia.org/wiki/Japan_Atomic_Energy_Agency | E26: =VLOOKUP(A26,'Web_of_Science_20251015 '!A:E,5,0) -> 3 | F26: 1 | G26: 2 | H26: Jacob | M26: =F26/E26 -> 0.33333333 | N26: =G26/E26 -> 0.66666667 | O26: =IFERROR(__xludf.DUMMYFUNCTION("INT(FILTER(GT(F26,0),ISNUMBER(F26)))"),1.0) -> 1 | P26: =F26/(F26+G26) -> 0.33333333 | Q26: =IFERROR(__xludf.DUMMYFUNCTION("INT(FILTER(EQ(E26,F26),ISNUMBER(E26),ISNUMBER(F26)))"),0.0) -> 0
A27: Neural activity, neural connectivity, and the processing of emotionally valenced information in older adults: links with life satisfaction | B27: https://doi.org/10.3758/s13415-011-0039-9 | C27: National Institute on Aging;NIA | D27: https://en.wikipedia.org/wiki/National_Institute_on_Aging | E27: =VLOOKUP(A27,'Web_of_Science_20251015 '!A:E,5,0) -> 1 | F27: 1 | G27: 0 | H27: Jacob | M27: =F27/E27 -> 1 | N27: =G27/E27 -> 0 | O27: =IFERROR(__xludf.DUMMYFUNCTION("INT(FILTER(GT(F27,0),ISNUMBER(F27)))"),1.0) -> 1 | P27: =F27/(F27+G27) -> 1 | Q27: =IFERROR(__xludf.DUMMYFUNCTION("INT(FILTER(EQ(E27,F27),ISNUMBER(E27),ISNUMBER(F27)))"),1.0) -> 1
A28: On the Non-trivial Origin of Atomic-Scale Patterns in Friction Force Microscopy | B28: https://doi.org/10.1007/s11249-018-1127-6 | C28: Dutch Research Council;Netherlands Organisation for Scientific Research;NWO||European Research Council;ERC | D28: https://en.wikipedia.org/wiki/Dutch_Research_Council||https://en.wikipedia.org/wiki/European_Research_Council | E28: =VLOOKUP(A28,'Web_of_Science_20251015 '!A:E,5,0) -> 2 | F28: 2 | G28: 0 | H28: Jacob | M28: =F28/E28 -> 1 | N28: =G28/E28 -> 0 | O28: =IFERROR(__xludf.DUMMYFUNCTION("INT(FILTER(GT(F28,0),ISNUMBER(F28)))"),1.0) -> 1 | P28: =F28/(F28+G28) -> 1 | Q28: =IFERROR(__xludf.DUMMYFUNCTION("INT(FILTER(EQ(E28,F28),ISNUMBER(E28),ISNUMBER(F28)))"),1.0) -> 1
A29: Multicoil Shimming of the Mouse Brain | B29: https://doi.org/10.1002/mrm.22850 | C29: National Cancer Institute;NCI||National Institute of Biomedical Imaging and Bioengineering;NIBIB||National Institute of Neurological Disorders and Stroke;NINDS | D29: https://en.wikipedia.org/wiki/National_Institute_of_Biomedical_Imaging_and_Bioengineering||https://en.wikipedia.org/wiki/National_Institute_of_Neurological_Disorders_and_Stroke||https://en.wikipedia.org/wiki/National_Cancer_Institute | E29: =VLOOKUP(A29,'Web_of_Science_20251015 '!A:E,5,0) -> 4 | F29: 4 | G29: 0 | H29: Jacob | M29: =F29/E29 -> 1 | N29: =G29/E29 -> 0 | O29: =IFERROR(__xludf.DUMMYFUNCTION("INT(FILTER(GT(F29,0),ISNUMBER(F29)))"),1.0) -> 1 | P29: =F29/(F29+G29) -> 1 | Q29: =IFERROR(__xludf.DUMMYFUNCTION("INT(FILTER(EQ(E29,F29),ISNUMBER(E29),ISNUMBER(F29)))"),1.0) -> 1
A30: The Suggestion of Revised Criteria for Endoscopic Resection of Differentiated-Type Submucosal Gastric Cancer | B30: https://doi.org/10.1245/s10434-019-08102-3 | C30: National Research Foundation of Korea;NRF | D30: https://en.wikipedia.org/wiki/National_Research_Foundation_of_Korea | E30: =VLOOKUP(A30,'Web_of_Science_20251015 '!A:E,5,0) -> 2 | F30: 1 | G30: 0 | H30: Jacob | M30: =F30/E30 -> 0.5 | N30: =G30/E30 -> 0 | O30: =IFERROR(__xludf.DUMMYFUNCTION("INT(FILTER(GT(F30,0),ISNUMBER(F30)))"),1.0) -> 1 | P30: =F30/(F30+G30) -> 1 | Q30: =IFERROR(__xludf.DUMMYFUNCTION("INT(FILTER(EQ(E30,F30),ISNUMBER(E30),ISNUMBER(F30)))"),0.0) -> 0
A31: Professional identity research in the health professions-a scoping review | B31: https://doi.org/10.1007/s10459-022-10171-1 | C31: Australian Government;Government of Australia;Government of the Commonwealth of Australia | D31: https://en.wikipedia.org/wiki/Government_of_Australia | E31: =VLOOKUP(A31,'Web_of_Science_20251015 '!A:E,5,0) -> 2 | F31: 1 | G31: 0 | H31: Jacob | M31: =F31/E31 -> 0.5 | N31: =G31/E31 -> 0 | O31: =IF(ISNUMBER(F31), INT(F31>0), "") -> 1 | P31: =F31/(F31+G31) -> 1
A32: Parental Life Span and Polygenic Risk Score of Longevity Are Associated With White Matter Hyperintensities | B32: https://doi.org/10.1093/gerona/glab323 | C32: National Health and Medical Research Council;NHMRC||National Computational Infrastructure;NCI Australia;NCI||Medical Research Council;MRC | D32: https://en.wikipedia.org/wiki/National_Health_and_Medical_Research_Council||http://en.wikipedia.org/wiki/Medical_Research_Council_%28United_Kingdom%29||https://en.wikipedia.org/wiki/National_Computational_Infrastructure | E32: =VLOOKUP(A32,'Web_of_Science_20251015 '!A:E,5,0) -> 2 | F32: 2 | G32: 1 | H32: Jacob | M32: =F32/E32 -> 1 | N32: =G32/E32 -> 0.5 | O32: =IF(ISNUMBER(F32), INT(F32>0), "") -> 1 | P32: =F32/(F32+G32) -> 0.66666667
A33: Developing Concentration Index of Industrial and Occupational Accidents: The Case of European Countries | B33: https://doi.org/10.1016/j.shaw.2020.05.003 | C33: Ministry of Education;MOE||National Research Foundation of Korea;NRF | D33: https://en.wikipedia.org/wiki/Ministry_of_Education_(South_Korea)||https://en.wikipedia.org/wiki/National_Research_Foundation_of_Korea | E33: =VLOOKUP(A33,'Web_of_Science_20251015 '!A:E,5,0) -> 2 | F33: 2 | G33: 0 | H33: Jacob | M33: =F33/E33 -> 1 | N33: =G33/E33 -> 0 | O33: =IF(ISNUMBER(F33), INT(F33>0), "") -> 1 | P33: =F33/(F33+G33) -> 1
A34: Bifurcation Phenomena of Nonlinear Waves in a Generalized Zakharov-Kuznetsov Equation | B34: https://doi.org/10.1155/2013/812120 | C34: National Natural Science Foundation of China;NSFC | D34: https://en.wikipedia.org/wiki/National_Natural_Science_Foundation_of_China | E34: =VLOOKUP(A34,'Web_of_Science_20251015 '!A:E,5,0) -> 2 | F34: 1 | G34: 0 | H34: Jacob | M34: =F34/E34 -> 0.5 | N34: =G34/E34 -> 0 | O34: =IF(ISNUMBER(F34), INT(F34>0), "") -> 1 | P34: =F34/(F34+G34) -> 1
A35: Gall size of Dryocosmus kuriphilus limits down-regulation by native parasitoids | B35: https://doi.org/10.1007/s10530-020-02427-x | C35: Ministry of Economy, Industry and Competitiveness;MINECO | D35: https://en.wikipedia.org/wiki/Ministry_of_Economy_and_Enterprise | E35: =VLOOKUP(A35,'Web_of_Science_20251015 '!A:E,5,0) -> 1 | F35: 1 | G35: 0 | H35: Jacob | M35: =F35/E35 -> 1 | N35: =G35/E35 -> 0 | O35: =IF(ISNUMBER(F35), INT(F35>0), "") -> 1 | P35: =F35/(F35+G35) -> 1
A36: A multiplex serologic platform for diagnosis of tick-borne diseases | B36: https://doi.org/10.1038/s41598-018-21349-2 | C36: National Institute of Allergy and Infectious Diseases;NIAID | D36: https://en.wikipedia.org/wiki/National_Institute_of_Allergy_and_Infectious_Diseases | E36: =VLOOKUP(A36,'Web_of_Science_20251015 '!A:E,5,0) -> 3 | F36: 1 | G36: 0 | H36: Jacob | M36: =F36/E36 -> 0.33333333 | N36: =G36/E36 -> 0 | O36: =IF(ISNUMBER(F36), INT(F36>0), "") -> 1 | P36: =F36/(F36+G36) -> 1
A37: Coordinated energy management for an islanded microgrid with multi-energy and multi-storage units | B37: https://doi.org/10.1016/j.egyr.2021.11.131 | C37: National Natural Science Foundation of China;NSFC | D37: https://en.wikipedia.org/wiki/National_Natural_Science_Foundation_of_China | E37: =VLOOKUP(A37,'Web_of_Science_20251015 '!A:E,5,0) -> 1 | F37: 1 | G37: 0 | H37: Jacob | M37: =F37/E37 -> 1 | N37: =G37/E37 -> 0 | O37: =IF(ISNUMBER(F37), INT(F37>0), "") -> 1 | P37: =F37/(F37+G37) -> 1
A38: Dynamic Characteristics Analysis of ISD Suspension System under Different Working Conditions | B38: https://doi.org/10.3390/math9121345 | C38: National Natural Science Foundation of China;NSFC | D38: https://en.wikipedia.org/wiki/National_Natural_Science_Foundation_of_China | E38: =VLOOKUP(A38,'Web_of_Science_20251015 '!A:E,5,0) -> 2 | F38: 1 | G38: 0 | H38: Jacob | M38: =F38/E38 -> 0.5 | N38: =G38/E38 -> 0 | O38: =IF(ISNUMBER(F38), INT(F38>0), "") -> 1 | P38: =F38/(F38+G38) -> 1
A39: Effects of Prunella vulgaris on the Mice Immune Function | B39: https://doi.org/10.1371/journal.pone.0077355 | C39: National Institute on Alcohol Abuse and Alcoholism;NIAAA||National Natural Science Foundation of China;NSFC||Ministry of Science and Technology of the People's Republic of China;State Science and Technology Commission;MOST||Guangdong Science and Technology Department | D39: ||https://en.wikipedia.org/wiki/Ministry_of_Science_and_Technology_of_the_People%27s_Republic_of_China||https://en.wikipedia.org/wiki/National_Institute_on_Alcohol_Abuse_and_Alcoholism||https://en.wikipedia.org/wiki/National_Natural_Science_Foundation_of_China | E39: =VLOOKUP(A39,'Web_of_Science_20251015 '!A:E,5,0) -> 4 | F39: 1 | G39: 1 | H39: Jacob | M39: =F39/E39 -> 0.25 | N39: =G39/E39 -> 0.25 | O39: =IF(ISNUMBER(F39), INT(F39>0), "") -> 1 | P39: =F39/(F39+G39) -> 0.5
A40: Dynamic covalent chemistry constrained diphenylethenes: control over reactivity and luminescence both in solution and in the solid state | B40: https://doi.org/10.1039/d2qo00057a | C40: Fujian Institute of Research on the Structure of Matter;FJIRSM||National Natural Science Foundation of China;NSFC||Chinese Academy of Sciences;CAS | D40: http://en.wikipedia.org/wiki/Chinese_Academy_of_Sciences||https://en.wikipedia.org/wiki/National_Natural_Science_Foundation_of_China|| | E40: =VLOOKUP(A40,'Web_of_Science_20251015 '!A:E,5,0) -> 5 | F40: 3 | G40: 0 | H40: Jacob | M40: =F40/E40 -> 0.6 | N40: =G40/E40 -> 0 | O40: =IF(ISNUMBER(F40), INT(F40>0), "") -> 1 | P40: =F40/(F40+G40) -> 1
A41: Dynamic changes in positive interferon-gamma release assay in a dialysis population: An observational cohort study | B41: https://doi.org/10.1016/j.jinf.2013.07.029 | C41: Ministry of Health and Welfare;Wèishēng Shǔ;Department of Health;Zhōnghuá Mínguó Wèishēng Fúlì Bù;DOH;MOHW||National Taiwan University Hospital;Guólì Táiwān Dàxué Yīxuéyuàn Fùshè Yīyuàn;NTUH||National Science and Technology Council;National Science Council;Ministry of Science and Technology;MOST;NSC | D41: https://en.wikipedia.org/wiki/National_Taiwan_University_Hospital||https://en.wikipedia.org/wiki/Ministry_of_Science_and_Technology_(Taiwan)||https://en.wikipedia.org/wiki/Ministry_of_Health_and_Welfare_(Taiwan) | E41: =VLOOKUP(A41,'Web_of_Science_20251015 '!A:E,5,0) -> 3 | F41: 2 | G41: 1 | H41: Jacob | M41: =F41/E41 -> 0.66666667 | N41: =G41/E41 -> 0.33333333 | O41: =IF(ISNUMBER(F41), INT(F41>0), "") -> 1 | P41: =F41/(F41+G41) -> 0.66666667
A42: Cystathionine beta-synthase is required for body iron homeostasis | B42: https://doi.org/10.1002/hep.29499 | C42: Ministry of Science and Technology of the People's Republic of China;State Science and Technology Commission;MOST||National Natural Science Foundation of China;NSFC||University Grants Committee;UGC | D42: https://en.wikipedia.org/wiki/National_Natural_Science_Foundation_of_China||https://en.wikipedia.org/wiki/Ministry_of_Science_and_Technology_of_the_People%27s_Republic_of_China||https://en.wikipedia.org/wiki/University_Grants_Committee_(Hong_Kong) | E42: =VLOOKUP(A42,'Web_of_Science_20251015 '!A:E,5,0) -> 3 | F42: 2 | G42: 1 | H42: Jacob | M42: =F42/E42 -> 0.66666667 | N42: =G42/E42 -> 0.33333333 | O42: =IF(ISNUMBER(F42), INT(F42>0), "") -> 1 | P42: =F42/(F42+G42) -> 0.66666667
... A64: Shunt capacitor placement in radial distribution networks considering switching transients decision making approach | B64: https://doi.org/10.1016/j.ijepes.2017.05.001 | C64: European Commission;EC||Fundação para a Ciência e Tecnologia;FCT | D64: https://en.wikipedia.org/wiki/Funda%C3%A7%C3%A3o_para_a_Ci%C3%AAncia_e_Tecnologia||https://en.wikipedia.org/wiki/European_Commission | E64: =VLOOKUP(A64,'Web_of_Science_20251015 '!A:E,5,0) -> 3 | F64: 2 | G64: 0 | H64: Jin | M64: =F64/E64 -> 0.66666667 | N64: =G64/E64 -> 0 | O64: =IF(ISNUMBER(F64), INT(F64>0), "") -> 1 | P64: =F64/(F64+G64) -> 1
A65: Analysis of ligamentary atomization of highly perturbed liquid sheets | B65: https://doi.org/10.1016/j.ijmultiphaseflow.2018.05.027 | C65: Direction Générale des Entreprises;Direction générale de la compétitivité, de l'industrie et des services;DGE | E65: =VLOOKUP(A65,'Web_of_Science_20251015 '!A:E,5,0) -> 1 | F65: 1 | G65: 0 | H65: Jin | M65: =F65/E65 -> 1 | N65: =G65/E65 -> 0 | O65: =IF(ISNUMBER(F65), INT(F65>0), "") -> 1 | P65: =F65/(F65+G65) -> 1
A66: Effects of deposition temperature on structure and properties of (K0.48Na0.52)NbO3 ferroelectric thin films by pulsed laser deposition | B66: https://doi.org/10.1063/1.4823852 | C66: Ministry of Education of the People's Republic of China;Ministry of Education Central People's Government;State Education Commission;MOE||Ministry of Science and Technology of the People's Republic of China;State Science and Technology Commission;MOST||National Natural Science Foundation of China;NSFC | D66: http://en.wikipedia.org/wiki/Ministry_of_Education_of_the_People's_Republic_of_China||https://en.wikipedia.org/wiki/Ministry_of_Science_and_Technology_of_the_People%27s_Republic_of_China||https://en.wikipedia.org/wiki/National_Natural_Science_Foundation_of_China | E66: =VLOOKUP(A66,'Web_of_Science_20251015 '!A:E,5,0) -> 4 | F66: 3 | G66: 0 | H66: Jin | M66: =F66/E66 -> 0.75 | N66: =G66/E66 -> 0 | O66: =IF(ISNUMBER(F66), INT(F66>0), "") -> 1 | P66: =F66/(F66+G66) -> 1
A67: Concise Review: Geminin-A Tale of Two Tails: DNA Replication and Transcriptional/Epigenetic Regulation in Stem Cells | B67: https://doi.org/10.1002/stem.2529 | C67: European Research Council;ERC | D67: https://en.wikipedia.org/wiki/European_Research_Council | E67: =VLOOKUP(A67,'Web_of_Science_20251015 '!A:E,5,0) -> 4 | F67: 1 | G67: 0 | H67: Jin | M67: =F67/E67 -> 0.25 | N67: =G67/E67 -> 0 | O67: =IF(ISNUMBER(F67), INT(F67>0), "") -> 1 | P67: =F67/(F67+G67) -> 1
A68: Electrical fingerprinting, 3D profiling and detection of tumor cells with solid-state micropores | B68: https://doi.org/10.1039/c2lc21012f | C68: Directorate for Engineering;NSF ENG | E68: =VLOOKUP(A68,'Web_of_Science_20251015 '!A:E,5,0) -> 3 | F68: 1 | G68: 0 | H68: Jin | M68: =F68/E68 -> 0.33333333 | N68: =G68/E68 -> 0 | O68: =IF(ISNUMBER(F68), INT(F68>0), "") -> 1 | P68: =F68/(F68+G68) -> 1
A69: Twist1 expression induced by sunitinib accelerates tumor cell vasculogenic mimicry by increasing the population of CD133(+) cells in triple-negative breast cancer | B69: https://doi.org/10.1186/1476-4598-13-207 | C69: Ministry of Science and Technology of the People's Republic of China;State Science and Technology Commission;MOST||Ministry of Education of the People's Republic of China;Ministry of Education Central People's Government;State Education Commission;MOE||National Natural Science Foundation of China;NSFC | D69: https://en.wikipedia.org/wiki/Ministry_of_Science_and_Technology_of_the_People%27s_Republic_of_China||https://en.wikipedia.org/wiki/National_Natural_Science_Foundation_of_China||http://en.wikipedia.org/wiki/Ministry_of_Education_of_the_People's_Republic_of_China | E69: =VLOOKUP(A69,'Web_of_Science_20251015 '!A:E,5,0) -> 4 | F69: 3 | G69: 0 | H69: Jin | M69: =F69/E69 -> 0.75 | N69: =G69/E69 -> 0 | O69: =IF(ISNUMBER(F69), INT(F69>0), "") -> 1 | P69: =F69/(F69+G69) -> 1
A70: Assessing species occurrence and species-specific use patterns of bais (forest clearings) in Central Africa with camera traps | B70: https://doi.org/10.1111/aje.12084 | C70: Wildlife Conservation Society;New York Zoological Society;WCS;NYZS||Idea Wild||Rufford Foundation;Rufford Maurice Laing Foundation||German Academic Exchange Service;DAAD | D70: https://en.wikipedia.org/wiki/Rufford_Foundation||||https://en.wikipedia.org/wiki/Wildlife_Conservation_Society||https://en.wikipedia.org/wiki/German_Academic_Exchange_Service | E70: =VLOOKUP(A70,'Web_of_Science_20251015 '!A:E,5,0) -> 4 | F70: 3 | G70: 1 | H70: Jin | M70: =F70/E70 -> 0.75 | N70: =G70/E70 -> 0.25 | O70: =IF(ISNUMBER(F70), INT(F70>0), "") -> 1 | P70: =F70/(F70+G70) -> 0.75
A71: Three-dimensional imaging of cavity vacuum with single atoms localized by a nanohole array | B71: https://doi.org/10.1038/ncomms4441 | C71: National Research Foundation of Korea;NRF||National Institute of Biomedical Imaging and Bioengineering;NIBIB | D71: https://en.wikipedia.org/wiki/National_Institute_of_Biomedical_Imaging_and_Bioengineering||https://en.wikipedia.org/wiki/National_Research_Foundation_of_Korea | E71: =VLOOKUP(A71,'Web_of_Science_20251015 '!A:E,5,0) -> 1 | F71: 1 | G71: 1 | H71: Jin | M71: =F71/E71 -> 1 | N71: =G71/E71 -> 1 | O71: =IF(ISNUMBER(F71), INT(F71>0), "") -> 1 | P71: =F71/(F71+G71) -> 0.5
A72: Proteomics and Phosphoproteomics Profiling of Drug-Addicted BRAFi-Resistant Melanoma Cells | B72: https://doi.org/10.1021/acs.jproteome.1c00331 | C72: China Scholarship Council;CSC||Dutch Research Council;Netherlands Organisation for Scientific Research;NWO | D72: https://en.wikipedia.org/wiki/China_Scholarship_Council||https://en.wikipedia.org/wiki/Dutch_Research_Council | E72: =VLOOKUP(A72,'Web_of_Science_20251015 '!A:E,5,0) -> 2 | F72: 2 | G72: 0 | H72: Jin | M72: =F72/E72 -> 1 | N72: =G72/E72 -> 0 | O72: =IF(ISNUMBER(F72), INT(F72>0), "") -> 1 | P72: =F72/(F72+G72) -> 1
A73: A multi-class SVM approach based on the l(1)-norm minimization of the distances between the reduced convex hulls | B73: https://doi.org/10.1016/j.patcog.2014.12.006 | C73: Agencia Nacional de Investigación y Desarrollo;ANID | E73: =VLOOKUP(A73,'Web_of_Science_20251015 '!A:E,5,0) -> 2 | F73: 1 | G73: 0 | H73: Jin | M73: =F73/E73 -> 0.5 | N73: =G73/E73 -> 0 | O73: =IF(ISNUMBER(F73), INT(F73>0), "") -> 1 | P73: =F73/(F73+G73) -> 1
A74: Oxidative Dissolution of Arsenic-Bearing Sulfide Minerals inGroundwater: Impact of Hydrochemical and HydrodynamicConditions on Arsenic Release and Surface Evolution | B74: https://doi.org/10.1021/acs.est.2c00309 | C74: Danish Agency for Science and Higher Education||The Velux Foundations;Villum Fonden;Villum Foundation;Villum Kann Rasmussen Foundation | E74: =VLOOKUP(A74,'Web_of_Science_20251015 '!A:E,5,0) -> 2 | F74: 2 | G74: 0 | H74: Jin | M74: =F74/E74 -> 1 | N74: =G74/E74 -> 0 | O74: =IF(ISNUMBER(F74), INT(F74>0), "") -> 1 | P74: =F74/(F74+G74) -> 1
A75: An Optimization of Oregano, Thyme, and Lemongrass Essential Oil Blend to Simultaneous Inactivation of Relevant Foodborne Pathogens by Simplex-Centroid Mixture Design | B75: https://doi.org/10.3390/antibiotics11111572 | C75: National Council for Scientific and Technological Development;Conselho Nacional de Pesquisa;CNPq||Coordenação de Aperfeicoamento de Pessoal de Nível Superior;CAPES||Fundação Carlos Chagas Filho de Amparo à Pesquisa do Estado do Rio de Janeiro;FAPERJ | D75: ||https://en.wikipedia.org/wiki/Coordena%C3%A7%C3%A3o_de_Aperfeicoamento_de_Pessoal_de_N%C3%ADvel_Superior||https://en.wikipedia.org/wiki/National_Council_for_Scientific_and_Technological_Development | E75: =VLOOKUP(A75,'Web_of_Science_20251015 '!A:E,5,0) -> 3 | F75: 3 | G75: 0 | H75: Jin | M75: =F75/E75 -> 1 | N75: =G75/E75 -> 0 | O75: =IF(ISNUMBER(F75), INT(F75>0), "") -> 1 | P75: =F75/(F75+G75) -> 1
A76: Uncovering steroidopathy in women with autism: a latent class analysis | B76: https://doi.org/10.1186/2040-2392-5-27 | C76: National Institute for Health and Care Research;National Institute for Health Research;NIHR||Wellcome Trust;WT||Medical Research Council;MRC | D76: http://en.wikipedia.org/wiki/Medical_Research_Council_%28United_Kingdom%29||https://en.wikipedia.org/wiki/National_Institute_for_Health_and_Care_Research||http://en.wikipedia.org/wiki/Wellcome_Trust | E76: =VLOOKUP(A76,'Web_of_Science_20251015 '!A:E,5,0) -> 4 | F76: 2 | G76: 1 | H76: Jin | M76: =F76/E76 -> 0.5 | N76: =G76/E76 -> 0.25 | O76: =IF(ISNUMBER(F76), INT(F76>0), "") -> 1 | P76: =F76/(F76+G76) -> 0.66666667
A77: Metabolomics: A Primer | B77: https://doi.org/10.1016/j.tibs.2017.01.004 | C77: National Cancer Institute;NCI | D77: https://en.wikipedia.org/wiki/National_Cancer_Institute | E77: =VLOOKUP(A77,'Web_of_Science_20251015 '!A:E,5,0) -> 1 | F77: 1 | G77: 0 | H77: Jin | M77: =F77/E77 -> 1 | N77: =G77/E77 -> 0 | O77: =IF(ISNUMBER(F77), INT(F77>0), "") -> 1 | P77: =F77/(F77+G77) -> 1
A78: Classification Method and Determination of Mountainous Area Types at Township Scales: A Case Study of Yuxi City, Yunnan Province | B78: https://doi.org/10.1155/2020/3484568 | C78: National Natural Science Foundation of China;NSFC | D78: https://en.wikipedia.org/wiki/National_Natural_Science_Foundation_of_China | E78: =VLOOKUP(A78,'Web_of_Science_20251015 '!A:E,5,0) -> 3 | F78: 1 | G78: 0 | H78: Jin | M78: =F78/E78 -> 0.33333333 | N78: =G78/E78 -> 0 | O78: =IF(ISNUMBER(F78), INT(F78>0), "") -> 1 | P78: =F78/(F78+G78) -> 1
A79: Relationship between Helmholtz-resonance absorption and panel-type absorption in finite flexible microperforated-panel absorbers | B79: https://doi.org/10.1016/j.apacoust.2009.10.007 | C79: Ministry of Education, Culture, Sports, Science and Technology;Monbu-kagaku-shō;MEXT | D79: https://en.wikipedia.org/wiki/Ministry_of_Education,_Culture,_Sports,_Science_and_Technology | E79: =VLOOKUP(A79,'Web_of_Science_20251015 '!A:E,5,0) -> 1 | F79: 1 | G79: 0 | H79: Jin | M79: =F79/E79 -> 1 | N79: =G79/E79 -> 0 | O79: =IF(ISNUMBER(F79), INT(F79>0), "") -> 1 | P79: =F79/(F79+G79) -> 1
A80: Hydrogel from Acellular Porcine Adipose Tissue Accelerates Wound Healing by Inducing Intradermal Adipocyte Regeneration | B80: https://doi.org/10.1016/j.jid.2018.08.013 | C80: Ministry of Science and Technology of the People's Republic of China;State Science and Technology Commission;MOST | D80: https://en.wikipedia.org/wiki/Ministry_of_Science_and_Technology_of_the_People%27s_Republic_of_China | E80: =VLOOKUP(A80,'Web_of_Science_20251015 '!A:E,5,0) -> 2 | F80: 1 | G80: 0 | H80: Jin | M80: =F80/E80 -> 0.5 | N80: =G80/E80 -> 0 | O80: =IF(ISNUMBER(F80), INT(F80>0), "") -> 1 | P80: =F80/(F80+G80) -> 1
A81: Oxaliplatin induces hypomyelination and reduced neuregulin 1 expression in the rat sciatic nerve | B81: https://doi.org/10.1016/j.neures.2014.02.004 | C81: Japan Society for the Promotion of Science;Nihon Gakujutsu Shinkō Kai;JSPS||Nakatomi Foundation | D81: http://en.wikipedia.org/wiki/Japan_Society_for_the_Promotion_of_Science|| | E81: =VLOOKUP(A81,'Web_of_Science_20251015 '!A:E,5,0) -> 2 | F81: 2 | G81: 0 | H81: Jin | M81: =F81/E81 -> 1 | N81: =G81/E81 -> 0 | O81: =IF(ISNUMBER(F81), INT(F81>0), "") -> 1 | P81: =F81/(F81+G81) -> 1
A82: A new twist for Stork-Danheiser products enabled by visible light mediated trans-cyclohexene formation; access to acyclic distal enones | B82: https://doi.org/10.1039/d1sc03774a | C82: Directorate for Computer & Information Science & Engineering;NSF CISE||National Institute of General Medical Sciences;NIGMS||American Chemical Society;ACS||National Science Foundation;NSF | D82: ||https://en.wikipedia.org/wiki/National_Institute_of_General_Medical_Sciences||https://en.wikipedia.org/wiki/National_Science_Foundation||https://en.wikipedia.org/wiki/American_Chemical_Society | E82: =VLOOKUP(A82,'Web_of_Science_20251015 '!A:E,5,0) -> 4 | F82: 3 | G82: 0 | H82: Jin | M82: =F82/E82 -> 0.75 | N82: =G82/E82 -> 0 | O82: =IF(ISNUMBER(F82), INT(F82>0), "") -> 1 | P82: =F82/(F82+G82) -> 1
A83: Comparative genome sequencing to assess the genetic diversity and virulence attributes of 15 Vibrio anguillarum isolates | B83: https://doi.org/10.1111/jfd.12290 | C83: European Commission;EC||Research Foundation - Flanders;FWO | D83: https://en.wikipedia.org/wiki/Research_Foundation_-_Flanders_(FWO)||https://en.wikipedia.org/wiki/European_Commission | E83: =VLOOKUP(A83,'Web_of_Science_20251015 '!A:E,5,0) -> 3 | F83: 1 | G83: 1 | H83: Jin | M83: =F83/E83 -> 0.33333333 | N83: =G83/E83 -> 0.33333333 | O83: =IF(ISNUMBER(F83), INT(F83>0), "") -> 1 | P83: =F83/(F83+G83) -> 0.5
